Workbook

Sheet HOME
C3: LUSAKA OAKTREE SCHOOL
G6: LUSAKA OAKTREE SCHOOL
H8: School management system
C16: ALEVEL | E16: ASLEVEL | G16: IGCSE 1 | I16: LS3A | J16: LS3B | L16: LS2A | M16: LS2B | N16: LS1B | P16: LS1A F
C18: A LEVEL REPORT CARD | G18: LS3 A REPORT CARD | J18: LS1 A REPORT CARD F
C20: AS LEVEL REPORT CARD | G20: LS3 B REPORT CARD | J20: LS1 B REPORT CARD
D22: IGCSE 2 REPORT CARD | G22: LS2 A REPORT CARD
C24: IGCSE 1 REPORT CARD | G24: LS2 B REPORT CARD

Sheet Overall Analysis
D2: SECONDARY RESULTS ANALYSIS
B5: LS1 A
B6: ENGLISH | C6: MATHEMATICS | D6: SCIENCE | E6: SOCIAL STUDIES | F6: NEW COMPUTING | G6: BUSINESS STUDIES | H6: FRENCH | I6: ART | J6: MDD | K6: PE
A7: Average | B7: =LS1A!E36 -> 63.375 | C7: =LS1A!I36 -> 46.458333 | D7: =LS1A!M36 -> 53.208333 | E7: =LS1A!Q36 -> 67.666667 | F7: =LS1A!U36 -> 65.291667 | G7: =LS1A!Y36 -> 63.375 | H7: =LS1A!AC36 -> 61.333333 | I7: =LS1A!AG36 -> 73.625 | J7: =LS1A!AK36 -> 76.333333 | K7: =LS1A!AO36 -> 66.941667
A8: NO. Students | B8: =LS1A!E37 -> 24 | C8: =LS1A!I37 -> 24 | D8: =LS1A!M37 -> 24 | E8: =LS1A!Q37 -> 24 | F8: =LS1A!U37 -> 24 | G8: =LS1A!Y37 -> 24 | H8: =LS1A!AC37 -> 24 | I8: =LS1A!AG37 -> 24 | J8: =LS1A!AK37 -> 24 | K8: =LS1A!AO37 -> 24
A9: Pass | B9: =LS1A!E38 -> 21 | C9: =LS1A!I38 -> 12 | D9: =LS1A!M38 -> 11 | E9: =LS1A!Q38 -> 21 | F9: =LS1A!U38 -> 22 | G9: =LS1A!Y38 -> 21 | H9: =LS1A!AC38 -> 15 | I9: =LS1A!AG38 -> 24 | J9: =LS1A!AK38 -> 24 | K9: =LS1A!AO38 -> 22
A10: Fail | B10: =LS1A!E39 -> 3 | C10: =LS1A!I39 -> 12 | D10: =LS1A!M39 -> 13 | E10: =LS1A!Q39 -> 3 | F10: =LS1A!U39 -> 2 | G10: =LS1A!Y39 -> 3 | H10: =LS1A!AC39 -> 9 | I10: =LS1A!AG39 -> 0 | J10: =LS1A!AK39 -> 0 | K10: =LS1A!AO39 -> 2
A11: Pass Rate % | B11: =LS1A!E40 -> 87.5 | C11: =LS1A!I40 -> 50 | D11: =LS1A!M40 -> 45.833333 | E11: =LS1A!Q40 -> 87.5 | F11: =LS1A!U40 -> 91.666667 | G11: =LS1A!Y40 -> 87.5 | H11: =LS1A!AC40 -> 62.5 | I11: =LS1A!AG40 -> 100 | J11: =LS1A!AK40 -> 100 | K11: =LS1A!AO40 -> 91.666667
B14: LS1 B
B15: ENGLISH | C15: MATHEMATICS | D15: SCIENCE | E15: SOCIAL STUDIES | F15: NEW COMPUTING | G15: BUSINESS STUDIES | H15: FRENCH | I15: ART | J15: MDD | K15: PE
A16: Average | B16: =LS1B!E35 -> 65.962963 | C16: =LS1B!I35 -> 52.555556 | D16: =LS1B!M35 -> 58.937037 | E16: =LS1B!Q35 -> 61.666667 | F16: =LS1B!U35 -> 68.777778 | G16: =LS1B!Y35 -> 70.888889 | H16: =LS1B!AC35 -> 70.076923 | I16: =LS1B!AG35 -> 75.740741 | J16: =LS1B!AK35 -> 68.814815 | K16: =LS1B!AO35 -> 66.862963
A17: NO. Students | B17: =LS1B!E36 -> 27 | C17: =LS1B!I36 -> 27 | D17: =LS1B!M36 -> 27 | E17: =LS1B!Q36 -> 27 | F17: =LS1B!U36 -> 27 | G17: =LS1B!Y36 -> 27 | H17: =LS1B!AC36 -> 26 | I17: =LS1B!AG36 -> 27 | J17: =LS1B!AK36 -> 27 | K17: =LS1B!AO36 -> 27
A18: Pass | B18: =LS1B!E37 -> 26 | C18: =LS1B!I37 -> 17 | D18: =LS1B!M37 -> 19 | E18: =LS1B!Q37 -> 23 | F18: =LS1B!U37 -> 26 | G18: =LS1B!Y37 -> 26 | H18: =LS1B!AC37 -> 21 | I18: =LS1B!AG37 -> 27 | J18: =LS1B!AK37 -> 24 | K18: =LS1B!AO37 -> 27
A19: Fail | B19: =LS1B!E38 -> 1 | C19: =LS1B!I38 -> 10 | D19: =LS1B!M38 -> 8 | E19: =LS1B!Q38 -> 4 | F19: =LS1B!U38 -> 1 | G19: =LS1B!Y38 -> 1 | H19: =LS1B!AC38 -> 5 | I19: =LS1B!AG38 -> 0 | J19: =LS1B!AK38 -> 3 | K19: =LS1B!AO38 -> 0
A20: Pass Rate % | B20: =LS1B!E39 -> 96.296296 | C20: =LS1B!I39 -> 62.962963 | D20: =LS1B!M39 -> 70.37037 | E20: =LS1B!Q39 -> 85.185185 | F20: =LS1B!U39 -> 96.296296 | G20: =LS1B!Y39 -> 96.296296 | H20: =LS1B!AC39 -> 80.769231 | I20: =LS1B!AG39 -> 100 | J20: =LS1B!AK39 -> 88.888889 | K20: =LS1B!AO39 -> 100
B23: LS2 A
B24: ENGLISH | C24: MATHEMATICS | D24: SCIENCE | E24: SOCIAL STUDIES | F24: NEW COMPUTING | G24: BUSINESS STUDIES | H24: FRENCH | I24: ART | J24: MDD | K24: PE
A25: Average | B25: =LS2A!E34 -> 50.48 | C25: =LS2A!I34 -> 53.52 | D25: =LS2A!M34 -> 61.48 | E25: =LS2A!Q34 -> 63.48 | F25: =LS2A!U34 -> 69.56 | G25: =LS2A!Y34 -> 71.24 | H25: =LS2A!AC34 -> 61.8 | I25: =LS2A!AG34 -> 68.48 | J25: =LS2A!AK34 -> 71.68 | K25: =LS2A!AO34 -> 67.744
A26: NO. Students | B26: =LS2A!E35 -> 25 | C26: =LS2A!I35 -> 25 | D26: =LS2A!M35 -> 25 | E26: =LS2A!Q35 -> 25 | F26: =LS2A!U35 -> 25 | G26: =LS2A!Y35 -> 25 | H26: =LS2A!AC35 -> 25 | I26: =LS2A!AG35 -> 25 | J26: =LS2A!AK35 -> 25 | K26: =LS2A!AO35 -> 25
A27: Pass | B27: =LS2A!E36 -> 17 | C27: =LS2A!I36 -> 15 | D27: =LS2A!M36 -> 21 | E27: =LS2A!Q36 -> 21 | F27: =LS2A!U36 -> 22 | G27: =LS2A!Y36 -> 22 | H27: =LS2A!AC36 -> 21 | I27: =LS2A!AG36 -> 23 | J27: =LS2A!AK36 -> 23 | K27: =LS2A!AO36 -> 24
A28: Fail | B28: =LS2A!E37 -> 8 | C28: =LS2A!I37 -> 10 | D28: =LS2A!M37 -> 4 | E28: =LS2A!Q37 -> 4 | F28: =LS2A!U37 -> 3 | G28: =LS2A!Y37 -> 3 | H28: =LS2A!AC37 -> 4 | I28: =LS2A!AG37 -> 2 | J28: =LS2A!AK37 -> 2 | K28: =LS2A!AO37 -> 1
A29: Pass Rate % | B29: =LS2A!E38 -> 68 | C29: =LS2A!I38 -> 60 | D29: =LS2A!M38 -> 84 | E29: =LS2A!Q38 -> 84 | F29: =LS2A!U38 -> 88 | G29: =LS2A!Y38 -> 88 | H29: =LS2A!AC38 -> 84 | I29: =LS2A!AG38 -> 92 | J29: =LS2A!AK38 -> 92 | K29: =LS2A!AO38 -> 96
B32: LS2 B
B33: ENGLISH | C33: MATHEMATICS | D33: SCIENCE | E33: SOCIAL STUDIES | F33: NEW COMPUTING | G33: BUSINESS STUDIES | H33: FRENCH | I33: ART | J33: MDD | K33: PE
A34: Average | B34: =LS2B!E30 -> 57.5 | C34: =LS2B!I30 -> 64.833333 | D34: =LS2B!M30 -> 69.555556 | E34: =LS2B!Q30 -> 71.944444 | F34: =LS2B!U30 -> 86 | G34: =LS2B!Y30 -> 78.722222 | H34: =LS2B!AC30 -> 73.055556 | I34: =LS2B!AG30 -> 74.666667 | J34: =LS2B!AK30 -> 71.666667 | K34: =LS2B!AO30 -> 71.527778
A35: NO. Students | B35: =LS2B!E31 -> 18 | C35: =LS2B!I31 -> 18 | D35: =LS2B!M31 -> 18 | E35: =LS2B!Q31 -> 18 | F35: =LS2B!U31 -> 18 | G35: =LS2B!Y31 -> 18 | H35: =LS2B!AC31 -> 18 | I35: =LS2B!AG31 -> 18 | J35: =LS2B!AK31 -> 18 | K35: =LS2B!AO31 -> 18
A36: Pass | B36: =LS2B!E32 -> 16 | C36: =LS2B!I32 -> 16 | D36: =LS2B!M32 -> 16 | E36: =LS2B!Q32 -> 17 | F36: =LS2B!U32 -> 17 | G36: =LS2B!Y32 -> 17 | H36: =LS2B!AC32 -> 17 | I36: =LS2B!AG32 -> 18 | J36: =LS2B!AK32 -> 18 | K36: =LS2B!AO32 -> 18
A37: Fail | B37: =LS2B!E33 -> 2 | C37: =LS2B!I33 -> 2 | D37: =LS2B!M33 -> 2 | E37: =LS2B!Q33 -> 1 | F37: =LS2B!U33 -> 1 | G37: =LS2B!Y33 -> 1 | H37: =LS2B!AC33 -> 1 | I37: =LS2B!AG33 -> 0 | J37: =LS2B!AK33 -> 0 | K37: =LS2B!AO33 -> 0
A38: Pass Rate % | B38: =LS2B!E34 -> 88.888889 | C38: =LS2B!I34 -> 88.888889 | D38: =LS2B!M34 -> 88.888889 | E38: =LS2B!Q34 -> 94.444444 | F38: =LS2B!U34 -> 94.444444 | G38: =LS2B!Y34 -> 94.444444 | H38: =LS2B!AC34 -> 94.444444 | I38: =LS2B!AG34 -> 100 | J38: =LS2B!AK34 -> 100 | K38: =LS2B!AO34 -> 100
B41: LS3 A
B42: ENGLISH | C42: MATHEMATICS | D42: SCIENCE | E42: SOCIAL STUDIES | F42: NEW COMPUTING | G42: BUSINESS STUDIES | H42: FRENCH | I42: ART | J42: MDD | K42: PE
A43: Average | B43: =LS3A!E31 -> 55.26087 | C43: =LS3A!I31 -> 54.391304 | D43: =LS3A!M31 -> 56.430435 | E43: =LS3A!Q31 -> 60.043478 | F43: =LS3A!U31 -> 62.913043 | G43: =LS3A!Y31 -> 66.869565 | H43: =LS3A!AC31 -> 64.478261 | I43: =LS3A!AG31 -> 73.869565 | J43: =LS3A!AK31 -> 78.565217 | K43: =LS3A!AO31 -> 61.478261
A44: NO. Students | B44: =LS3A!E32 -> 23 | C44: =LS3A!I32 -> 23 | D44: =LS3A!M32 -> 23 | E44: =LS3A!Q32 -> 23 | F44: =LS3A!U32 -> 23 | G44: =LS3A!Y32 -> 23 | H44: =LS3A!AC32 -> 23 | I44: =LS3A!AG32 -> 23 | J44: =LS3A!AK32 -> 23 | K44: =LS3A!AO32 -> 23
A45: Pass | B45: =LS3A!E33 -> 17 | C45: =LS3A!I33 -> 15 | D45: =LS3A!M33 -> 17 | E45: =LS3A!Q33 -> 20 | F45: =LS3A!U33 -> 21 | G45: =LS3A!Y33 -> 20 | H45: =LS3A!AC33 -> 19 | I45: =LS3A!AG33 -> 23 | J45: =LS3A!AK33 -> 23 | K45: =LS3A!AO33 -> 21
A46: Fail | B46: =LS3A!E34 -> 6 | C46: =LS3A!I34 -> 8 | D46: =LS3A!M34 -> 6 | E46: =LS3A!Q34 -> 3 | F46: =LS3A!U34 -> 2 | G46: =LS3A!Y34 -> 3 | H46: =LS3A!AC34 -> 4 | I46: =LS3A!AG34 -> 0 | J46: =LS3A!AK34 -> 0 | K46: =LS3A!AO34 -> 2
A47: Pass Rate % | B47: =LS3A!E35 -> 73.913043 | C47: =LS3A!I35 -> 65.217391 | D47: =LS3A!M35 -> 73.913043 | E47: =LS3A!Q35 -> 86.956522 | F47: =LS3A!U35 -> 91.304348 | G47: =LS3A!Y35 -> 86.956522 | H47: =LS3A!AC35 -> 82.608696 | I47: =LS3A!AG35 -> 100 | J47: =LS3A!AK35 -> 100 | K47: =LS3A!AO35 -> 91.304348
B50: LS3 B
B51: ENGLISH | C51: MATHEMATICS | D51: SCIENCE | E51: SOCIAL STUDIES | F51: NEW COMPUTING | G51: BUSINESS STUDIES | H51: FRENCH | I51: ART | J51: MDD | K51: PE
A52: Average | B52: =LS3B!E36 -> 54.48 | C52: =LS3B!I36 -> 54 | D52: =LS3B!M36 -> 57.34 | E52: =LS3B!Q36 -> 62.36 | F52: =LS3B!U36 -> 55.76 | G52: =LS3B!Y36 -> 66.56 | H52: =LS3B!AC36 -> 58.2 | I52: =LS3B!AG36 -> 75.6 | J52: =LS3B!AK36 -> 57.6 | K52: =LS3B!AO36 -> 68.624
A53: NO. Students | B53: =LS3B!E37 -> 25 | C53: =LS3B!I37 -> 25 | D53: =LS3B!M37 -> 25 | E53: =LS3B!Q37 -> 25 | F53: =LS3B!U37 -> 25 | G53: =LS3B!Y37 -> 25 | H53: =LS3B!AC37 -> 25 | I53: =LS3B!AG37 -> 25 | J53: =LS3B!AK37 -> 25 | K53: =LS3B!AO37 -> 25
A54: Pass | B54: =LS3B!E38 -> 12 | C54: =LS3B!I38 -> 15 | D54: =LS3B!M38 -> 16 | E54: =LS3B!Q38 -> 22 | F54: =LS3B!U38 -> 16 | G54: =LS3B!Y38 -> 21 | H54: =LS3B!AC38 -> 17 | I54: =LS3B!AG38 -> 25 | J54: =LS3B!AK38 -> 22 | K54: =LS3B!AO38 -> 25
A55: Fail | B55: =LS3B!E39 -> 13 | C55: =LS3B!I39 -> 10 | D55: =LS3B!M39 -> 9 | E55: =LS3B!Q39 -> 3 | F55: =LS3B!U39 -> 9 | G55: =LS3B!Y39 -> 4 | H55: =LS3B!AC39 -> 8 | I55: =LS3B!AG39 -> 0 | J55: =LS3B!AK39 -> 3 | K55: =LS3B!AO39 -> 0
A56: Pass Rate % | B56: =LS3B!E40 -> 48 | C56: =LS3B!I40 -> 60 | D56: =LS3B!M40 -> 64 | E56: =LS3B!Q40 -> 88 | F56: =LS3B!U40 -> 64 | G56: =LS3B!Y40 -> 84 | H56: =LS3B!AC40 -> 68 | I56: =LS3B!AG40 -> 100 | J56: =LS3B!AK40 -> 88 | K56: =LS3B!AO40 -> 100
B59: IGCSE 1A
B60: ENGLISH | C60: MATHEMATICS | D60: BIOLOGY | E60: PHYSICS | F60: GEOGRAPHY | G60: BUSINESS STUDIES | H60: HISTORY | I60: ICT | J60: CHEMISTRY | K60: PE
A61: Average | B61: ='IGCSE 1A'!C34 -> 60.95 | C61: ='IGCSE 1A'!E34 -> 57.8 | D61: ='IGCSE 1A'!G34 -> 67.444444 | E61: ='IGCSE 1A'!I34 -> 55.4 | F61: ='IGCSE 1A'!K34 -> 89.333333 | G61: ='IGCSE 1A'!M34 -> 65 | H61: ='IGCSE 1A'!O34 -> #DIV/0! | I61: ='IGCSE 1A'!Q34 -> 55 | J61: ='IGCSE 1A'!S34 -> 75.85 | K61: ='IGCSE 1A'!U34 -> 58.75
A62: NO. Students | B62: ='IGCSE 1A'!C35 -> 20 | C62: ='IGCSE 1A'!E35 -> 20 | D62: ='IGCSE 1A'!G35 -> 18 | E62: ='IGCSE 1A'!I35 -> 20 | F62: ='IGCSE 1A'!K35 -> 3 | G62: ='IGCSE 1A'!M35 -> 2 | H62: ='IGCSE 1A'!O35 -> 0 | I62: ='IGCSE 1A'!Q35 -> 8 | J62: ='IGCSE 1A'!S35 -> 20 | K62: ='IGCSE 1A'!U35 -> 12
A63: Pass | B63: ='IGCSE 1A'!C36 -> 17 | C63: ='IGCSE 1A'!E36 -> 15 | D63: ='IGCSE 1A'!G36 -> 17 | E63: ='IGCSE 1A'!I36 -> 11 | F63: ='IGCSE 1A'!K36 -> 3 | G63: ='IGCSE 1A'!M36 -> 2 | H63: ='IGCSE 1A'!O36 -> 0 | I63: ='IGCSE 1A'!Q36 -> 6 | J63: ='IGCSE 1A'!S36 -> 19 | K63: ='IGCSE 1A'!U36 -> 10
A64: Fail | B64: ='IGCSE 1A'!C37 -> 3 | C64: ='IGCSE 1A'!E37 -> 5 | D64: ='IGCSE 1A'!G37 -> 1 | E64: ='IGCSE 1A'!I37 -> 9 | F64: ='IGCSE 1A'!K37 -> 0 | G64: ='IGCSE 1A'!M37 -> 0 | H64: ='IGCSE 1A'!O37 -> 0 | I64: ='IGCSE 1A'!Q37 -> 2 | J64: ='IGCSE 1A'!S37 -> 1 | K64: ='IGCSE 1A'!U37 -> 2
A65: Pass Rate % | B65: ='IGCSE 1A'!C38 -> 85 | C65: ='IGCSE 1A'!E38 -> 75 | D65: ='IGCSE 1A'!G38 -> 94.444444 | E65: ='IGCSE 1A'!I38 -> 55 | F65: ='IGCSE 1A'!K38 -> 100 | G65: ='IGCSE 1A'!M38 -> 100 | H65: ='IGCSE 1A'!O38 -> #DIV/0! | I65: ='IGCSE 1A'!Q38 -> 75 | J65: ='IGCSE 1A'!S38 -> 95 | K65: ='IGCSE 1A'!U38 -> 83.333333
B67: IGCSE 1B
B68: ENGLISH | C68: MATHEMATICS | D68: BIOLOGY | E68: PHYSICS | F68: GEOGRAPHY | G68: BUSINESS STUDIES | H68: HISTORY | I68: ICT | J68: CHEMISTRY | K68: PE
A69: Average | B69: ='IGCSE 1B'!C34 | C69: ='IGCSE 1A'!E34 -> 57.8 | D69: ='IGCSE 1A'!G34 -> 67.444444 | E69: ='IGCSE 1A'!I34 -> 55.4 | F69: ='IGCSE 1A'!K34 -> 89.333333 | G69: ='IGCSE 1A'!M34 -> 65 | H69: ='IGCSE 1A'!O34 -> #DIV/0! | I69: ='IGCSE 1A'!Q34 -> 55 | J69: ='IGCSE 1A'!S34 -> 75.85 | K69: ='IGCSE 1A'!U34 -> 58.75
A70: NO. Students | B70: ='IGCSE 1A'!C35 -> 20 | C70: ='IGCSE 1A'!E35 -> 20 | D70: ='IGCSE 1A'!G35 -> 18 | E70: ='IGCSE 1A'!I35 -> 20 | F70: ='IGCSE 1A'!K35 -> 3 | G70: ='IGCSE 1A'!M35 -> 2 | H70: ='IGCSE 1A'!O35 -> 0 | I70: ='IGCSE 1A'!Q35 -> 8 | J70: ='IGCSE 1A'!S35 -> 20 | K70: ='IGCSE 1A'!U35 -> 12
A71: Pass | B71: ='IGCSE 1A'!C36 -> 17 | C71: ='IGCSE 1A'!E36 -> 15 | D71: ='IGCSE 1A'!G36 -> 17 | E71: ='IGCSE 1A'!I36 -> 11 | F71: ='IGCSE 1A'!K36 -> 3 | G71: ='IGCSE 1A'!M36 -> 2 | H71: ='IGCSE 1A'!O36 -> 0 | I71: ='IGCSE 1A'!Q36 -> 6 | J71: ='IGCSE 1A'!S36 -> 19 | K71: ='IGCSE 1A'!U36 -> 10
A72: Fail | B72: ='IGCSE 1A'!C37 -> 3 | C72: ='IGCSE 1A'!E37 -> 5 | D72: ='IGCSE 1A'!G37 -> 1 | E72: ='IGCSE 1A'!I37 -> 9 | F72: ='IGCSE 1A'!K37 -> 0 | G72: ='IGCSE 1A'!M37 -> 0 | H72: ='IGCSE 1A'!O37 -> 0 | I72: ='IGCSE 1A'!Q37 -> 2 | J72: ='IGCSE 1A'!S37 -> 1 | K72: ='IGCSE 1A'!U37 -> 2
A73: Pass Rate % | B73: ='IGCSE 1A'!C38 -> 85 | C73: ='IGCSE 1A'!E38 -> 75 | D73: ='IGCSE 1A'!G38 -> 94.444444 | E73: ='IGCSE 1A'!I38 -> 55 | F73: ='IGCSE 1A'!K38 -> 100 | G73: ='IGCSE 1A'!M38 -> 100 | H73: ='IGCSE 1A'!O38 -> #DIV/0! | I73: ='IGCSE 1A'!Q38 -> 75 | J73: ='IGCSE 1A'!S38 -> 95 | K73: ='IGCSE 1A'!U38 -> 83.333333
B76: IGCSE 1C
B77: ENGLISH | C77: MATHEMATICS | D77: BIOLOGY | E77: PHYSICS | F77: GEOGRAPHY | G77: BUSINESS STUDIES | H77: HISTORY | I77: ICT | J77: CHEMISTRY | K77: PE
A78: Average | B78: ='IGCSE 1C'!C25 -> 57.5 | C78: ='IGCSE 1C'!E25 -> 56.117647 | D78: ='IGCSE 1C'!G25 -> 59 | E78: ='IGCSE 1C'!I25 -> #DIV/0! | F78: ='IGCSE 1C'!K25 -> 74.333333 | G78: ='IGCSE 1C'!M25 -> 47.785714 | H78: ='IGCSE 1C'!O25 -> 72.588235 | I78: ='IGCSE 1C'!Q25 -> 46.769231 | J78: ='IGCSE 1C'!S25 -> 68.444444 | K78: ='IGCSE 1C'!U25 -> 42.5
A79: NO. Students | B79: ='IGCSE 1C'!C26 -> 16 | C79: ='IGCSE 1C'!E26 -> 17 | D79: ='IGCSE 1C'!G26 -> 2 | E79: ='IGCSE 1C'!I26 -> 0 | F79: ='IGCSE 1C'!K26 -> 6 | G79: ='IGCSE 1C'!M26 -> 14 | H79: ='IGCSE 1C'!O26 -> 17 | I79: ='IGCSE 1C'!Q26 -> 13 | J79: ='IGCSE 1C'!S26 -> 9 | K79: ='IGCSE 1C'!U26 -> 2
A80: Pass | B80: ='IGCSE 1C'!C27 -> 12 | C80: ='IGCSE 1C'!E27 -> 10 | D80: ='IGCSE 1C'!G27 -> 2 | E80: ='IGCSE 1C'!I27 -> 0 | F80: ='IGCSE 1C'!K27 -> 6 | G80: ='IGCSE 1C'!M27 -> 5 | H80: ='IGCSE 1C'!O27 -> 17 | I80: ='IGCSE 1C'!Q27 -> 6 | J80: ='IGCSE 1C'!S27 -> 9 | K80: ='IGCSE 1C'!U27 -> 0
A81: Fail | B81: ='IGCSE 1C'!C28 -> 4 | C81: ='IGCSE 1C'!E28 -> 7 | D81: ='IGCSE 1C'!G28 -> 0 | E81: ='IGCSE 1C'!I28 -> 0 | F81: ='IGCSE 1C'!K28 -> 0 | G81: ='IGCSE 1C'!M28 -> 9 | H81: ='IGCSE 1C'!O28 -> 0 | I81: ='IGCSE 1C'!Q28 -> 7 | J81: ='IGCSE 1C'!S28 -> 0 | K81: ='IGCSE 1C'!U28 -> 2
A82: Pass Rate % | B82: ='IGCSE 1C'!C29 -> 75 | C82: ='IGCSE 1C'!E29 -> 58.823529 | D82: ='IGCSE 1C'!G29 -> 100 | E82: ='IGCSE 1C'!I29 -> #DIV/0! | F82: ='IGCSE 1C'!K29 -> 100 | G82: ='IGCSE 1C'!M29 -> 35.714286 | H82: ='IGCSE 1C'!O29 -> 100 | I82: ='IGCSE 1C'!Q29 -> 46.153846 | J82: ='IGCSE 1C'!S29 -> 100 | K82: ='IGCSE 1C'!U29 -> 0
B86: IGCSE 2A
B87: ENGLISH | C87: MATHEMATICS | D87: BIOLOGY | E87: PHYSICS | F87: GEOGRAPHY | G87: BUSINESS STUDIES | H87: HISTORY | I87: ICT | J87: CHEMISTRY | K87: PE
A88: Average | B88: ='IGCSE 2A'!C34 -> 43.473684 | C88: ='IGCSE 2A'!E34 -> 52 | D88: ='IGCSE 2A'!G34 -> 52.315789 | E88: ='IGCSE 2A'!I34 -> 59.75 | F88: ='IGCSE 2A'!K34 -> 61.666667 | G88: ='IGCSE 2A'!M34 -> 45.333333 | H88: ='IGCSE 2A'!O34 -> #DIV/0! | I88: ='IGCSE 2A'!Q34 -> 48.636364 | J88: ='IGCSE 2A'!S34 -> 53 | K88: ='IGCSE 2A'!U34 -> 63.2
A89: NO. Students | B89: ='IGCSE 2A'!C35 -> 19 | C89: ='IGCSE 2A'!E35 -> 22 | D89: ='IGCSE 2A'!G35 -> 19 | E89: ='IGCSE 2A'!I35 -> 20 | F89: ='IGCSE 2A'!K35 -> 3 | G89: ='IGCSE 2A'!M35 -> 3 | H89: ='IGCSE 2A'!O35 -> 0 | I89: ='IGCSE 2A'!Q35 -> 11 | J89: ='IGCSE 2A'!S35 -> 16 | K89: ='IGCSE 2A'!U35 -> 10
A90: Pass | B90: ='IGCSE 2A'!C36 -> 6 | C90: ='IGCSE 2A'!E36 -> 14 | D90: ='IGCSE 2A'!G36 -> 13 | E90: ='IGCSE 2A'!I36 -> 17 | F90: ='IGCSE 2A'!K36 -> 2 | G90: ='IGCSE 2A'!M36 -> 1 | H90: ='IGCSE 2A'!O36 -> 0 | I90: ='IGCSE 2A'!Q36 -> 7 | J90: ='IGCSE 2A'!S36 -> 12 | K90: ='IGCSE 2A'!U36 -> 7
A91: Fail | B91: ='IGCSE 2A'!C37 -> 13 | C91: ='IGCSE 2A'!E37 -> 8 | D91: ='IGCSE 2A'!G37 -> 6 | E91: ='IGCSE 2A'!I37 -> 3 | F91: ='IGCSE 2A'!K37 -> 1 | G91: ='IGCSE 2A'!M37 -> 2 | H91: ='IGCSE 2A'!O37 -> 0 | I91: ='IGCSE 2A'!Q37 -> 4 | J91: ='IGCSE 2A'!S37 -> 4 | K91: ='IGCSE 2A'!U37 -> 3
A92: Pass Rate % | B92: ='IGCSE 2A'!C38 -> 31.578947 | C92: ='IGCSE 2A'!E38 -> 63.636364 | D92: ='IGCSE 2A'!G38 -> 68.421053 | E92: ='IGCSE 2A'!I38 -> 85 | F92: ='IGCSE 2A'!K38 -> 66.666667 | G92: ='IGCSE 2A'!M38 -> 33.333333 | H92: ='IGCSE 2A'!O38 -> #DIV/0! | I92: ='IGCSE 2A'!Q38 -> 63.636364 | J92: ='IGCSE 2A'!S38 -> 75 | K92: ='IGCSE 2A'!U38 -> 70
B94: IGCSE 2B
B95: ENGLISH | C95: MATHEMATICS | D95: BIOLOGY | E95: PHYSICS | F95: GEOGRAPHY | G95: BUSINESS STUDIES | H95: HISTORY | I95: ICT | J95: CHEMISTRY | K95: PE
A96: Average | B96: ='IGCSE 2B'!C14 -> 38.25 | C96: ='IGCSE 2B'!E14 -> 39.25 | D96: ='IGCSE 2B'!G14 -> 41 | E96: ='IGCSE 2B'!I14 -> 44.666667 | F96: ='IGCSE 2B'!K14 -> 40.5 | G96: ='IGCSE 2B'!M14 -> 32.2 | H96: ='IGCSE 2B'!O14 -> #DIV/0! | I96: ='IGCSE 2B'!Q14 -> 44.2 | J96: ='IGCSE 2B'!S14 -> 44 | K96: ='IGCSE 2B'!U14 -> 59.333333
A97: NO. Students | B97: ='IGCSE 2B'!C15 -> 8 | C97: ='IGCSE 2B'!E15 -> 8 | D97: ='IGCSE 2B'!G15 -> 3 | E97: ='IGCSE 2B'!I15 -> 3 | F97: ='IGCSE 2B'!K15 -> 6 | G97: ='IGCSE 2B'!M15 -> 5 | H97: ='IGCSE 2B'!O15 -> 0 | I97: ='IGCSE 2B'!Q15 -> 5 | J97: ='IGCSE 2B'!S15 -> 2 | K97: ='IGCSE 2B'!U15 -> 3
A98: Pass | B98: ='IGCSE 2B'!C16 -> 0 | C98: ='IGCSE 2B'!E16 -> 1 | D98: ='IGCSE 2B'!G16 -> 1 | E98: ='IGCSE 2B'!I16 -> 1 | F98: ='IGCSE 2B'!K16 -> 1 | G98: ='IGCSE 2B'!M16 -> 1 | H98: ='IGCSE 2B'!O16 -> 0 | I98: ='IGCSE 2B'!Q16 -> 1 | J98: ='IGCSE 2B'!S16 -> 1 | K98: ='IGCSE 2B'!U16 -> 3
A99: Fail | B99: ='IGCSE 2B'!C17 -> 8 | C99: ='IGCSE 2B'!E17 -> 7 | D99: ='IGCSE 2B'!G17 -> 2 | E99: ='IGCSE 2B'!I17 -> 2 | F99: ='IGCSE 2B'!K17 -> 5 | G99: ='IGCSE 2B'!M17 -> 4 | H99: ='IGCSE 2B'!O17 -> 0 | I99: ='IGCSE 2B'!Q17 -> 4 | J99: ='IGCSE 2B'!S17 -> 1 | K99: ='IGCSE 2B'!U17 -> 0
A100: Pass Rate % | B100: ='IGCSE 2B'!C18 -> 0 | C100: ='IGCSE 2B'!E18 -> 12.5 | D100: ='IGCSE 2B'!G18 -> 33.333333 | E100: ='IGCSE 2B'!I18 -> 33.333333 | F100: ='IGCSE 2B'!K18 -> 16.666667 | G100: ='IGCSE 2B'!M18 -> 20 | H100: ='IGCSE 2B'!O18 -> #DIV/0! | I100: ='IGCSE 2B'!Q18 -> 20 | J100: ='IGCSE 2B'!S18 -> 50 | K100: ='IGCSE 2B'!U18 -> 100
B103: IGCSE 2C
B104: ENGLISH | C104: MATHEMATICS | D104: BIOLOGY | E104: PHYSICS | F104: GEOGRAPHY | G104: BUSINESS STUDIES | H104: HISTORY | I104: ICT | J104: CHEMISTRY | K104: PE
A105: Average | B105: ='IGCSE 2C'!C24 -> 56.444444 | C105: ='IGCSE 2C'!E24 -> 50.222222 | D105: ='IGCSE 2C'!G24 -> 49.545455 | E105: ='IGCSE 2C'!I24 -> 55.142857 | F105: ='IGCSE 2C'!K24 -> 49.090909 | G105: ='IGCSE 2C'!M24 -> 49.333333 | H105: ='IGCSE 2C'!O24 -> 43.111111 | I105: ='IGCSE 2C'!Q24 -> 48.571429 | J105: ='IGCSE 2C'!S24 -> 47 | K105: ='IGCSE 2C'!U24 -> 62.25
A106: NO. Students | B106: ='IGCSE 2C'!C25 -> 18 | C106: ='IGCSE 2C'!E25 -> 18 | D106: ='IGCSE 2C'!G25 -> 11 | E106: ='IGCSE 2C'!I25 -> 7 | F106: ='IGCSE 2C'!K25 -> 11 | G106: ='IGCSE 2C'!M25 -> 9 | H106: ='IGCSE 2C'!O25 -> 9 | I106: ='IGCSE 2C'!Q25 -> 7 | J106: ='IGCSE 2C'!S25 -> 4 | K106: ='IGCSE 2C'!U25 -> 8
A107: Pass | B107: ='IGCSE 2C'!C26 -> 14 | C107: ='IGCSE 2C'!E26 -> 10 | D107: ='IGCSE 2C'!G26 -> 5 | E107: ='IGCSE 2C'!I26 -> 6 | F107: ='IGCSE 2C'!K26 -> 5 | G107: ='IGCSE 2C'!M26 -> 4 | H107: ='IGCSE 2C'!O26 -> 4 | I107: ='IGCSE 2C'!Q26 -> 2 | J107: ='IGCSE 2C'!S26 -> 3 | K107: ='IGCSE 2C'!U26 -> 7
A108: Fail | B108: ='IGCSE 2C'!C27 -> 4 | C108: ='IGCSE 2C'!E27 -> 8 | D108: ='IGCSE 2C'!G27 -> 6 | E108: ='IGCSE 2C'!I27 -> 1 | F108: ='IGCSE 2C'!K27 -> 6 | G108: ='IGCSE 2C'!M27 -> 5 | H108: ='IGCSE 2C'!O27 -> 5 | I108: ='IGCSE 2C'!Q27 -> 5 | J108: ='IGCSE 2C'!S27 -> 1 | K108: ='IGCSE 2C'!U27 -> 1
A109: Pass Rate % | B109: ='IGCSE 2C'!C28 -> 77.777778 | C109: ='IGCSE 2C'!E28 -> 55.555556 | D109: ='IGCSE 2C'!G28 -> 45.454545 | E109: ='IGCSE 2C'!I28 -> 85.714286 | F109: ='IGCSE 2C'!K28 -> 45.454545 | G109: ='IGCSE 2C'!M28 -> 44.444444 | H109: ='IGCSE 2C'!O28 -> 44.444444 | I109: ='IGCSE 2C'!Q28 -> 28.571429 | J109: ='IGCSE 2C'!S28 -> 75 | K109: ='IGCSE 2C'!U28 -> 87.5
B111: AS LEVEL
B112: ENGLISH | C112: MATHEMATICS | D112: BIOLOGY | E112: PHYSICS | F112: COMPUTER SCIENCE | G112: BUSINESS STUDIES | H112: HISTORY | I112: IT | J112: ACCOUNTS | K112: ART
A113: Average | B113: =AVERAGE(ASLEVEL!$C$2:$C$14) -> #REF! | C113: =AVERAGE(ASLEVEL!$E$2:$E$14) -> #REF! | D113: =AVERAGE(ASLEVEL!$G$2:$G$14) -> #REF! | E113: =AVERAGE(ASLEVEL!$I$2:$I$14) -> #REF! | F113: =AVERAGE(ASLEVEL!$K$2:$K$14) -> #REF! | G113: =AVERAGE(ASLEVEL!$M$2:$M$14) -> #REF! | H113: =AVERAGE(ASLEVEL!$O$2:$O$14) -> #REF! | I113: =AVERAGE(ASLEVEL!$Q$2:$Q$14) -> #REF! | J113: =AVERAGE(ASLEVEL!$U$10:$U$11) -> #REF! | K113: 85
A114: NO. Students | B114: =COUNT(ASLEVEL!$C$2:$C$14) -> 0 | C114: =COUNT(ASLEVEL!$E$2:$E$14) -> 0 | D114: =COUNT(ASLEVEL!$G$2:$G$14) -> 0 | E114: =COUNT(ASLEVEL!$I$2:$I$14) -> 0 | F114: =COUNT(ASLEVEL!$K$2:$K$14) -> 0 | G114: =COUNT(ASLEVEL!$M$2:$M$14) -> 0 | H114: =COUNT(ASLEVEL!$O$2:$O$14) -> 0 | I114: =COUNT(ASLEVEL!$Q$2:$Q$14) -> 0 | J114: =COUNT(ASLEVEL!$U$10:$U$11) -> 0 | K114: 1
A115: Pass | B115: =COUNTIF(ASLEVEL!$C$2:$C$14,">49") -> #REF! | C115: =COUNTIF(ASLEVEL!$E$2:$E$14,">49") -> #REF! | D115: =COUNTIF(ASLEVEL!$G$2:$G$14,">49") -> #REF! | E115: =COUNTIF(ASLEVEL!$I$2:$I$14,">49") -> #REF! | F115: =COUNTIF(ASLEVEL!$K$2:$K$14,">49") -> #REF! | G115: =COUNTIF(ASLEVEL!$M$2:$M$14,">49") -> #REF! | H115: =COUNTIF(ASLEVEL!$O$2:$O$14,">49") -> #REF! | I115: =COUNTIF(ASLEVEL!$Q$2:$Q$14,">49") -> #REF! | J115: =COUNTIF(ASLEVEL!$U$10:$U$11,">49") -> #REF! | K115: 1
A116: Fail | B116: =COUNTIF(ASLEVEL!$C$2:$C$14,"<50") -> #REF! | C116: =COUNTIF(ASLEVEL!$E$2:$E$14,"<50") -> #REF! | D116: =COUNTIF(ASLEVEL!$G$2:$G$14,"<50") -> #REF! | E116: =COUNTIF(ASLEVEL!$I$2:$I$14,"<50") -> #REF! | F116: =COUNTIF(ASLEVEL!$K$2:$K$14,"<50") -> #REF! | G116: =COUNTIF(ASLEVEL!$M$2:$M$14,"<50") -> #REF! | H116: =COUNTIF(ASLEVEL!$O$2:$O$14,"<50") -> #REF! | I116: =COUNTIF(ASLEVEL!$Q$2:$Q$14,"<50") -> #REF! | J116: =COUNTIF(ASLEVEL!$C$2:$C$14,"<50") -> #REF! | K116: 0
A117: Pass Rate % | B117: =B115*100/B114 -> #REF! | C117: =C115*100/C114 -> #REF! | D117: =D115*100/D114 -> #REF! | E117: =E115*100/E114 -> #REF! | F117: =F115*100/F114 -> #REF! | G117: =G115*100/G114 -> #REF! | H117: =H115*100/H114 -> #REF! | I117: =I115*100/I114 -> #REF! | ... K117: =K115*100/K114 -> 100

Sheet LS1A
A3: Roll N0. | B3: Name | C3: English | G3: Mathematics | K3: Science | O3: Global Perspective | S3: New Computing | W3: Business Studies | AA3: French | AE3: Art | AI3: MDD | AM3: PE | AR3: AVERAGE | AS3: POSITION | AT3: CREATIVITY | AU3: RESPECT | AV3: EXCELLENCE | AW3: EMPATHY | AX3: DISCIPLINE | AY3: CLASS TEACHER'S COMMENT
C4: Formative | D4: Summative | E4: Final Mark | F4: Grade | G4: Formative | H4: Summative | I4: Final Mark | J4: Grade | K4: Formative | L4: Summative | M4: Final Mark | N4: Grade | O4: Formative | P4: Summative | Q4: Final Mark | R4: Grade | S4: Formative | T4: Summative | U4: Final Mark | V4: Grade | W4: Formative | X4: Summative | Y4: Final Mark | Z4: Grade | AA4: Formative | AB4: Summative | AC4: Final Mark | AD4: Grade | AE4: Formative | AF4: Summative | AG4: Final Mark | AH4: Grade | AI4: Formative | AJ4: Summative | AK4: Final Mark | AL4: Grade | AM4: Formative | AN4: Summative | AO4: Final Mark | AP4: Grade
A5: 1 | B5: Maine Ralesite | C5: 31 | D5: 41 | E5: =C5+D5 -> 72 | F5: =VLOOKUP(E5,$B$44:$C$52,2) -> B | G5: 28 | H5: 45 | I5: =G5+H5 -> 73 | J5: =VLOOKUP(I5,$B$44:$C$52,2) -> B | K5: 32 | L5: 45 | M5: =K5+L5 -> 77 | N5: =VLOOKUP(M5,$B$44:$C$52,2) -> B | O5: 35 | P5: 50 | Q5: =O5+P5 -> 85 | R5: =VLOOKUP(Q5,$B$44:$C$52,2) -> A | S5: 33 | T5: 47 | U5: =S5+T5 -> 80 | V5: =VLOOKUP(U5,$B$44:$C$52,2) -> A | W5: 28 | X5: 43 | Y5: =W5+X5 -> 71 | Z5: =VLOOKUP(Y5,$B$44:$C$52,2) -> B | AA5: 30 | AB5: 38 | AC5: =AA5+AB5 -> 68 | AD5: =VLOOKUP(AC5,$B$44:$C$52,2) -> C | AE5: 28 | AF5: 49 | AG5: 77 | AH5: =VLOOKUP(AG5,$B$44:$C$52,2) -> B | AI5: 37 | AJ5: 45 | AK5: =AI5+AJ5 -> 82 | AL5: =VLOOKUP(AK5,$B$44:$C$52,2) -> A | AM5: 23 | AN5: 41 | AO5: =AM5+AN5 -> 64 | AP5: =VLOOKUP(AO5,$B$44:$C$52,2) -> C | AR5: =AVERAGE(E5,I5,M5,Q5,U5,Y5,AC5,AG5,AK5,AO5) -> 74.9 | AS5: =RANK(AR5,$AR$5:$AR$33) -> 5 | AT5: A | AU5: A+ | AV5: B | AW5: A | AX5: A+ | AY5: Ralesite is a very respectful and well-mannered student who works well in class. His academic performance is good, showing clear understanding of key concepts. To improve further, he should participate more actively and ask questions to deepen his understanding. Regular practice and reviewing class notes will strengthen his learning. I encourage Ralesite to continue his positive behaviour and maintain steady effort towards higher achievement.
A6: 2 | B6: AIsha | C6: 21 | D6: 35 | E6: =C6+D6 -> 56 | F6: =VLOOKUP(E6,$B$44:$C$52,2) -> D | G6: 9 | H6: 17 | I6: =G6+H6 -> 26 | J6: =VLOOKUP(I6,$B$44:$C$52,2) -> G | K6: 18 | L6: 30 | M6: =K6+L6 -> 48 | N6: =VLOOKUP(M6,$B$44:$C$52,2) -> E | O6: 23 | P6: 22 | Q6: =O6+P6 -> 45 | R6: =VLOOKUP(Q6,$B$44:$C$52,2) -> E | S6: 23 | T6: 37 | U6: =S6+T6 -> 60 | V6: =VLOOKUP(U6,$B$44:$C$52,2) -> C | W6: 16 | X6: 31 | Y6: =W6+X6 -> 47 | Z6: =VLOOKUP(Y6,$B$44:$C$52,2) -> E | AA6: 19 | AB6: 40 | AC6: =AA6+AB6 -> 59 | AD6: =VLOOKUP(AC6,$B$44:$C$52,2) -> D | AE6: 24 | AF6: 43 | AG6: =AE6+AF6 -> 67 | AH6: =VLOOKUP(AG6,$B$44:$C$52,2) -> C | AI6: 37 | AJ6: 45 | AK6: =AI6+AJ6 -> 82 | AL6: =VLOOKUP(AK6,$B$44:$C$52,2) -> A | AM6: 18.9 | AN6: 40 | AO6: =AM6+AN6 -> 58.9 | AP6: =VLOOKUP(AO6,$B$44:$C$52,2) -> D | AR6: =AVERAGE(E6,I6,M6,Q6,U6,Y6,AC6,AG6,AK6,AO6) -> 54.89 | AS6: =RANK(AR6,$AR$5:$AR$33) -> 20 | AT6: C | AU6: A | AV6: C | AW6: B | AX6: A | AY6: Aisha behaves well and participates positively in class. However, she needs to improve in Science, Maths, and English. Paying close attention during lessons and completing extra practice will help her strengthen her skills. Asking questions when unsure and revising daily will support her learning. I encourage her to remain focused and dedicated. With consistent effort, Aisha can make great progress.
A7: 3 | B7: Chokr Mohammad | C7: 19 | D7: 18 | E7: =C7+D7 -> 37 | F7: =VLOOKUP(E7,$B$44:$C$52,2) -> F | G7: 9 | H7: 14 | I7: =G7+H7 -> 23 | J7: =VLOOKUP(I7,$B$44:$C$52,2) -> G | K7: 15 | L7: 17 | M7: =K7+L7 -> 32 | N7: =VLOOKUP(M7,$B$44:$C$52,2) -> F | O7: 23 | P7: 21 | Q7: =O7+P7 -> 44 | R7: =VLOOKUP(Q7,$B$44:$C$52,2) -> E | S7: 10 | T7: 33 | U7: =S7+T7 -> 43 | V7: =VLOOKUP(U7,$B$44:$C$52,2) -> E | W7: 9 | X7: 10 | Y7: =W7+X7 -> 19 | Z7: =VLOOKUP(Y7,$B$44:$C$52,2) -> U | AA7: 16 | AB7: 23 | AC7: =AA7+AB7 -> 39 | AD7: =VLOOKUP(AC7,$B$44:$C$52,2) -> F | AE7: 23 | AF7: 38 | AG7: =AE7+AF7 -> 61 | AH7: =VLOOKUP(AG7,$B$44:$C$52,2) -> C | AI7: 24 | AJ7: 42 | AK7: =AI7+AJ7 -> 66 | AL7: =VLOOKUP(AK7,$B$44:$C$52,2) -> C | AM7: 20 | AN7: 44 | AO7: =AM7+AN7 -> 64 | AP7: =VLOOKUP(AO7,$B$44:$C$52,2) -> C | AR7: =AVERAGE(E7,I7,M7,Q7,U7,Y7,AC7,AG7,AK7,AO7) -> 42.8 | AS7: =RANK(AR7,$AR$5:$AR$33) -> 24 | AT7: C | AU7: D | AV7: D | AW7: C | AX7: D | AY7: Mohammed shows average behaviour and finds it difficult to sit still for long periods, often becoming distracted by friends. Despite this, his academic performance is very good. To improve further, he should work on managing distractions and developing better concentration habits. Sitting in a quiet area and following structured study routines will help him stay focused. Mohammed is encouraged to continue working hard while improving his behaviour.
A8: 4 | B8: Munshi Khadijah | C8: 26 | D8: 54 | E8: =C8+D8 -> 80 | F8: =VLOOKUP(E8,$B$44:$C$52,2) -> A | G8: 7 | H8: 10 | I8: =G8+H8 -> 17 | J8: =VLOOKUP(I8,$B$44:$C$52,2) -> U | K8: 14 | L8: 29 | M8: =K8+L8 -> 43 | N8: =VLOOKUP(M8,$B$44:$C$52,2) -> E | O8: 31 | P8: 24 | Q8: =O8+P8 -> 55 | R8: =VLOOKUP(Q8,$B$44:$C$52,2) -> D | S8: 20 | T8: 36 | U8: =S8+T8 -> 56 | V8: =VLOOKUP(U8,$B$44:$C$52,2) -> D | W8: 32 | X8: 24 | Y8: =W8+X8 -> 56 | Z8: =VLOOKUP(Y8,$B$44:$C$52,2) -> D | AA8: 14 | AB8: 34 | AC8: =AA8+AB8 -> 48 | AD8: =VLOOKUP(AC8,$B$44:$C$52,2) -> E | AE8: 32 | AF8: 48 | AG8: =AE8+AF8 -> 80 | AH8: =VLOOKUP(AG8,$B$44:$C$52,2) -> A | AI8: 32 | AJ8: 42 | AK8: =AI8+AJ8 -> 74 | AL8: =VLOOKUP(AK8,$B$44:$C$52,2) -> B | AM8: 22.5 | AN8: 49 | AO8: =AM8+AN8 -> 71.5 | AP8: =VLOOKUP(AO8,$B$44:$C$52,2) -> B | AR8: =AVERAGE(E8,I8,M8,Q8,U8,Y8,AC8,AG8,AK8,AO8) -> 58.05 | AS8: =RANK(AR8,$AR$5:$AR$33) -> 17 | AT8: B | AU8: B | AV8: B | AW8: C | AX8: B | AY8: Khadijah demonstrates very good behaviour and a positive attitude towards learning. Her academic performance is good and shows clear potential for further growth. She can improve by taking more initiative in challenging tasks and deepening her understanding through wider reading. Maintaining consistent study habits will support her progress. I encourage Khadijah to continue her strong effort and stay committed to excellence.
A9: 5 | B9: Mwewa Likezo | C9: 25 | D9: 20 | E9: =C9+D9 -> 45 | F9: =VLOOKUP(E9,$B$44:$C$52,2) -> E | G9: 5 | H9: 13 | I9: =G9+H9 -> 18 | J9: =VLOOKUP(I9,$B$44:$C$52,2) -> U | K9: 11 | L9: 17 | M9: =K9+L9 -> 28 | N9: =VLOOKUP(M9,$B$44:$C$52,2) -> G | O9: 26 | P9: 31 | Q9: =O9+P9 -> 57 | R9: =VLOOKUP(Q9,$B$44:$C$52,2) -> D | S9: 19 | T9: 36 | U9: =S9+T9 -> 55 | V9: =VLOOKUP(U9,$B$44:$C$52,2) -> D | W9: 30 | X9: 37 | Y9: =W9+X9 -> 67 | Z9: =VLOOKUP(Y9,$B$44:$C$52,2) -> C | AA9: 17 | AB9: 29 | AC9: =AA9+AB9 -> 46 | AD9: =VLOOKUP(AC9,$B$44:$C$52,2) -> E | AE9: 24 | AF9: 39 | AG9: =AE9+AF9 -> 63 | AH9: =VLOOKUP(AG9,$B$44:$C$52,2) -> C | AI9: 29 | AJ9: 42 | AK9: =AI9+AJ9 -> 71 | AL9: =VLOOKUP(AK9,$B$44:$C$52,2) -> B | AM9: 16.7 | AN9: 25 | AO9: =AM9+AN9 -> 41.7 | AP9: =VLOOKUP(AO9,$B$44:$C$52,2) -> E | AR9: =AVERAGE(E9,I9,M9,Q9,U9,Y9,AC9,AG9,AK9,AO9) -> 49.17 | AS9: =RANK(AR9,$AR$5:$AR$33) -> 22 | AT9: A | AU9: A | AV9: C | AW9: C | AX9: B | AY9: Likezo behaves well but struggles to stay focused for long periods and often isolates himself. He needs improvement in Science, Maths, and English. Developing better engagement in class and participating more actively will support his progress. Completing regular practice at home and reviewing lessons will help strengthen his understanding. I encourage Likezo to interact more
A10: 6 | B10: Blount Jaxen | C10: 28 | D10: 42 | E10: =C10+D10 -> 70 | F10: =VLOOKUP(E10,$B$44:$C$52,2) -> B | G10: 8 | H10: 30 | I10: =G10+H10 -> 38 | J10: =VLOOKUP(I10,$B$44:$C$52,2) -> F | K10: 10 | L10: 35 | M10: =K10+L10 -> 45 | N10: =VLOOKUP(M10,$B$44:$C$52,2) -> E | O10: 31 | P10: 47 | Q10: =O10+P10 -> 78 | R10: =VLOOKUP(Q10,$B$44:$C$52,2) -> B | S10: 22 | T10: 36 | U10: =S10+T10 -> 58 | V10: =VLOOKUP(U10,$B$44:$C$52,2) -> D | W10: 23 | X10: 31 | Y10: =W10+X10 -> 54 | Z10: =VLOOKUP(Y10,$B$44:$C$52,2) -> D | AA10: 13 | AB10: 35 | AC10: =AA10+AB10 -> 48 | AD10: =VLOOKUP(AC10,$B$44:$C$52,2) -> E | AE10: 25 | AF10: 47 | AG10: =AE10+AF10 -> 72 | AH10: =VLOOKUP(AG10,$B$44:$C$52,2) -> B | AI10: 30 | AJ10: 51 | AK10: =AI10+AJ10 -> 81 | AL10: =VLOOKUP(AK10,$B$44:$C$52,2) -> A | AM10: 21 | AN10: 39 | AO10: =AM10+AN10 -> 60 | AP10: =VLOOKUP(AO10,$B$44:$C$52,2) -> C | AR10: =AVERAGE(E10,I10,M10,Q10,U10,Y10,AC10,AG10,AK10,AO10) -> 60.4 | AS10: =RANK(AR10,$AR$5:$AR$33) -> 14 | AT10: A+ | AU10: C | AV10: C | AW10: C | AX10: C | AY10: Jaxen displays average behaviour and often loses focus, becoming easily distracted. His performance in Science, Maths, and English needs improvement. I would also like to acknowledge his effort and confidence in presenting at TEDx, which is a commendable achievement. He should practise staying attentive in class and completing tasks without rushing. Regular revision, extra exercises, and asking for help when needed will support his progress. Improving his study routines and reducing distractions will greatly benefit him. With consistent effort and a more focused approach, Jaxen has the potential to achieve much stronger results.
A11: 7 | B11: Shamiso | C11: 27 | D11: 37 | E11: =C11+D11 -> 64 | F11: =VLOOKUP(E11,$B$44:$C$52,2) -> C | G11: 15 | H11: 36 | I11: =G11+H11 -> 51 | J11: =VLOOKUP(I11,$B$44:$C$52,2) -> D | K11: 12 | L11: 30 | M11: =K11+L11 -> 42 | N11: =VLOOKUP(M11,$B$44:$C$52,2) -> E | O11: 28 | P11: 47 | Q11: =O11+P11 -> 75 | R11: =VLOOKUP(Q11,$B$44:$C$52,2) -> B | S11: 18 | T11: 43 | U11: =S11+T11 -> 61 | V11: =VLOOKUP(U11,$B$44:$C$52,2) -> C | W11: 23 | X11: 31 | Y11: =W11+X11 -> 54 | Z11: =VLOOKUP(Y11,$B$44:$C$52,2) -> D | AA11: 18 | AB11: 41 | AC11: =AA11+AB11 -> 59 | AD11: =VLOOKUP(AC11,$B$44:$C$52,2) -> D | AE11: 30 | AF11: 46 | AG11: =AE11+AF11 -> 76 | AH11: =VLOOKUP(AG11,$B$44:$C$52,2) -> B | AI11: 31 | AJ11: 48 | AK11: =AI11+AJ11 -> 79 | AL11: =VLOOKUP(AK11,$B$44:$C$52,2) -> B | AM11: 33.5 | AN11: 50 | AO11: =AM11+AN11 -> 83.5 | AP11: =VLOOKUP(AO11,$B$44:$C$52,2) -> A | AR11: =AVERAGE(E11,I11,M11,Q11,U11,Y11,AC11,AG11,AK11,AO11) -> 64.45 | AS11: =RANK(AR11,$AR$5:$AR$33) -> 12 | AT11: C | AU11: A | AV11: C | AW11: A | AX11: A | AY11: Shamiso behaves well and participates positively in class. However, she needs to improve in Science, Maths, and English. Paying close attention during lessons and completing extra practice will help her strengthen her skills. Asking questions when unsure and revising daily will support her learning. I encourage her to remain focused and dedicated. With consistent effort, Shamiso can make great progress.
A12: 8 | B12: Mwansa Louise Elizabeth | C12: 29 | D12: 41 | E12: =C12+D12 -> 70 | F12: =VLOOKUP(E12,$B$44:$C$52,2) -> B | G12: 15 | H12: 22 | I12: =G12+H12 -> 37 | J12: =VLOOKUP(I12,$B$44:$C$52,2) -> F | K12: 23 | L12: 31 | M12: =K12+L12 -> 54 | N12: =VLOOKUP(M12,$B$44:$C$52,2) -> D | O12: 29 | P12: 37 | Q12: =O12+P12 -> 66 | R12: =VLOOKUP(Q12,$B$44:$C$52,2) -> C | S12: 23 | T12: 38 | U12: =S12+T12 -> 61 | V12: =VLOOKUP(U12,$B$44:$C$52,2) -> C | W12: 33 | X12: 35 | Y12: =W12+X12 -> 68 | Z12: =VLOOKUP(Y12,$B$44:$C$52,2) -> C | AA12: 30 | AB12: 44 | AC12: =AA12+AB12 -> 74 | AD12: =VLOOKUP(AC12,$B$44:$C$52,2) -> B | AE12: 36 | AF12: 53 | AG12: =AE12+AF12 -> 89 | AH12: =VLOOKUP(AG12,$B$44:$C$52,2) -> A | AI12: 33 | AJ12: 41 | AK12: =AI12+AJ12 -> 74 | AL12: =VLOOKUP(AK12,$B$44:$C$52,2) -> B | AM12: 25.6 | AN12: 49 | AO12: =AM12+AN12 -> 74.6 | AP12: =VLOOKUP(AO12,$B$44:$C$52,2) -> B | AR12: =AVERAGE(E12,I12,M12,Q12,U12,Y12,AC12,AG12,AK12,AO12) -> 66.76 | AS12: =RANK(AR12,$AR$5:$AR$33) -> 10 | AT12: C | AU12: C | AV12: C | AW12: C | AX12: D | AY12: Louise displays average behaviour and often moves around a lot, which affects her concentration. She needs improvement in Science, Maths, and English. Staying focused in class and reducing unnecessary movement will help improve her understanding. Regular practice at home and revising key concepts will support her progress. With greater focus and discipline, Louise can achieve stronger academic results. I encourage her to stay motivated and committed.
A13: 9 | B13: Patel Maahir | C13: 23 | D13: 30 | E13: =C13+D13 -> 53 | F13: =VLOOKUP(E13,$B$44:$C$52,2) -> D | G13: 26 | H13: 43 | I13: =G13+H13 -> 69 | J13: =VLOOKUP(I13,$B$44:$C$52,2) -> C | K13: 34 | L13: 40 | M13: =K13+L13 -> 74 | N13: =VLOOKUP(M13,$B$44:$C$52,2) -> B | O13: 26 | P13: 42 | Q13: =O13+P13 -> 68 | R13: =VLOOKUP(Q13,$B$44:$C$52,2) -> C | S13: 30 | T13: 50 | U13: =S13+T13 -> 80 | V13: =VLOOKUP(U13,$B$44:$C$52,2) -> A | W13: 37 | X13: 46 | Y13: =W13+X13 -> 83 | Z13: =VLOOKUP(Y13,$B$44:$C$52,2) -> A | AA13: 31 | AB13: 52 | AC13: =AA13+AB13 -> 83 | AD13: =VLOOKUP(AC13,$B$44:$C$52,2) -> A | AE13: 28 | AF13: 54 | AG13: =AE13+AF13 -> 82 | AH13: =VLOOKUP(AG13,$B$44:$C$52,2) -> A | AI13: 30 | AJ13: 51 | AK13: =AI13+AJ13 -> 81 | AL13: =VLOOKUP(AK13,$B$44:$C$52,2) -> A | AM13: 24.9 | AN13: 38 | AO13: =AM13+AN13 -> 62.9 | AP13: =VLOOKUP(AO13,$B$44:$C$52,2) -> C | AR13: =AVERAGE(E13,I13,M13,Q13,U13,Y13,AC13,AG13,AK13,AO13) -> 73.59 | AS13: =RANK(AR13,$AR$5:$AR$33) -> 6 | AT13: A | AU13: A+ | AV13: C | AW13: C | AX13: B | AY13: Maahir demonstrates excellent behaviour and consistently shows a positive attitude towards learning. His academic performance is very strong across all subjects. To extend his skills further, he should continue exploring challenging tasks and developing independent study habits. Engaging confidently in discussions will enrich his learning. Maahir is encouraged to maintain his outstanding effort and continue striving for excellence.
A14: 10 | B14: Aloyo Viola | C14: 26 | D14: 33 | E14: =C14+D14 -> 59 | F14: =VLOOKUP(E14,$B$44:$C$52,2) -> D | G14: 8 | H14: 16 | I14: =G14+H14 -> 24 | J14: =VLOOKUP(I14,$B$44:$C$52,2) -> G | K14: 18 | L14: 28 | M14: =K14+L14 -> 46 | N14: =VLOOKUP(M14,$B$44:$C$52,2) -> E | O14: 25 | P14: 27 | Q14: =O14+P14 -> 52 | R14: =VLOOKUP(Q14,$B$44:$C$52,2) -> D | S14: 17 | T14: 37 | U14: =S14+T14 -> 54 | V14: =VLOOKUP(U14,$B$44:$C$52,2) -> D | W14: 21 | X14: 33 | Y14: =W14+X14 -> 54 | Z14: =VLOOKUP(Y14,$B$44:$C$52,2) -> D | AA14: 11 | AB14: 42 | AC14: =AA14+AB14 -> 53 | AD14: =VLOOKUP(AC14,$B$44:$C$52,2) -> D | AE14: 26 | AF14: 40 | AG14: =AE14+AF14 -> 66 | AH14: =VLOOKUP(AG14,$B$44:$C$52,2) -> C | AI14: 30 | AJ14: 43 | AK14: =AI14+AJ14 -> 73 | AL14: =VLOOKUP(AK14,$B$44:$C$52,2) -> B | AM14: 19.5 | AN14: 35 | AO14: =AM14+AN14 -> 54.5 | AP14: =VLOOKUP(AO14,$B$44:$C$52,2) -> D | AR14: =AVERAGE(E14,I14,M14,Q14,U14,Y14,AC14,AG14,AK14,AO14) -> 53.55 | AS14: =RANK(AR14,$AR$5:$AR$33) -> 21 | AT14: C | AU14: C | AV14: C | AW14: C | AX14: C | AY14: Viola maintains good behaviour and shows willingness to learn. She needs improvement in Science, Maths, and English. Strengthening her focus and completing tasks carefully will support her progress in these subjects. Regular revision and independent practice at home will help build confidence. I encourage her to keep working hard and stay dedicated. With determination, Viola can achieve better results.
A15: 11 | B15: Mohamed Moaz | C15: 16 | D15: 14 | E15: =C15+D15 -> 30 | F15: =VLOOKUP(E15,$B$44:$C$52,2) -> F | G15: 15 | H15: 17 | I15: =G15+H15 -> 32 | J15: =VLOOKUP(I15,$B$44:$C$52,2) -> F | K15: 19 | L15: 23 | M15: =K15+L15 -> 42 | N15: =VLOOKUP(M15,$B$44:$C$52,2) -> E | O15: 19 | P15: 16 | Q15: =O15+P15 -> 35 | R15: =VLOOKUP(Q15,$B$44:$C$52,2) -> F | S15: 17 | T15: 26 | U15: =S15+T15 -> 43 | V15: =VLOOKUP(U15,$B$44:$C$52,2) -> E | W15: 22 | X15: 30 | Y15: =W15+X15 -> 52 | Z15: =VLOOKUP(Y15,$B$44:$C$52,2) -> D | AA15: 12 | AB15: 19 | AC15: =AA15+AB15 -> 31 | AD15: =VLOOKUP(AC15,$B$44:$C$52,2) -> F | AE15: 27 | AF15: 54 | AG15: =AE15+AF15 -> 81 | AH15: =VLOOKUP(AG15,$B$44:$C$52,2) -> A | AI15: 25 | AJ15: 40 | AK15: =AI15+AJ15 -> 65 | AL15: =VLOOKUP(AK15,$B$44:$C$52,2) -> C | AM15: 24.9 | AN15: 46 | AO15: =AM15+AN15 -> 70.9 | AP15: =VLOOKUP(AO15,$B$44:$C$52,2) -> B | AR15: =AVERAGE(E15,I15,M15,Q15,U15,Y15,AC15,AG15,AK15,AO15) -> 48.19 | AS15: =RANK(AR15,$AR$5:$AR$33) -> 23 | AT15: C | AU15: C | AV15: C | AW15: C | AX15: C | AY15: Moaz is generally well-behaved and interacts positively with others. His performance in Science, Maths, and English needs improvement. Staying attentive, participating more actively, and completing all class tasks will support his academic development. Additional practice at home and reviewing lessons will strengthen his understanding. Moaz is encouraged to remain motivated and take responsibility for his learning. With effort, he can achieve steady improvement.
A16: 12 | B16: Mutonga Israel | C16: 21 | D16: 34 | E16: =C16+D16 -> 55 | F16: =VLOOKUP(E16,$B$44:$C$52,2) -> D | G16: 7 | H16: 19 | I16: =G16+H16 -> 26 | J16: =VLOOKUP(I16,$B$44:$C$52,2) -> G | K16: 14 | L16: 24 | M16: =K16+L16 -> 38 | N16: =VLOOKUP(M16,$B$44:$C$52,2) -> F | O16: 32 | P16: 41 | Q16: =O16+P16 -> 73 | R16: =VLOOKUP(Q16,$B$44:$C$52,2) -> B | S16: 28 | T16: 40 | U16: =S16+T16 -> 68 | V16: =VLOOKUP(U16,$B$44:$C$52,2) -> C | W16: 24 | X16: 36 | Y16: =W16+X16 -> 60 | Z16: =VLOOKUP(Y16,$B$44:$C$52,2) -> C | AA16: 20 | AB16: 28 | AC16: =AA16+AB16 -> 48 | AD16: =VLOOKUP(AC16,$B$44:$C$52,2) -> E | AE16: 29 | AF16: 45 | AG16: =AE16+AF16 -> 74 | AH16: =VLOOKUP(AG16,$B$44:$C$52,2) -> B | AI16: 31 | AJ16: 35 | AK16: =AI16+AJ16 -> 66 | AL16: =VLOOKUP(AK16,$B$44:$C$52,2) -> C | AM16: 24.7 | AN16: 48 | AO16: =AM16+AN16 -> 72.7 | AP16: =VLOOKUP(AO16,$B$44:$C$52,2) -> B | AR16: =AVERAGE(E16,I16,M16,Q16,U16,Y16,AC16,AG16,AK16,AO16) -> 58.07 | AS16: =RANK(AR16,$AR$5:$AR$33) -> 16 | AT16: C | AU16: B | AV16: C | AW16: C | AX16: C | AY16: Israel behaves well overall but becomes easily distracted, which affects his performance. He needs to improve in Science, Maths, and English. Staying focused during lessons and managing distractions will greatly help his learning. Extra practice at home, reading regularly, and revising daily will support improvement. Israel is encouraged to participate more actively and ask questions for clarity. With consistent effort, he can make strong academic progress.
A17: 13 | B17: Abdulle Abdullahi | C17: 22 | D17: 31 | E17: =C17+D17 -> 53 | F17: =VLOOKUP(E17,$B$44:$C$52,2) -> D | G17: 19 | H17: 33 | I17: =G17+H17 -> 52 | J17: =VLOOKUP(I17,$B$44:$C$52,2) -> D | K17: 28 | L17: 38 | M17: =K17+L17 -> 66 | N17: =VLOOKUP(M17,$B$44:$C$52,2) -> C | O17: 26 | P17: 29 | Q17: =O17+P17 -> 55 | R17: =VLOOKUP(Q17,$B$44:$C$52,2) -> D | S17: 17 | T17: 33 | U17: =S17+T17 -> 50 | V17: =VLOOKUP(U17,$B$44:$C$52,2) -> D | W17: 27 | X17: 32 | Y17: 59 | Z17: =VLOOKUP(Y17,$B$44:$C$52,2) -> D | AA17: 18 | AB17: 31 | AC17: =AA17+AB17 -> 49 | AD17: =VLOOKUP(AC17,$B$44:$C$52,2) -> E | AE17: 22 | AF17: 32 | AG17: =AE17+AF17 -> 54 | AH17: =VLOOKUP(AG17,$B$44:$C$52,2) -> D | AI17: 27 | AJ17: 43 | AK17: =AI17+AJ17 -> 70 | AL17: =VLOOKUP(AK17,$B$44:$C$52,2) -> B | AM17: 24.7 | AN17: 46 | AO17: =AM17+AN17 -> 70.7 | AP17: =VLOOKUP(AO17,$B$44:$C$52,2) -> B | AR17: =AVERAGE(E17,I17,M17,Q17,U17,Y17,AC17,AG17,AK17,AO17) -> 57.87 | AS17: =RANK(AR17,$AR$5:$AR$33) -> 18 | AT17: C | AU17: C | AV17: C | AW17: C | AX17: A | AY17: Abdullahi is a polite and well-behaved learner who engages positively in class activities. His academic performance shows potential, but he needs to put in more consistent effort to achieve better results. He would benefit from improving his concentration during lessons and completing tasks with greater care. Regular revision at home and seeking clarification when unsure will support his progress. I encourage him to remain committed and to stay focused during class. With steady effort, Abdullahi can make significant improvement.
A18: 14 | B18: Sillitoe Alan | C18: 32 | D18: 40 | E18: =C18+D18 -> 72 | F18: =VLOOKUP(E18,$B$44:$C$52,2) -> B | G18: 18 | H18: 27 | I18: =G18+H18 -> 45 | J18: =VLOOKUP(I18,$B$44:$C$52,2) -> E | K18: 19 | L18: 36 | M18: =K18+L18 -> 55 | N18: =VLOOKUP(M18,$B$44:$C$52,2) -> D | O18: 32 | P18: 50 | Q18: =O18+P18 -> 82 | R18: =VLOOKUP(Q18,$B$44:$C$52,2) -> A | S18: 29 | T18: 43 | U18: =S18+T18 -> 72 | V18: =VLOOKUP(U18,$B$44:$C$52,2) -> B | W18: 30 | X18: 37 | Y18: =W18+X18 -> 67 | Z18: =VLOOKUP(Y18,$B$44:$C$52,2) -> C | AA18: 17 | AB18: 20 | AC18: =AA18+AB18 -> 37 | AD18: =VLOOKUP(AC18,$B$44:$C$52,2) -> F | AE18: 29 | AF18: 44 | AG18: =AE18+AF18 -> 73 | AH18: =VLOOKUP(AG18,$B$44:$C$52,2) -> B | AI18: 31 | AJ18: 40 | AK18: =AI18+AJ18 -> 71 | AL18: =VLOOKUP(AK18,$B$44:$C$52,2) -> B | AM18: 26 | AN18: 47 | AO18: =AM18+AN18 -> 73 | AP18: =VLOOKUP(AO18,$B$44:$C$52,2) -> B | AR18: =AVERAGE(E18,I18,M18,Q18,U18,Y18,AC18,AG18,AK18,AO18) -> 64.7 | AS18: =RANK(AR18,$AR$5:$AR$33) -> 11 | AT18: C | AU18: B | AV18: C | AW18: C | AX18: B | AY18: Aaban behaves reasonably well but is easily distracted, which affects his concentration in class. His academic performance is good when he remains focused. He needs to work on minimising distractions and staying engaged throughout lessons. Using short study routines and sitting away from distractions will support his progress. With improved concentration, Aaban can achieve even better results. I encourage him to stay committed and focused.
A19: 15 | B19: Kaoma Natasha | C19: 37 | D19: 48 | E19: =C19+D19 -> 85 | F19: =VLOOKUP(E19,$B$44:$C$52,2) -> A | G19: 24 | H19: 45 | I19: =G19+H19 -> 69 | J19: =VLOOKUP(I19,$B$44:$C$52,2) -> C | K19: 32 | L19: 50 | M19: =K19+L19 -> 82 | N19: =VLOOKUP(M19,$B$44:$C$52,2) -> A | O19: 33 | P19: 53 | Q19: =O19+P19 -> 86 | R19: =VLOOKUP(Q19,$B$44:$C$52,2) -> A | S19: 26 | T19: 45 | U19: =S19+T19 -> 71 | V19: =VLOOKUP(U19,$B$44:$C$52,2) -> B | W19: 40 | X19: 35 | Y19: =W19+X19 -> 75 | Z19: =VLOOKUP(Y19,$B$44:$C$52,2) -> B | AA19: 35 | AB19: 49 | AC19: =AA19+AB19 -> 84 | AD19: =VLOOKUP(AC19,$B$44:$C$52,2) -> A | AE19: 32 | AF19: 52 | AG19: =AE19+AF19 -> 84 | AH19: =VLOOKUP(AG19,$B$44:$C$52,2) -> A | AI19: 33 | AJ19: 54 | AK19: =AI19+AJ19 -> 87 | AL19: =VLOOKUP(AK19,$B$44:$C$52,2) -> A | AM19: 23.7 | AN19: 49 | AO19: =AM19+AN19 -> 72.7 | AP19: =VLOOKUP(AO19,$B$44:$C$52,2) -> B | AR19: =AVERAGE(E19,I19,M19,Q19,U19,Y19,AC19,AG19,AK19,AO19) -> 79.57 | AS19: =RANK(AR19,$AR$5:$AR$33) -> 2 | AT19: C | AU19: B | AV19: C | AW19: C | AX19: B | AY19: Natasha is a very well-behaved student who always sets a positive example for others. Her academic performance is excellent, and she shows great commitment to her studies. To extend her abilities further, she should continue challenging herself with higher-level tasks. Continued reading and independent study will help deepen her knowledge. Natasha is encouraged to maintain her outstanding attitude and keep striving for excellence.
A20: 16 | B20: Chauhan Humera | C20: 30 | D20: 42 | E20: =C20+D20 -> 72 | F20: =VLOOKUP(E20,$B$44:$C$52,2) -> B | G20: 19 | H20: 38 | I20: =G20+H20 -> 57 | J20: =VLOOKUP(I20,$B$44:$C$52,2) -> D | K20: 26 | L20: 43 | M20: =K20+L20 -> 69 | N20: =VLOOKUP(M20,$B$44:$C$52,2) -> C | O20: 34 | P20: 49 | Q20: =O20+P20 -> 83 | R20: =VLOOKUP(Q20,$B$44:$C$52,2) -> A | S20: 32 | T20: 51 | U20: =S20+T20 -> 83 | V20: =VLOOKUP(U20,$B$44:$C$52,2) -> A | W20: 40 | X20: 52 | Y20: =W20+X20 -> 92 | Z20: =VLOOKUP(Y20,$B$44:$C$52,2) -> A* | AA20: 30 | AB20: 49 | AC20: =AA20+AB20 -> 79 | AD20: =VLOOKUP(AC20,$B$44:$C$52,2) -> B | AE20: 28 | AF20: 46 | AG20: =AE20+AF20 -> 74 | AH20: =VLOOKUP(AG20,$B$44:$C$52,2) -> B | AI20: 31 | AJ20: 54 | AK20: =AI20+AJ20 -> 85 | AL20: =VLOOKUP(AK20,$B$44:$C$52,2) -> A | AM20: 22.5 | AN20: 48 | AO20: =AM20+AN20 -> 70.5 | AP20: =VLOOKUP(AO20,$B$44:$C$52,2) -> B | AR20: =AVERAGE(E20,I20,M20,Q20,U20,Y20,AC20,AG20,AK20,AO20) -> 76.45 | AS20: =RANK(AR20,$AR$5:$AR$33) -> 4 | AT20: C | AU20: B | AV20: C | AW20: C | AX20: A | AY20: Humera maintains good behaviour and displays a positive attitude towards learning. Her academic performance is strong, and she consistently produces good work. I would also like to commend her for confidently presenting at TEDx, a remarkable achievement that reflects her dedication and courage. To reach even higher levels, she should continue building her confidence in class discussions and challenge herself with extended tasks. Maintaining her current study habits and practising regular revision will help her excel. I encourage Humera to keep up her excellent attitude and continue striving for excellence.
A21: 17 | B21: Ntinda Joy | C21: 31 | D21: 31 | E21: =C21+D21 -> 62 | F21: =VLOOKUP(E21,$B$44:$C$52,2) -> C | G21: 16 | H21: 42 | I21: =G21+H21 -> 58 | J21: =VLOOKUP(I21,$B$44:$C$52,2) -> D | K21: 9 | L21: 25 | M21: =K21+L21 -> 34 | N21: =VLOOKUP(M21,$B$44:$C$52,2) -> F | O21: 28 | P21: 36 | Q21: =O21+P21 -> 64 | R21: =VLOOKUP(Q21,$B$44:$C$52,2) -> C | S21: 25 | T21: 34 | U21: =S21+T21 -> 59 | V21: =VLOOKUP(U21,$B$44:$C$52,2) -> D | W21: 16 | X21: 23 | Y21: =W21+X21 -> 39 | Z21: =VLOOKUP(Y21,$B$44:$C$52,2) -> F | AA21: 14 | AB21: 32 | AC21: =AA21+AB21 -> 46 | AD21: =VLOOKUP(AC21,$B$44:$C$52,2) -> E | AE21: 27 | AF21: 47 | AG21: =AE21+AF21 -> 74 | AH21: =VLOOKUP(AG21,$B$44:$C$52,2) -> B | AI21: 27 | AJ21: 41 | AK21: =AI21+AJ21 -> 68 | AL21: =VLOOKUP(AK21,$B$44:$C$52,2) -> C | AM21: 27 | AN21: 54 | AO21: =AM21+AN21 -> 81 | AP21: =VLOOKUP(AO21,$B$44:$C$52,2) -> A | AR21: =AVERAGE(E21,I21,M21,Q21,U21,Y21,AC21,AG21,AK21,AO21) -> 58.5 | AS21: =RANK(AR21,$AR$5:$AR$33) -> 15 | AT21: C | AU21: C | AV21: C | AW21: C | AX21: C | AY21: Joy shows average behaviour and often moves around unnecessarily, which affects her focus. She needs to improve in Science, Maths, and English. Staying seated, listening attentively, and following instructions will help her concentrate better. Regular revision and practising core skills at home will support her learning. With improved discipline and commitment, Joy can achieve much stronger results. I encourage her to keep trying and stay motivated.
A22: 18 | B22: Msoni Zhange | C22: 33 | D22: 40 | E22: =C22+D22 -> 73 | F22: =VLOOKUP(E22,$B$44:$C$52,2) -> B | G22: 5 | H22: 20 | I22: =G22+H22 -> 25 | J22: =VLOOKUP(I22,$B$44:$C$52,2) -> G | K22: 12 | L22: 23 | M22: =K22+L22 -> 35 | N22: =VLOOKUP(M22,$B$44:$C$52,2) -> F | O22: 26 | P22: 49 | Q22: =O22+P22 -> 75 | R22: =VLOOKUP(Q22,$B$44:$C$52,2) -> B | S22: 27 | T22: 37 | U22: =S22+T22 -> 64 | V22: =VLOOKUP(U22,$B$44:$C$52,2) -> C | W22: 28 | X22: 26 | Y22: =W22+X22 -> 54 | Z22: =VLOOKUP(Y22,$B$44:$C$52,2) -> D | AA22: 20 | AB22: 41 | AC22: =AA22+AB22 -> 61 | AD22: =VLOOKUP(AC22,$B$44:$C$52,2) -> C | AE22: 25 | AF22: 38 | AG22: =AE22+AF22 -> 63 | AH22: =VLOOKUP(AG22,$B$44:$C$52,2) -> C | AI22: 32 | AJ22: 41 | AK22: =AI22+AJ22 -> 73 | AL22: =VLOOKUP(AK22,$B$44:$C$52,2) -> B | AM22: 20.8 | AN22: 24 | AO22: =AM22+AN22 -> 44.8 | AP22: =VLOOKUP(AO22,$B$44:$C$52,2) -> E | AR22: =AVERAGE(E22,I22,M22,Q22,U22,Y22,AC22,AG22,AK22,AO22) -> 56.78 | AS22: =RANK(AR22,$AR$5:$AR$33) -> 19 | AT22: C | AU22: B | AV22: C | AW22: C | AX22: B | AY22: Zhange is generally well-behaved and polite. However, she needs to improve her performance in Science, Maths, and English. She would benefit from developing better focus during lessons and practising regularly at home. Using additional learning materials and reviewing class notes will help strengthen her understanding. I encourage Zhange to stay motivated and seek support whenever needed. With determination, she can make steady progress.
A23: 19 | B23: Nalishuwa Zeruiah | C23: 28 | D23: 41 | E23: =C23+D23 -> 69 | F23: =VLOOKUP(E23,$B$44:$C$52,2) -> C | G23: 24 | H23: 38 | I23: =G23+H23 -> 62 | J23: =VLOOKUP(I23,$B$44:$C$52,2) -> C | K23: 30 | L23: 26 | M23: =K23+L23 -> 56 | N23: =VLOOKUP(M23,$B$44:$C$52,2) -> D | O23: 34 | P23: 46 | Q23: =O23+P23 -> 80 | R23: =VLOOKUP(Q23,$B$44:$C$52,2) -> A | S23: 27 | T23: 42 | U23: =S23+T23 -> 69 | V23: =VLOOKUP(U23,$B$44:$C$52,2) -> C | W23: 40 | X23: 36 | Y23: =W23+X23 -> 76 | Z23: =VLOOKUP(Y23,$B$44:$C$52,2) -> B | AA23: 23 | AB23: 44 | AC23: =AA23+AB23 -> 67 | AD23: =VLOOKUP(AC23,$B$44:$C$52,2) -> C | AE23: 26 | AF23: 50 | AG23: =AE23+AF23 -> 76 | AH23: =VLOOKUP(AG23,$B$44:$C$52,2) -> B | AI23: 33 | AJ23: 50 | AK23: =AI23+AJ23 -> 83 | AL23: =VLOOKUP(AK23,$B$44:$C$52,2) -> A | AM23: 28 | AN23: 47 | AO23: =AM23+AN23 -> 75 | AP23: =VLOOKUP(AO23,$B$44:$C$52,2) -> B | AR23: =AVERAGE(E23,I23,M23,Q23,U23,Y23,AC23,AG23,AK23,AO23) -> 71.3 | AS23: =RANK(AR23,$AR$5:$AR$33) -> 7 | AT23: B | AU23: B | AV23: C | AW23: C | AX23: A | AY23: Zeruiah is a very well-behaved learner who consistently shows a positive attitude. Her academic performance is good, and she completes tasks to a high standard. To develop further, she should continue challenging herself with extension activities and practising independent study. Regular reading will also strengthen her skills. Zeruiah is encouraged to maintain her excellent attitude and continue striving for success.
A24: 20 | B24: Shalak Jad | C24: 27 | D24: 39 | E24: =C24+D24 -> 66 | F24: =VLOOKUP(E24,$B$44:$C$52,2) -> C | G24: 32 | H24: 48 | I24: =G24+H24 -> 80 | J24: =VLOOKUP(I24,$B$44:$C$52,2) -> A | K24: 26 | L24: 43 | M24: =K24+L24 -> 69 | N24: =VLOOKUP(M24,$B$44:$C$52,2) -> C | O24: 30 | P24: 43 | Q24: =O24+P24 -> 73 | R24: =VLOOKUP(Q24,$B$44:$C$52,2) -> B | S24: 37 | T24: 49 | U24: =S24+T24 -> 86 | V24: =VLOOKUP(U24,$B$44:$C$52,2) -> A | W24: 40 | X24: 54 | Y24: =W24+X24 -> 94 | Z24: =VLOOKUP(Y24,$B$44:$C$52,2) -> A* | AA24: 34 | AB24: 52 | AC24: =AA24+AB24 -> 86 | AD24: =VLOOKUP(AC24,$B$44:$C$52,2) -> A | AE24: 26 | AF24: 46 | AG24: =AE24+AF24 -> 72 | AH24: =VLOOKUP(AG24,$B$44:$C$52,2) -> B | AI24: 32 | AJ24: 54 | AK24: =AI24+AJ24 -> 86 | AL24: =VLOOKUP(AK24,$B$44:$C$52,2) -> A | AM24: 25 | AN24: 38 | AO24: =AM24+AN24 -> 63 | AP24: =VLOOKUP(AO24,$B$44:$C$52,2) -> C | AR24: =AVERAGE(E24,I24,M24,Q24,U24,Y24,AC24,AG24,AK24,AO24) -> 77.5 | AS24: =RANK(AR24,$AR$5:$AR$33) -> 3 | AT24: A | AU24: A+ | AV24: B | AW24: C | AX24: A | AY24: Jad consistently demonstrates very good behaviour and enthusiasm for learning. His academic performance is very strong across subjects. To further enrich his learning, he should continue developing his critical-thinking skills through independent tasks and wider reading. Participating even more confidently in class discussions will also benefit him. Jad is encouraged to maintain his high standards and keep up his excellent work.
A25: 21 | B25: Nyirenda Lauzi | C25: 27 | D25: 30 | E25: =C25+D25 -> 57 | F25: =VLOOKUP(E25,$B$44:$C$52,2) -> D | G25: 7 | H25: 25 | I25: =G25+H25 -> 32 | J25: =VLOOKUP(I25,$B$44:$C$52,2) -> F | K25: 18 | L25: 31 | M25: =K25+L25 -> 49 | N25: =VLOOKUP(M25,$B$44:$C$52,2) -> E | O25: 26 | P25: 56 | Q25: =O25+P25 -> 82 | R25: =VLOOKUP(Q25,$B$44:$C$52,2) -> A | S25: 31 | T25: 36 | U25: =S25+T25 -> 67 | V25: =VLOOKUP(U25,$B$44:$C$52,2) -> C | W25: 24 | X25: 33 | Y25: =W25+X25 -> 57 | Z25: =VLOOKUP(Y25,$B$44:$C$52,2) -> D | AA25: 22 | AB25: 36 | AC25: =AA25+AB25 -> 58 | AD25: =VLOOKUP(AC25,$B$44:$C$52,2) -> D | AE25: 26 | AF25: 50 | AG25: =AE25+AF25 -> 76 | AH25: =VLOOKUP(AG25,$B$44:$C$52,2) -> B | AI25: 28 | AJ25: 39 | AK25: =AI25+AJ25 -> 67 | AL25: =VLOOKUP(AK25,$B$44:$C$52,2) -> C | AM25: 29.7 | AN25: 51 | AO25: =AM25+AN25 -> 80.7 | AP25: =VLOOKUP(AO25,$B$44:$C$52,2) -> A | AR25: =AVERAGE(E25,I25,M25,Q25,U25,Y25,AC25,AG25,AK25,AO25) -> 62.57 | AS25: =RANK(AR25,$AR$5:$AR$33) -> 13 | AT25: C | AU25: D | AV25: C | AW25: C | AX25: D | AY25: Lauzi shows an average level of behaviour, and she sometimes needs reminders to remain fully focused. Academically she performs well, demonstrating good understanding of classwork. To reach her full potential, she should work on staying attentive during lessons and organising her tasks more effectively. Setting small study goals at home will help reinforce learning. With improved focus and consistency, Lauzi can continue to grow academically.
A26: 22 | B26: Hasan Aaban | C26: 31 | D26: 35 | E26: =C26+D26 -> 66 | F26: =VLOOKUP(E26,$B$44:$C$52,2) -> C | G26: 13 | H26: 53 | I26: =G26+H26 -> 66 | J26: =VLOOKUP(I26,$B$44:$C$52,2) -> C | K26: 29 | L26: 38 | M26: =K26+L26 -> 67 | N26: =VLOOKUP(M26,$B$44:$C$52,2) -> C | O26: 32 | P26: 32 | Q26: =O26+P26 -> 64 | R26: =VLOOKUP(Q26,$B$44:$C$52,2) -> C | S26: 28 | T26: 40 | U26: =S26+T26 -> 68 | V26: =VLOOKUP(U26,$B$44:$C$52,2) -> C | W26: 32 | X26: 39 | Y26: =W26+X26 -> 71 | Z26: =VLOOKUP(Y26,$B$44:$C$52,2) -> B | AA26: 33 | AB26: 40 | AC26: =AA26+AB26 -> 73 | AD26: =VLOOKUP(AC26,$B$44:$C$52,2) -> B | AE26: 24 | AF26: 44 | AG26: =AE26+AF26 -> 68 | AH26: =VLOOKUP(AG26,$B$44:$C$52,2) -> C | AI26: 32 | AJ26: 42 | AK26: =AI26+AJ26 -> 74 | AL26: =VLOOKUP(AK26,$B$44:$C$52,2) -> B | AM26: 25 | AN26: 40 | AO26: =AM26+AN26 -> 65 | AP26: =VLOOKUP(AO26,$B$44:$C$52,2) -> C | AR26: =AVERAGE(E26,I26,M26,Q26,U26,Y26,AC26,AG26,AK26,AO26) -> 68.2 | AS26: =RANK(AR26,$AR$5:$AR$33) -> 9 | AT26: C | AU26: D | AV26: C | AW26: C | AX26: D | AY26: Aaban behaves reasonably well but is easily distracted, which affects his concentration in class. His academic performance is good when he remains focused. He needs to work on minimising distractions and staying engaged throughout lessons. Using short study routines and sitting away from distractions will support his progress. With improved concentration, Aaban can achieve even better results. I encourage him to stay committed and focused.
A27: 23 | B27: Malijani Kasonde | C27: 30 | D27: 46 | E27: =C27+D27 -> 76 | F27: B | G27: 25 | H27: 41 | I27: =G27+H27 -> 66 | J27: =VLOOKUP(I27,$B$44:$C$52,2) -> C | K27: 29 | L27: 49 | M27: =K27+L27 -> 78 | N27: =VLOOKUP(M27,$B$44:$C$52,2) -> B | O27: 35 | P27: 38 | Q27: =O27+P27 -> 73 | R27: =VLOOKUP(Q27,$B$44:$C$52,2) -> B | S27: 35 | T27: 51 | U27: =S27+T27 -> 86 | V27: =VLOOKUP(U27,$B$44:$C$52,2) -> A | W27: 34 | X27: 46 | Y27: =W27+X27 -> 80 | Z27: =VLOOKUP(Y27,$B$44:$C$52,2) -> A | AA27: 39 | AB27: 59 | AC27: =AA27+AB27 -> 98 | AD27: =VLOOKUP(AC27,$B$44:$C$52,2) -> A* | AE27: 35 | AF27: 52 | AG27: =AE27+AF27 -> 87 | AH27: =VLOOKUP(AG27,$B$44:$C$52,2) -> A | AI27: 37 | AJ27: 56 | AK27: =AI27+AJ27 -> 93 | AL27: =VLOOKUP(AK27,$B$44:$C$52,2) -> A* | AM27: 23 | AN27: 49 | AO27: =AM27+AN27 -> 72 | AP27: =VLOOKUP(AO27,$B$44:$C$52,2) -> B | AR27: =AVERAGE(E27,I27,M27,Q27,U27,Y27,AC27,AG27,AK27,AO27) -> 80.9 | AS27: =RANK(AR27,$AR$5:$AR$33) -> 1 | AT27: C | AU27: A+ | AV27: C | AW27: C | AX27: A | AY27: Kasonde is a very well-behaved learner who approaches her work positively. Her academic performance is good, and she completes tasks to a satisfactory standard. She can improve further by challenging herself with more complex questions and participating more actively in class. Regular home revision will also strengthen her understanding. Kasonde is encouraged to continue her positive approach and show confidence in her abilities.
A28: 24 | B28: Mwiimbwa Chileleko | C28: 35 | D28: 44 | E28: =C28+D28 -> 79 | F28: =VLOOKUP(E28,$B$44:$C$52,2) -> B | G28: 25 | H28: 44 | I28: =G28+H28 -> 69 | J28: =VLOOKUP(I28,$B$44:$C$52,2) -> C | L28: 48 | M28: =K28+L28 -> 48 | N28: =VLOOKUP(M28,$B$44:$C$52,2) -> E | O28: 31 | P28: 43 | Q28: =O28+P28 -> 74 | R28: =VLOOKUP(Q28,$B$44:$C$52,2) -> B | S28: 31 | T28: 42 | U28: =S28+T28 -> 73 | V28: =VLOOKUP(U28,$B$44:$C$52,2) -> B | W28: 32 | X28: 40 | Y28: =W28+X28 -> 72 | Z28: =VLOOKUP(Y28,$B$44:$C$52,2) -> B | AA28: 28 | AB28: 50 | AC28: =AA28+AB28 -> 78 | AD28: =VLOOKUP(AC28,$B$44:$C$52,2) -> B | AE28: 27 | AF28: 51 | AG28: =AE28+AF28 -> 78 | AH28: =VLOOKUP(AG28,$B$44:$C$52,2) -> B | AI28: 38 | AJ28: 43 | AK28: =AI28+AJ28 -> 81 | AL28: =VLOOKUP(AK28,$B$44:$C$52,2) -> A | AM28: 20 | AN28: 39 | AO28: =AM28+AN28 -> 59 | AP28: =VLOOKUP(AO28,$B$44:$C$52,2) -> D | AR28: =AVERAGE(E28,I28,M28,Q28,U28,Y28,AC28,AG28,AK28,AO28) -> 71.1 | AS28: =RANK(AR28,$AR$5:$AR$33) -> 8 | AT28: C | AU28: A | AV28: C | AW28: C | AX28: A | AY28: Chileleko is a very well-behaved student, though he needs to improve his punctuality as late-coming affects his learning. Academically, he performs well and shows clear potential for further success. He can make even greater progress by maintaining focus and completing tasks with deeper detail. Ensuring he arrives on time will benefit his overall performance. I encourage Chileleko to keep up his good work and improve his punctuality.
A29: 25 | B29: Omar
A30: 26 | B30: Adeaze
A31: 27 | B31: Elijah
A32: 28
AH33: =VLOOKUP(AG33,$B$44:$C$52,2) -> U
B36: Average | E36: =AVERAGE(E5:E28) -> 63.375 | I36: =AVERAGE(I5:I28) -> 46.458333 | M36: =AVERAGE(M5:M28) -> 53.208333 | Q36: =AVERAGE(Q5:Q28) -> 67.666667 | U36: =AVERAGE(U5:U28) -> 65.291667 | Y36: =AVERAGE(Y5:Y28) -> 63.375 | AC36: =AVERAGE(AC5:AC28) -> 61.333333 | AG36: =AVERAGE(AG5:AG28) -> 73.625 | AK36: =AVERAGE(AK5:AK28) -> 76.333333 | AO36: =AVERAGE(AO5:AO28) -> 66.941667
B37: NO. Students | E37: =COUNT(E5:E28) -> 24 | I37: =COUNT(I5:I28) -> 24 | M37: =COUNT(M5:M28) -> 24 | Q37: =COUNT(Q5:Q28) -> 24 | U37: =COUNT(U5:U28) -> 24 | Y37: =COUNT(Y5:Y28) -> 24 | AC37: =COUNT(AC5:AC28) -> 24 | AG37: =COUNT(AG5:AG28) -> 24 | AK37: =COUNT(AK5:AK28) -> 24 | AO37: =COUNT(AO5:AO28) -> 24
B38: Pass | E38: =COUNTIF($E$5:$E$28,">49") -> 21 | I38: =COUNTIF($I$5:$I$28,">49") -> 12 | M38: =COUNTIF($M$5:$M$28,">49") -> 11 | Q38: =COUNTIF($Q$5:$Q$28,">49") -> 21 | U38: =COUNTIF($U$5:$U$28,">49") -> 22 | Y38: =COUNTIF($Y$5:$Y$28,">49") -> 21 | AC38: =COUNTIF($AC$5:$AC$28,">49") -> 15 | AG38: =COUNTIF($AG$5:$AG$28,">49") -> 24 | AK38: =COUNTIF($AK$5:$AK$28,">49") -> 24 | AO38: =COUNTIF($AO$5:$AO$28,">49") -> 22
B39: Fail | E39: =COUNTIF(E5:E28,"<50") -> 3 | I39: =COUNTIF(I5:I28,"<50") -> 12 | M39: =COUNTIF(M5:M28,"<50") -> 13 | Q39: =COUNTIF(Q5:Q28,"<50") -> 3 | U39: =COUNTIF(U5:U28,"<50") -> 2 | Y39: =COUNTIF(Y5:Y28,"<50") -> 3 | AC39: =COUNTIF(AC5:AC28,"<50") -> 9 | AG39: =COUNTIF(AG5:AG28,"<50") -> 0 | AK39: =COUNTIF(AK5:AK28,"<50") -> 0 | AO39: =COUNTIF(AO5:AO28,"<50") -> 2
B40: Pass Rate % | E40: =E38*100/E37 -> 87.5 | I40: =I38*100/I37 -> 50 | M40: =M38*100/M37 -> 45.833333 | Q40: =Q38*100/Q37 -> 87.5 | U40: =U38*100/U37 -> 91.666667 | Y40: =Y38*100/Y37 -> 87.5 | AC40: =AC38*100/AC37 -> 62.5 | AG40: =AG38*100/AG37 -> 100 | AK40: =AK38*100/AK37 -> 100 | AO40: =AO38*100/AO37 -> 91.666667
A44: 00-19 | B44: 0 | C44: U
A45: 20-29 | B45: 20 | C45: G
A46: 30-39 | B46: 30 | C46: F
A47: 40-49 | B47: 40 | C47: E
A48: 50-59 | B48: 50 | C48: D
A49: 60-69 | B49: 60 | C49: C
A50: 70-79 | B50: 70 | C50: B
A51: 80-89 | B51: 80 | C51: A
A52: 90-100 | B52: 90 | C52: A*

Sheet LS1B
A1: HOME
A3: Roll N0. | B3: Name | C3: English | G3: Mathematics | K3: Science | O3: Global Perspectives | S3: New Computing | W3: Business Studies | AA3: French | AE3: Art | AI3: MDD | AM3: PE | AR3: AVERAGE | AS3: POSITION | AT3: CREATIVITY | AU3: RESPECT | AV3: EXCELLENCE | AW3: EMPATHY | AX3: DISCIPLINE | AY3: CLASS TEACHER'S COMMENT
C4: Formative | D4: Summative | E4: Final Mark | F4: Grade | G4: Formative | H4: Summative | I4: Final Mark | J4: Grade | K4: Formative | L4: Summative | M4: Final Mark | N4: Grade | O4: Formative | P4: Summative | Q4: Final Mark | R4: Grade | S4: Formative | T4: Summative | U4: Final Mark | V4: Grade | W4: Formative | X4: Summative | Y4: Final Mark | Z4: Grade | AA4: Formative | AB4: Summative | AC4: Final Mark | AD4: Grade | AE4: Formative | AF4: Summative | AG4: Final Mark | AH4: Grade | AI4: Formative | AJ4: Summative | AK4: Final Mark | AL4: Grade | AM4: Formative | AN4: Summative | AO4: Final Mark | AP4: Grade
A5: 1 | B5: Nhundu Nokutenda | C5: 28 | D5: 36 | E5: =C5+D5 -> 64 | F5: =VLOOKUP(E5,$B$43:$C$51,2) -> C | G5: 18 | H5: 21 | I5: =G5+H5 -> 39 | J5: =VLOOKUP(I5,$B$43:$C$51,2) -> F | K5: 21 | L5: 30.1 | M5: =K5+L5 -> 51.1 | N5: =VLOOKUP(M5,$B$43:$C$51,2) -> D | O5: 28 | P5: 42 | Q5: =O5+P5 -> 70 | R5: =VLOOKUP(Q5,$B$43:$C$51,2) -> B | S5: 20 | T5: 37 | U5: =S5+T5 -> 57 | V5: =VLOOKUP(U5,$B$43:$C$51,2) -> D | W5: 24 | X5: 42 | Y5: =W5+X5 -> 66 | Z5: =VLOOKUP(Y5,$B$43:$C$51,2) -> C | AA5: 27 | AB5: 36 | AC5: =AA5+AB5 -> 63 | AD5: =VLOOKUP(AC5,$B$43:$C$51,2) -> C | AE5: 27 | AF5: 55 | AG5: =AE5+AF5 -> 82 | AH5: =VLOOKUP(AG5,$B$43:$C$51,2) -> A | AI5: 25 | AJ5: 53 | AK5: =AI5+AJ5 -> 78 | AL5: =VLOOKUP(AK5,$B$43:$C$51,2) -> B | AM5: 20 | AN5: 47 | AO5: =AM5+AN5 -> 67 | AP5: =VLOOKUP(AO5,$B$43:$C$51,2) -> C | AR5: =AVERAGE(E5,I5,M5,Q5,U5,Y5,AC5,AG5,AK5,AO5) -> 63.71 | AS5: =RANK(AR5,$AR$5:$AR$32) -> 19 | AT5: A | AU5: A+ | AV5: A | AW5: A+ | AX5: A | AY5: Nokutenda shows generally good behavior in class, following instructions and participating in activities with a positive attitude. She is respectful toward teachers and classmates and complete assignments on time. However, there are times when her focus lapses, especially during independent work, and she would benefit from engaging more actively in class discussions. With increased concentration and confidence, Nokutenda has the potential to make even greater progress this term.
A6: 2 | B6: Maponga Taonga | C6: 29 | D6: 31 | E6: =C6+D6 -> 60 | F6: =VLOOKUP(E6,$B$43:$C$51,2) -> C | G6: 6 | H6: 13 | I6: =G6+H6 -> 19 | J6: =VLOOKUP(I6,$B$43:$C$51,2) -> U | K6: 17.8 | L6: 24 | M6: =K6+L6 -> 41.8 | N6: =VLOOKUP(M6,$B$43:$C$51,2) -> E | O6: 25 | P6: 27 | Q6: =O6+P6 -> 52 | R6: =VLOOKUP(Q6,$B$43:$C$51,2) -> D | S6: 19 | T6: 37 | U6: =S6+T6 -> 56 | V6: =VLOOKUP(U6,$B$43:$C$51,2) -> D | W6: 22 | X6: 28 | Y6: =W6+X6 -> 50 | Z6: =VLOOKUP(Y6,$B$43:$C$51,2) -> D | AA6: 17 | AB6: 31 | AC6: =AA6+AB6 -> 48 | AD6: =VLOOKUP(AC6,$B$43:$C$51,2) -> E | AE6: 27 | AF6: 44 | AG6: =AE6+AF6 -> 71 | AH6: =VLOOKUP(AG6,$B$43:$C$51,2) -> B | AI6: 28 | AJ6: 27 | AK6: =AI6+AJ6 -> 55 | AL6: =VLOOKUP(AK6,$B$43:$C$51,2) -> D | AM6: 19 | AN6: 45 | AO6: =AM6+AN6 -> 64 | AP6: =VLOOKUP(AO6,$B$43:$C$51,2) -> C | AR6: =AVERAGE(E6,I6,M6,Q6,U6,Y6,AC6,AG6,AK6,AO6) -> 51.68 | AS6: =RANK(AR6,$AR$5:$AR$32) -> 25 | AT6: B | AU6: A | AV6: A | AW6: A | AX6: B | AY6: Taonga is a polite and cooperative student who has shown some effort this term. However, his academic performance requires significant improvement, particularly in English, Mathematics, and Science, as well as in other subjects. He would benefit greatly from close monitoring, regular revision, and attending support classes. I encourage strong cooperation between home and school to support his progress.
A7: 3 | B7: Chilufya Loisa Njavwa | C7: 24 | D7: 39 | E7: =C7+D7 -> 63 | F7: =VLOOKUP(E7,$B$43:$C$51,2) -> C | G7: 14 | H7: 20 | I7: =G7+H7 -> 34 | J7: =VLOOKUP(I7,$B$43:$C$51,2) -> F | K7: 20.2 | L7: 28.8 | M7: =K7+L7 -> 49 | N7: =VLOOKUP(M7,$B$43:$C$51,2) -> E | O7: 29 | P7: 33 | Q7: =O7+P7 -> 62 | R7: =VLOOKUP(Q7,$B$43:$C$51,2) -> C | S7: 25 | T7: 47 | U7: =S7+T7 -> 72 | V7: =VLOOKUP(U7,$B$43:$C$51,2) -> B | W7: 39 | X7: 54 | Y7: =W7+X7 -> 93 | Z7: =VLOOKUP(Y7,$B$43:$C$51,2) -> A* | AA7: 28 | AB7: 36 | AC7: =AA7+AB7 -> 64 | AD7: =VLOOKUP(AC7,$B$43:$C$51,2) -> C | AE7: 28 | AF7: 50 | AG7: =AE7+AF7 -> 78 | AH7: =VLOOKUP(AG7,$B$43:$C$51,2) -> B | AI7: 43 | AJ7: 29 | AK7: =AI7+AJ7 -> 72 | AL7: =VLOOKUP(AK7,$B$43:$C$51,2) -> B | AM7: 20 | AN7: 45 | AO7: =AM7+AN7 -> 65 | AP7: =VLOOKUP(AO7,$B$43:$C$51,2) -> C | AR7: =AVERAGE(E7,I7,M7,Q7,U7,Y7,AC7,AG7,AK7,AO7) -> 65.2 | AS7: =RANK(AR7,$AR$5:$AR$32) -> 16 | AT7: A | AU7: B | AV7: B | AW7: A+ | AX7: B | AY7: Njavwa is an energetic and friendly learner who enjoys interacting with peers. Although she has the potential to perform well, her distractibility affects the quality of her work. She must improve her concentration and develop consistent study habits. Mathematics and Science especially require additional support. I recommend structured revision, limited distractions at home, and regular teacher-parent follow-ups.
A8: 4 | B8: Ncube Nkosazana | C8: 32 | D8: 40 | E8: =C8+D8 -> 72 | F8: =VLOOKUP(E8,$B$43:$C$51,2) -> B | G8: 14 | H8: 32 | I8: =G8+H8 -> 46 | J8: =VLOOKUP(I8,$B$43:$C$51,2) -> E | K8: 25 | L8: 30 | M8: =K8+L8 -> 55 | N8: =VLOOKUP(M8,$B$43:$C$51,2) -> D | O8: 28 | P8: 47 | Q8: =O8+P8 -> 75 | R8: =VLOOKUP(Q8,$B$43:$C$51,2) -> B | S8: 37 | T8: 50 | U8: =S8+T8 -> 87 | V8: =VLOOKUP(U8,$B$43:$C$51,2) -> A | W8: 26 | X8: 45 | Y8: =W8+X8 -> 71 | Z8: =VLOOKUP(Y8,$B$43:$C$51,2) -> B | AA8: 29 | AB8: 43 | AC8: =AA8+AB8 -> 72 | AD8: =VLOOKUP(AC8,$B$43:$C$51,2) -> B | AE8: 32 | AF8: 45 | AG8: =AE8+AF8 -> 77 | AH8: =VLOOKUP(AG8,$B$43:$C$51,2) -> B | AI8: 27 | AJ8: 47 | AK8: =AI8+AJ8 -> 74 | AL8: =VLOOKUP(AK8,$B$43:$C$51,2) -> B | AM8: 15 | AN8: 46 | AO8: =AM8+AN8 -> 61 | AP8: =VLOOKUP(AO8,$B$43:$C$51,2) -> C | AR8: =AVERAGE(E8,I8,M8,Q8,U8,Y8,AC8,AG8,AK8,AO8) -> 69 | AS8: =RANK(AR8,$AR$5:$AR$32) -> 11 | AT8: A | AU8: A+ | AV8: A | AW8: A+ | AX8: A+ | AY8: Nkosazana is a polite and cooperative student who has demonstrated some effort this term. However, her academic progress requires improvement, with Mathematics being a primary area of focus. To support her development, she would benefit greatly from close monitoring, consistent revision, and participation in support classes. I strongly encourage close collaboration between home and school to help Nkosazana build her confidence and skills. With targeted support and sustained effort, she has the potential to achieve stronger results.
A9: 5 | B9: Munshi Mahira | C9: 29 | D9: 42 | E9: =C9+D9 -> 71 | F9: =VLOOKUP(E9,$B$43:$C$51,2) -> B | G9: 21 | H9: 38 | I9: =G9+H9 -> 59 | J9: =VLOOKUP(I9,$B$43:$C$51,2) -> D | K9: 25 | L9: 30.6 | M9: =K9+L9 -> 55.6 | N9: =VLOOKUP(M9,$B$43:$C$51,2) -> D | O9: 24 | P9: 38 | Q9: =O9+P9 -> 62 | R9: =VLOOKUP(Q9,$B$43:$C$51,2) -> C | S9: 31 | T9: 44 | U9: =S9+T9 -> 75 | V9: =VLOOKUP(U9,$B$43:$C$51,2) -> B | W9: 32 | X9: 43 | Y9: =W9+X9 -> 75 | Z9: =VLOOKUP(Y9,$B$43:$C$51,2) -> B | AA9: 27 | AB9: 50 | AC9: =AA9+AB9 -> 77 | AD9: =VLOOKUP(AC9,$B$43:$C$51,2) -> B | AE9: 35 | AF9: 39 | AG9: =AE9+AF9 -> 74 | AH9: =VLOOKUP(AG9,$B$43:$C$51,2) -> B | AI9: 28 | AJ9: 34 | AK9: =AI9+AJ9 -> 62 | AL9: =VLOOKUP(AK9,$B$43:$C$51,2) -> C | AM9: 17.6 | AN9: 38 | AO9: =AM9+AN9 -> 55.6 | AP9: =VLOOKUP(AO9,$B$43:$C$51,2) -> D | AR9: =AVERAGE(E9,I9,M9,Q9,U9,Y9,AC9,AG9,AK9,AO9) -> 66.62 | AS9: =RANK(AR9,$AR$5:$AR$32) -> 14 | AT9: A+ | AU9: A | AV9: A | AW9: A+ | AX9: A | AY9: Mahira is a respectful and well-mannered student who relates well with peers and teachers. Despite her good behaviour, she needs to put more effort into her academic work, particularly in Mathematics and English and Science . She must develop stronger study habits and complete assignments more thoroughly. Close collaboration between home and school will help her unlock her potential.
A10: 6 | B10: Mavhunga Mukudzei | C10: 25 | D10: 39 | E10: =C10+D10 -> 64 | F10: =VLOOKUP(E10,$B$43:$C$51,2) -> C | G10: 27 | H10: 45 | I10: =G10+H10 -> 72 | J10: =VLOOKUP(I10,$B$43:$C$51,2) -> B | K10: 32.2 | L10: 39.6 | M10: =K10+L10 -> 71.8 | N10: =VLOOKUP(M10,$B$43:$C$51,2) -> B | O10: 26 | P10: 38 | Q10: =O10+P10 -> 64 | R10: =VLOOKUP(Q10,$B$43:$C$51,2) -> C | S10: 33 | T10: 48 | U10: =S10+T10 -> 81 | V10: =VLOOKUP(U10,$B$43:$C$51,2) -> A | W10: 27 | X10: 41 | Y10: =W10+X10 -> 68 | Z10: =VLOOKUP(Y10,$B$43:$C$51,2) -> C | AA10: 24 | AB10: 54 | AC10: =AA10+AB10 -> 78 | AD10: =VLOOKUP(AC10,$B$43:$C$51,2) -> B | AE10: 28 | AF10: 50 | AG10: =AE10+AF10 -> 78 | AH10: =VLOOKUP(AG10,$B$43:$C$51,2) -> B | AI10: 25 | AJ10: 48 | AK10: =AI10+AJ10 -> 73 | AL10: =VLOOKUP(AK10,$B$43:$C$51,2) -> B | AM10: 18.8 | AN10: 44 | AO10: =AM10+AN10 -> 62.8 | AP10: =VLOOKUP(AO10,$B$43:$C$51,2) -> C | AR10: =AVERAGE(E10,I10,M10,Q10,U10,Y10,AC10,AG10,AK10,AO10) -> 71.26 | AS10: =RANK(AR10,$AR$5:$AR$32) -> 6 | AT10: A+ | AU10: A+ | AV10: A | AW10: A | AX10: A+ | AY10: Mukudzei is an energetic and friendly learner who enjoys interacting with peers. Although he has the potential to perform well, his distractibility affects the quality of his work. He must improve his concentration and develop consistent study habits. English and Science especially require additional support. I recommend structured revision, limited distractions at home, and regular teacher-parent follow-ups.
A11: 7 | B11: Rakindas Rijith Hayagriv | C11: 32 | D11: 41 | E11: =C11+D11 -> 73 | F11: =VLOOKUP(E11,$B$43:$C$51,2) -> B | G11: 34 | H11: 52 | I11: =G11+H11 -> 86 | J11: =VLOOKUP(I11,$B$43:$C$51,2) -> A | K11: 37.6 | L11: 54.6 | M11: =K11+L11 -> 92.2 | N11: =VLOOKUP(M11,$B$43:$C$51,2) -> A* | O11: 31 | P11: 50 | Q11: =O11+P11 -> 81 | R11: =VLOOKUP(Q11,$B$43:$C$51,2) -> A | S11: 38 | T11: 51 | U11: =S11+T11 -> 89 | V11: =VLOOKUP(U11,$B$43:$C$51,2) -> A | W11: 35 | X11: 55 | Y11: =W11+X11 -> 90 | Z11: =VLOOKUP(Y11,$B$43:$C$51,2) -> A* | AA11: 33 | AB11: 56 | AC11: =AA11+AB11 -> 89 | AD11: =VLOOKUP(AC11,$B$43:$C$51,2) -> A | AE11: 29 | AF11: 53 | AG11: =AE11+AF11 -> 82 | AH11: =VLOOKUP(AG11,$B$43:$C$51,2) -> A | AI11: 27 | AJ11: 53 | AK11: =AI11+AJ11 -> 80 | AL11: =VLOOKUP(AK11,$B$43:$C$51,2) -> A | AM11: 24 | AN11: 38 | AO11: =AM11+AN11 -> 62 | AP11: =VLOOKUP(AO11,$B$43:$C$51,2) -> C | AR11: =AVERAGE(E11,I11,M11,Q11,U11,Y11,AC11,AG11,AK11,AO11) -> 82.42 | AS11: =RANK(AR11,$AR$5:$AR$32) -> 2 | AT11: A | AU11: B | AV11: A | AW11: B | AX11: B | AY11: Rijith consistently demonstrates very good behaviour and enthusiasm for learning. His academic performance is good across subjects. To further enrich his learning, he should continue developing his critical-thinking skills through independent tasks and wider reading. Participating even more confidently in class discussions will also benefit him. Jad is encouraged to maintain his high standards and keep up his excellent work.
A12: 8 | B12: Konnur Vibha | C12: 34 | D12: 44 | E12: =C12+D12 -> 78 | F12: =VLOOKUP(E12,$B$43:$C$51,2) -> B | G12: 32 | H12: 51 | I12: =G12+H12 -> 83 | J12: =VLOOKUP(I12,$B$43:$C$51,2) -> A | K12: 34.2 | L12: 54 | M12: =K12+L12 -> 88.2 | N12: =VLOOKUP(M12,$B$43:$C$51,2) -> A | O12: 34 | P12: 40 | Q12: =O12+P12 -> 74 | R12: =VLOOKUP(Q12,$B$43:$C$51,2) -> B | S12: 39 | T12: 55 | U12: =S12+T12 -> 94 | V12: =VLOOKUP(U12,$B$43:$C$51,2) -> A* | W12: 32 | X12: 55 | Y12: =W12+X12 -> 87 | Z12: =VLOOKUP(Y12,$B$43:$C$51,2) -> A | AA12: 36 | AB12: 58 | AC12: =AA12+AB12 -> 94 | AD12: =VLOOKUP(AC12,$B$43:$C$51,2) -> A* | AE12: 33 | AF12: 57 | AG12: =AE12+AF12 -> 90 | AH12: =VLOOKUP(AG12,$B$43:$C$51,2) -> A* | AI12: 31 | AJ12: 51 | AK12: =AI12+AJ12 -> 82 | AL12: =VLOOKUP(AK12,$B$43:$C$51,2) -> A | AM12: 20 | AN12: 36 | AO12: =AM12+AN12 -> 56 | AP12: =VLOOKUP(AO12,$B$43:$C$51,2) -> D | AR12: =AVERAGE(E12,I12,M12,Q12,U12,Y12,AC12,AG12,AK12,AO12) -> 82.62 | AS12: =RANK(AR12,$AR$5:$AR$32) -> 1 | AT12: A+ | AU12: A+ | AV12: A+ | AW12: A+ | AX12: A+ | AY12: Vibha maintains good behaviour and displays a positive attitude towards learning. Her academic performance is strong, and she consistently produces good work. To reach even higher levels, she should continue building her confidence in class discussions and challenge herself with extended tasks. Maintaining her current study habits and practising regular revision will help her excel. I encourage Vibha to keep up her excellent attitude and continue striving for excellence.
A13: 9 | B13: Sanderse Chendi | C13: 22 | D13: 40 | E13: =C13+D13 -> 62 | F13: =VLOOKUP(E13,$B$43:$C$51,2) -> C | G13: 26 | H13: 36 | I13: =G13+H13 -> 62 | J13: =VLOOKUP(I13,$B$43:$C$51,2) -> C | K13: 22.6 | L13: 39.6 | M13: =K13+L13 -> 62.2 | N13: =VLOOKUP(M13,$B$43:$C$51,2) -> C | O13: 28 | P13: 30 | Q13: =O13+P13 -> 58 | R13: =VLOOKUP(Q13,$B$43:$C$51,2) -> D | S13: 24 | T13: 39 | U13: =S13+T13 -> 63 | V13: =VLOOKUP(U13,$B$43:$C$51,2) -> C | W13: 25 | X13: 41 | Y13: =W13+X13 -> 66 | Z13: =VLOOKUP(Y13,$B$43:$C$51,2) -> C | AA13: 16 | AB13: 54 | AC13: =AA13+AB13 -> 70 | AD13: =VLOOKUP(AC13,$B$43:$C$51,2) -> B | AE13: 32 | AF13: 50 | AG13: =AE13+AF13 -> 82 | AH13: =VLOOKUP(AG13,$B$43:$C$51,2) -> A | AI13: 27 | AJ13: 52 | AK13: =AI13+AJ13 -> 79 | AL13: =VLOOKUP(AK13,$B$43:$C$51,2) -> B | AM13: 20 | AN13: 35 | AO13: =AM13+AN13 -> 55 | AP13: =VLOOKUP(AO13,$B$43:$C$51,2) -> D | AR13: =AVERAGE(E13,I13,M13,Q13,U13,Y13,AC13,AG13,AK13,AO13) -> 65.92 | AS13: =RANK(AR13,$AR$5:$AR$32) -> 15 | AT13: A | AU13: A+ | AV13: A | AW13: A+ | AX13: A+ | AY13: Chendi is a very well-behaved student who consistently sets a positive example for others. She shows great commitment to her studies; however, to enhance her Good performance, she should focus on strengthening her core skills in Math, English, and Science subjects where she currently earns C. I recommend she dedicate extra practice and study time specifically in these areas. Continuing to read widely, challenge herself with more complex tasks, and engage in independent study will help deepen her understanding and raise her achievement. I encourage Chendi to maintain her outstanding attitude and keep striving for excellence.
A14: 10 | B14: Khalil Sara Ahmed Mohamed | C14: 24 | D14: 30 | E14: =C14+D14 -> 54 | F14: =VLOOKUP(E14,$B$43:$C$51,2) -> D | G14: 21 | H14: 35 | I14: =G14+H14 -> 56 | J14: =VLOOKUP(I14,$B$43:$C$51,2) -> D | K14: 17 | L14: 36 | M14: =K14+L14 -> 53 | N14: =VLOOKUP(M14,$B$43:$C$51,2) -> D | O14: 30 | P14: 43 | Q14: =O14+P14 -> 73 | R14: =VLOOKUP(Q14,$B$43:$C$51,2) -> B | S14: 25 | T14: 41 | U14: =S14+T14 -> 66 | V14: =VLOOKUP(U14,$B$43:$C$51,2) -> C | W14: 27 | X14: 53 | Y14: =W14+X14 -> 80 | Z14: =VLOOKUP(Y14,$B$43:$C$51,2) -> A | AA14: 16 | AB14: 31 | AC14: =AA14+AB14 -> 47 | AD14: =VLOOKUP(AC14,$B$43:$C$51,2) -> E | AE14: 29 | AF14: 51 | AG14: =AE14+AF14 -> 80 | AH14: =VLOOKUP(AG14,$B$43:$C$51,2) -> A | AI14: 26 | AJ14: 50 | AK14: =AI14+AJ14 -> 76 | AL14: =VLOOKUP(AK14,$B$43:$C$51,2) -> B | AM14: 21 | AN14: 37 | AO14: =AM14+AN14 -> 58 | AP14: =VLOOKUP(AO14,$B$43:$C$51,2) -> D | AR14: =AVERAGE(E14,I14,M14,Q14,U14,Y14,AC14,AG14,AK14,AO14) -> 64.3 | AS14: =RANK(AR14,$AR$5:$AR$32) -> 17 | AT14: B | AU14: A | AV14: A | AW14: A+ | AX14: B | AY14: Sara is a respectful and well-mannered student who relates well with peers and teachers. Despite her good behaviour, she needs to put more effort into her academic work, particularly in Mathematics and English,Science.She must develop stronger study habits and complete assignments more thoroughly. Close collaboration between home and school will help her unlock her potential.
A15: 11 | B15: Mutombo Marlo Mande | C15: 31 | D15: 40 | E15: =C15+D15 -> 71 | F15: =VLOOKUP(E15,$B$43:$C$51,2) -> B | G15: 18 | H15: 43 | I15: =G15+H15 -> 61 | J15: =VLOOKUP(I15,$B$43:$C$51,2) -> C | K15: 33.2 | L15: 54 | M15: =K15+L15 -> 87.2 | N15: =VLOOKUP(M15,$B$43:$C$51,2) -> A | O15: 29 | P15: 31 | Q15: =O15+P15 -> 60 | R15: =VLOOKUP(Q15,$B$43:$C$51,2) -> C | S15: 32 | T15: 44 | U15: =S15+T15 -> 76 | V15: =VLOOKUP(U15,$B$43:$C$51,2) -> B | W15: 26 | X15: 46 | Y15: =W15+X15 -> 72 | Z15: =VLOOKUP(Y15,$B$43:$C$51,2) -> B | AA15: 39 | AB15: 53 | AC15: =AA15+AB15 -> 92 | AD15: =VLOOKUP(AC15,$B$43:$C$51,2) -> A* | AE15: 28 | AF15: 50 | AG15: =AE15+AF15 -> 78 | AH15: =VLOOKUP(AG15,$B$43:$C$51,2) -> B | AI15: 30 | AJ15: 53 | AK15: =AI15+AJ15 -> 83 | AL15: =VLOOKUP(AK15,$B$43:$C$51,2) -> A | AM15: 20 | AN15: 49 | AO15: =AM15+AN15 -> 69 | AP15: =VLOOKUP(AO15,$B$43:$C$51,2) -> C | AR15: =AVERAGE(E15,I15,M15,Q15,U15,Y15,AC15,AG15,AK15,AO15) -> 74.92 | AS15: =RANK(AR15,$AR$5:$AR$32) -> 4 | AT15: B | AU15: A | AV15: A | AW15: A | AX15: C | AY15: Marlo generally shows acceptable behavior but often requires reminders to remain attentive and follow instructions carefully. He can become easily distracted by conversations with peers, which causes him to lose track of tasks. By improving his focus and time management during lessons particularly in English, Mathematics, and Science. Marlo can make significant gains in his participation and achievement. If he can maintain good classroom conduct and manage distractions, he has the clear potential to achieve strong grades. Additional support in building these executive skills is recommended to help him excel.
A16: 12 | B16: Mushipe Angel Tasimbiswa | C16: 33 | D16: 36 | E16: =C16+D16 -> 69 | F16: =VLOOKUP(E16,$B$43:$C$51,2) -> C | G16: 18 | H16: 20 | I16: =G16+H16 -> 38 | J16: =VLOOKUP(I16,$B$43:$C$51,2) -> F | K16: 10.8 | L16: 30.6 | M16: =K16+L16 -> 41.4 | N16: =VLOOKUP(M16,$B$43:$C$51,2) -> E | O16: 24 | P16: 37 | Q16: =O16+P16 -> 61 | R16: =VLOOKUP(Q16,$B$43:$C$51,2) -> C | S16: 22 | T16: 43 | U16: =S16+T16 -> 65 | V16: =VLOOKUP(U16,$B$43:$C$51,2) -> C | W16: 24 | X16: 36 | Y16: =W16+X16 -> 60 | Z16: =VLOOKUP(Y16,$B$43:$C$51,2) -> C | AA16: 37 | AB16: 44 | AC16: =AA16+AB16 -> 81 | AD16: =VLOOKUP(AC16,$B$43:$C$51,2) -> A | AE16: 24 | AF16: 40 | AG16: =AE16+AF16 -> 64 | AH16: =VLOOKUP(AG16,$B$43:$C$51,2) -> C | AI16: 31 | AJ16: 30 | AK16: =AI16+AJ16 -> 61 | AL16: =VLOOKUP(AK16,$B$43:$C$51,2) -> C | AM16: 25 | AN16: 56 | AO16: =AM16+AN16 -> 81 | AP16: =VLOOKUP(AO16,$B$43:$C$51,2) -> A | AR16: =AVERAGE(E16,I16,M16,Q16,U16,Y16,AC16,AG16,AK16,AO16) -> 62.14 | AS16: =RANK(AR16,$AR$5:$AR$32) -> 20 | AT16: B | AU16: A | AV16: B | AW16: A+ | AX16: B | AY16: Angel exhibits average behavior, frequently moving around unnecessarily, which disrupts her concentration and focus in class. She requires improvement in core subjects, especially Science, Mathematics, and English. To support her academic progress, it is important for her to remain seated during lessons, listen attentively, and follow instructions carefully. Regular revision and consistent practice of foundational skills at home will further reinforce her learning. With greater self-discipline and commitment, Angel has the clear potential to achieve significantly stronger results. I encourage her to stay motivated and continue striving for improvement.
... A22: 18 | B22: Ghumra Shazneen | C22: 25 | D22: 30 | E22: =C22+D22 -> 55 | F22: =VLOOKUP(E22,$B$43:$C$51,2) -> D | G22: 17 | H22: 39 | I22: =G22+H22 -> 56 | J22: =VLOOKUP(I22,$B$43:$C$51,2) -> D | K22: 23.8 | L22: 39.6 | M22: =K22+L22 -> 63.4 | N22: =VLOOKUP(M22,$B$43:$C$51,2) -> C | O22: 22 | P22: 40 | Q22: =O22+P22 -> 62 | R22: =VLOOKUP(Q22,$B$43:$C$51,2) -> C | S22: 29 | T22: 52 | U22: =S22+T22 -> 81 | V22: =VLOOKUP(U22,$B$43:$C$51,2) -> A | W22: 21 | X22: 46 | Y22: =W22+X22 -> 67 | Z22: =VLOOKUP(Y22,$B$43:$C$51,2) -> C | AA22: 29 | AB22: 42 | AC22: =AA22+AB22 -> 71 | AD22: =VLOOKUP(AC22,$B$43:$C$51,2) -> B | AE22: 29 | AF22: 53 | AG22: =AE22+AF22 -> 82 | AH22: =VLOOKUP(AG22,$B$43:$C$51,2) -> A | AI22: 32 | AJ22: 40 | AK22: =AI22+AJ22 -> 72 | AL22: =VLOOKUP(AK22,$B$43:$C$51,2) -> B | AM22: 16 | AN22: 45 | AO22: =AM22+AN22 -> 61 | AP22: =VLOOKUP(AO22,$B$43:$C$51,2) -> C | AR22: =AVERAGE(E22,I22,M22,Q22,U22,Y22,AC22,AG22,AK22,AO22) -> 67.04 | AS22: =RANK(AR22,$AR$5:$AR$32) -> 13 | AT22: A | AU22: A+ | AV22: A | AW22: A+ | AX22: A+ | AY22: Shazneem is a well-behaved student who shows respect and kindness in class. She completes assignments reliably and listens attentively. There is room for improvement, especially in Math, Science, and English, as well as in sustaining focus throughout the lesson and speaking more confidently during activities. I encourage her to take small steps toward greater classroom involvement, which will strengthen her academic skills and self-assurance.
A23: 19 | B23: Pathak Akshat | C23: 28 | D23: 48 | E23: =C23+D23 -> 76 | F23: =VLOOKUP(E23,$B$43:$C$51,2) -> B | G23: 24 | H23: 46 | I23: =G23+H23 -> 70 | J23: =VLOOKUP(I23,$B$43:$C$51,2) -> B | K23: 35.4 | L23: 52 | M23: =K23+L23 -> 87.4 | N23: =VLOOKUP(M23,$B$43:$C$51,2) -> A | O23: 32 | P23: 44 | Q23: =O23+P23 -> 76 | R23: =VLOOKUP(Q23,$B$43:$C$51,2) -> B | S23: 33 | T23: 42 | U23: =S23+T23 -> 75 | V23: =VLOOKUP(U23,$B$43:$C$51,2) -> B | W23: 32 | X23: 53 | Y23: =W23+X23 -> 85 | Z23: =VLOOKUP(Y23,$B$43:$C$51,2) -> A | AA23: 28 | AB23: 46 | AC23: =AA23+AB23 -> 74 | AD23: =VLOOKUP(AC23,$B$43:$C$51,2) -> B | AE23: 28 | AF23: 43 | AG23: =AE23+AF23 -> 71 | AH23: =VLOOKUP(AG23,$B$43:$C$51,2) -> B | AI23: 26 | AJ23: 40 | AK23: =AI23+AJ23 -> 66 | AL23: =VLOOKUP(AK23,$B$43:$C$51,2) -> C | AM23: 21 | AN23: 35 | AO23: 56 | AP23: =VLOOKUP(AO23,$B$43:$C$51,2) -> D | AR23: =AVERAGE(E23,I23,M23,Q23,U23,Y23,AC23,AG23,AK23,AO23) -> 73.64 | AS23: =RANK(AR23,$AR$5:$AR$32) -> 5 | AT23: A | AU23: A | AV23: A | AW23: A | AX23: A | AY23: Akshat demonstrates excellent behaviour and consistently shows a positive attitude towards learning. His academic performance is very strong across all subjects. To extend his skills further, he should continue exploring challenging tasks and developing independent study habits. Engaging confidently in discussions will enrich his learning. Maahir is encouraged to maintain his outstanding effort and continue striving for excellence.
A24: 20 | B24: Pardesi Mariam | C24: 28 | D24: 38 | E24: =C24+D24 -> 66 | F24: =VLOOKUP(E24,$B$43:$C$51,2) -> C | G24: 19 | H24: 39 | I24: =G24+H24 -> 58 | J24: =VLOOKUP(I24,$B$43:$C$51,2) -> D | K24: 20.8 | L24: 47.4 | M24: =K24+L24 -> 68.2 | N24: =VLOOKUP(M24,$B$43:$C$51,2) -> C | O24: 16 | P24: 39 | Q24: =O24+P24 -> 55 | R24: =VLOOKUP(Q24,$B$43:$C$51,2) -> D | S24: 32 | T24: 46 | U24: =S24+T24 -> 78 | V24: =VLOOKUP(U24,$B$43:$C$51,2) -> B | W24: 28 | X24: 52 | Y24: =W24+X24 -> 80 | Z24: =VLOOKUP(Y24,$B$43:$C$51,2) -> A | AA24: 33 | AB24: 49 | AC24: =AA24+AB24 -> 82 | AD24: =VLOOKUP(AC24,$B$43:$C$51,2) -> A | AE24: 32 | AF24: 46 | AG24: =AE24+AF24 -> 78 | AH24: =VLOOKUP(AG24,$B$43:$C$51,2) -> B | AI24: 29 | AJ24: 41 | AK24: =AI24+AJ24 -> 70 | AL24: =VLOOKUP(AK24,$B$43:$C$51,2) -> B | AM24: 19 | AN24: 48 | AO24: =AM24+AN24 -> 67 | AP24: =VLOOKUP(AO24,$B$43:$C$51,2) -> C | AR24: =AVERAGE(E24,I24,M24,Q24,U24,Y24,AC24,AG24,AK24,AO24) -> 70.22 | AS24: =RANK(AR24,$AR$5:$AR$32) -> 7 | AT24: A | AU24: A+ | AV24: A | AW24: A+ | AX24: A+ | AY24: Mariam is a very well-behaved student who always sets a positive example for others. Her academic performance is excellent, and she shows great commitment to her studies. To extend her abilities further, she should continue challenging herself with higher-level tasks. Continued reading and independent study will help deepen her knowledge.Mariam is encouraged to maintain her outstanding attitude and keep striving for excellence.
A25: 21 | B25: Mutena Michelle | C25: 31 | D25: 26 | E25: =C25+D25 -> 57 | F25: =VLOOKUP(E25,$B$43:$C$51,2) -> D | G25: 17 | H25: 33 | I25: =G25+H25 -> 50 | J25: =VLOOKUP(I25,$B$43:$C$51,2) -> D | K25: 16.6 | L25: 21 | M25: =K25+L25 -> 37.6 | N25: =VLOOKUP(M25,$B$43:$C$51,2) -> F | O25: 26 | P25: 44 | Q25: =O25+P25 -> 70 | R25: =VLOOKUP(Q25,$B$43:$C$51,2) -> B | S25: 21 | T25: 39 | U25: =S25+T25 -> 60 | V25: =VLOOKUP(U25,$B$43:$C$51,2) -> C | W25: 28 | X25: 36 | Y25: =W25+X25 -> 64 | Z25: =VLOOKUP(Y25,$B$43:$C$51,2) -> C | AA25: 28 | AB25: 44 | AC25: =AA25+AB25 -> 72 | AD25: =VLOOKUP(AC25,$B$43:$C$51,2) -> B | AE25: 21 | AF25: 39 | AG25: =AE25+AF25 -> 60 | AH25: =VLOOKUP(AG25,$B$43:$C$51,2) -> C | AI25: 25 | AJ25: 46 | AK25: =AI25+AJ25 -> 71 | AL25: =VLOOKUP(AK25,$B$43:$C$51,2) -> B | AM25: 21 | AN25: 47 | AO25: =AM25+AN25 -> 68 | AP25: =VLOOKUP(AO25,$B$43:$C$51,2) -> C | AR25: =AVERAGE(E25,I25,M25,Q25,U25,Y25,AC25,AG25,AK25,AO25) -> 60.96 | AS25: =RANK(AR25,$AR$5:$AR$32) -> 22 | AT25: A | AU25: A | AV25: A | AW25: A+ | AX25: B | AY25: Michelle displays average behaviour and often moves around a lot, which affects her concentration. She needs improvement in Science, Maths, and English. Staying focused in class and reducing unnecessary movement will help improve her understanding. Regular practice at home and revising key concepts will support her progress. With greater focus and discipline, Michele can achieve stronger academic results. I encourage her to stay motivated and committed.
A26: 22 | B26: Nacidze Raquel | C26: 31 | D26: 44 | E26: =C26+D26 -> 75 | F26: =VLOOKUP(E26,$B$43:$C$51,2) -> B | G26: 16 | H26: 44 | I26: =G26+H26 -> 60 | J26: =VLOOKUP(I26,$B$43:$C$51,2) -> C | K26: 20.8 | L26: 40.8 | M26: =K26+L26 -> 61.6 | N26: =VLOOKUP(M26,$B$43:$C$51,2) -> C | O26: 28 | P26: 30 | Q26: =O26+P26 -> 58 | R26: =VLOOKUP(Q26,$B$43:$C$51,2) -> D | S26: 28 | T26: 40 | U26: =S26+T26 -> 68 | V26: =VLOOKUP(U26,$B$43:$C$51,2) -> C | W26: 32 | X26: 39 | Y26: =W26+X26 -> 71 | Z26: =VLOOKUP(Y26,$B$43:$C$51,2) -> B | AA26: 30 | AB26: 38 | AC26: =AA26+AB26 -> 68 | AD26: =VLOOKUP(AC26,$B$43:$C$51,2) -> C | AE26: 29 | AF26: 52 | AG26: =AE26+AF26 -> 81 | AH26: =VLOOKUP(AG26,$B$43:$C$51,2) -> A | AI26: 31 | AJ26: 45 | AK26: =AI26+AJ26 -> 76 | AL26: =VLOOKUP(AK26,$B$43:$C$51,2) -> B | AM26: 25.5 | AN26: 56 | AO26: =AM26+AN26 -> 81.5 | AP26: =VLOOKUP(AO26,$B$43:$C$51,2) -> A | AR26: =AVERAGE(E26,I26,M26,Q26,U26,Y26,AC26,AG26,AK26,AO26) -> 70.01 | AS26: =RANK(AR26,$AR$5:$AR$32) -> 8 | AT26: A | AU26: A | AV26: A | AW26: A+ | AX26: A+ | AY26: Raquel maintains good behaviour and displays a positive attitude towards learning. Her academic performance is consistently strong, and she produces good quality work. To reach an even higher level, she should focus on challenging herself further, particularly in Math and Science, and engage with more extended tasks. Maintaining her diligent study habits and practising regular revision will help her excel. I encourage Raquel to keep up her excellent attitude and continue striving for excellence.
A27: 23 | B27: Bredt Bupe | C27: 30 | D27: 40 | E27: =C27+D27 -> 70 | F27: =VLOOKUP(E27,$B$43:$C$51,2) -> B | G27: 14 | H27: 36 | I27: =G27+H27 -> 50 | J27: =VLOOKUP(I27,$B$43:$C$51,2) -> D | K27: 23.6 | L27: 42.6 | M27: =K27+L27 -> 66.2 | N27: =VLOOKUP(M27,$B$43:$C$51,2) -> C | O27: 32 | P27: 31 | Q27: =O27+P27 -> 63 | R27: =VLOOKUP(Q27,$B$43:$C$51,2) -> C | S27: 24 | T27: 36 | U27: =S27+T27 -> 60 | V27: =VLOOKUP(U27,$B$43:$C$51,2) -> C | W27: 27 | X27: 38 | Y27: =W27+X27 -> 65 | Z27: =VLOOKUP(Y27,$B$43:$C$51,2) -> C | AA27: 39 | AB27: 50 | AC27: =AA27+AB27 -> 89 | AD27: =VLOOKUP(AC27,$B$43:$C$51,2) -> A | AE27: 31 | AF27: 49 | AG27: =AE27+AF27 -> 80 | AH27: =VLOOKUP(AG27,$B$43:$C$51,2) -> A | AI27: 25 | AJ27: 40 | AK27: =AI27+AJ27 -> 65 | AL27: =VLOOKUP(AK27,$B$43:$C$51,2) -> C | AM27: 20.7 | AN27: 47 | AO27: =AM27+AN27 -> 67.7 | AP27: =VLOOKUP(AO27,$B$43:$C$51,2) -> C | AR27: =AVERAGE(E27,I27,M27,Q27,U27,Y27,AC27,AG27,AK27,AO27) -> 67.59 | AS27: =RANK(AR27,$AR$5:$AR$32) -> 12 | AT27: A+ | AU27: A | AV27: A+ | AW27: A | AX27: A+ | AY27: Bupe maintains good behaviour and displays a positive attitude towards learning. Her academic performance is consistently strong, and she produces good quality work. To reach an even higher level, she should focus on challenging herself further, particularly in Math and Science, and engage with more extended tasks. Maintaining her diligent study habits and practising regular revision will help her excel. I encourage Bupe to keep up her excellent attitude and continue striving for excellence.
A28: 24 | B28: Hamze Jaad | C28: 19 | D28: 43 | E28: =C28+D28 -> 62 | F28: =VLOOKUP(E28,$B$43:$C$51,2) -> C | G28: 8 | H28: 32 | I28: =G28+H28 -> 40 | J28: =VLOOKUP(I28,$B$43:$C$51,2) -> E | K28: 12 | L28: 25.8 | M28: =K28+L28 -> 37.8 | N28: =VLOOKUP(M28,$B$43:$C$51,2) -> F | O28: 28 | P28: 25 | Q28: =O28+P28 -> 53 | R28: =VLOOKUP(Q28,$B$43:$C$51,2) -> D | S28: 14 | T28: 26 | U28: =S28+T28 -> 40 | V28: =VLOOKUP(U28,$B$43:$C$51,2) -> E | W28: 22 | X28: 49 | Y28: =W28+X28 -> 71 | Z28: =VLOOKUP(Y28,$B$43:$C$51,2) -> B | AA28: 9 | AB28: 37 | AC28: =AA28+AB28 -> 46 | AD28: =VLOOKUP(AC28,$B$43:$C$51,2) -> E | AE28: 24 | AF28: 43 | AG28: =AE28+AF28 -> 67 | AH28: =VLOOKUP(AG28,$B$43:$C$51,2) -> C | AI28: 20 | AJ28: 23 | AK28: =AI28+AJ28 -> 43 | AL28: =VLOOKUP(AK28,$B$43:$C$51,2) -> E | AM28: 22 | AN28: 46 | AO28: =AM28+AN28 -> 68 | AP28: =VLOOKUP(AO28,$B$43:$C$51,2) -> C | AR28: =AVERAGE(E28,I28,M28,Q28,U28,Y28,AC28,AG28,AK28,AO28) -> 52.78 | AS28: =RANK(AR28,$AR$5:$AR$32) -> 24 | AT28: B | AU28: A | AV28: B | AW28: A | AX28: B | AY28: Hamze Hamze is well-behaved in class. To make further progress, he should work on maintaining his focus for longer periods and minimizing side conversations, as these distractions can cause him to disengage from lessons. He would benefit from targeted improvement in Science, Math, and English.I encourage him to participate more actively and interact with the lesson and his peers to strengthen his understanding. To support this, consistent practice at home and a daily review of lessons are essential. Organizing extra, structured study time at home will be particularly helpful in building his concentration and consolidating his learning, which will lead to strong academic improvement.
A29: 25 | B29: Kalupahana Kevin | C29: 29 | D29: 35 | E29: =C29+D29 -> 64 | F29: =VLOOKUP(E29,$B$43:$C$51,2) -> C | G29: 19 | H29: 36 | I29: =G29+H29 -> 55 | J29: =VLOOKUP(I29,$B$43:$C$51,2) -> D | K29: 16.4 | L29: 35.4 | M29: =K29+L29 -> 51.8 | N29: =VLOOKUP(M29,$B$43:$C$51,2) -> D | O29: 26 | P29: 21 | Q29: =O29+P29 -> 47 | R29: =VLOOKUP(Q29,$B$43:$C$51,2) -> E | S29: 28 | T29: 31 | U29: =S29+T29 -> 59 | V29: =VLOOKUP(U29,$B$43:$C$51,2) -> D | W29: 23 | X29: 39 | Y29: =W29+X29 -> 62 | Z29: =VLOOKUP(Y29,$B$43:$C$51,2) -> C | AA29: 22 | AB29: 49 | AC29: =AA29+AB29 -> 71 | AD29: =VLOOKUP(AC29,$B$43:$C$51,2) -> B | AE29: 28 | AF29: 37 | AG29: =AE29+AF29 -> 65 | AH29: =VLOOKUP(AG29,$B$43:$C$51,2) -> C | AI29: 20 | AJ29: 41 | AK29: =AI29+AJ29 -> 61 | AL29: =VLOOKUP(AK29,$B$43:$C$51,2) -> C | AM29: 27 | AN29: 53 | AO29: =AM29+AN29 -> 80 | AP29: =VLOOKUP(AO29,$B$43:$C$51,2) -> A | AR29: =AVERAGE(E29,I29,M29,Q29,U29,Y29,AC29,AG29,AK29,AO29) -> 61.58 | AS29: =RANK(AR29,$AR$5:$AR$32) -> 21 | AT29: B | AU29: A | AV29: B | AW29: A | AX29: B | AY29: Kevin is an energetic and friendly learner who enjoys interacting with peers. Although he has the potential to perform well, his distractibility affects the quality of his work. He must improve his concentration and develop consistent study habits. Mathematics, English and Science especially require additional support. I recommend structured revision, limited distractions at home, and regular teacher-parent follow-ups.
A30: 26 | B30: Bhagchandani Maahi | C30: 31 | D30: 42 | E30: =C30+D30 -> 73 | F30: =VLOOKUP(E30,$B$43:$C$51,2) -> B | G30: 23 | H30: 23 | I30: =G30+H30 -> 46 | J30: =VLOOKUP(I30,$B$43:$C$51,2) -> E | K30: 13.8 | L30: 30 | M30: =K30+L30 -> 43.8 | N30: =VLOOKUP(M30,$B$43:$C$51,2) -> E | O30: 28 | P30: 37 | Q30: =O30+P30 -> 65 | R30: =VLOOKUP(Q30,$B$43:$C$51,2) -> C | S30: 34 | T30: 37 | U30: =S30+T30 -> 71 | V30: =VLOOKUP(U30,$B$43:$C$51,2) -> B | W30: 24 | X30: 44 | Y30: =W30+X30 -> 68 | Z30: =VLOOKUP(Y30,$B$43:$C$51,2) -> C | AA30: 21 | AB30: 32 | AC30: =AA30+AB30 -> 53 | AD30: =VLOOKUP(AC30,$B$43:$C$51,2) -> D | AE30: 26 | AF30: 53 | AG30: =AE30+AF30 -> 79 | AH30: =VLOOKUP(AG30,$B$43:$C$51,2) -> B | AI30: 27 | AJ30: 44 | AK30: =AI30+AJ30 -> 71 | AL30: =VLOOKUP(AK30,$B$43:$C$51,2) -> B | AM30: 21 | AN30: 49 | AO30: =AM30+AN30 -> 70 | AP30: =VLOOKUP(AO30,$B$43:$C$51,2) -> B | AR30: =AVERAGE(E30,I30,M30,Q30,U30,Y30,AC30,AG30,AK30,AO30) -> 63.98 | AS30: =RANK(AR30,$AR$5:$AR$32) -> 18 | AT30: A | AU30: A | AV30: A | AW30: A | AX30: A | AY30: Maahi is a respectful and conscientious student with a positive attitude. While she generally demonstrates a good level of academic performance, she can be easily distracted by social conversations during lessons, which affects her focus. To achieve her full potential, she should aim to minimize these distractions and channel her efforts more consistently into her core subjects particularly English, Mathematics, and Science. By working extra hard in these areas and maintaining attentive participation in class, Maahi is well-positioned to achieve even stronger results.
A31: 27 | B31: Jeri Ethan Moses | C31: 18 | D31: 20 | E31: =C31+D31 -> 38 | F31: =VLOOKUP(E31,$B$43:$C$51,2) -> F | G31: 3 | H31: 14 | I31: =G31+H31 -> 17 | J31: =VLOOKUP(I31,$B$43:$C$51,2) -> U | K31: 8 | L31: 24 | M31: =K31+L31 -> 32 | N31: =VLOOKUP(M31,$B$43:$C$51,2) -> F | O31: 10 | P31: 15 | Q31: =O31+P31 -> 25 | R31: =VLOOKUP(Q31,$B$43:$C$51,2) -> G | S31: 25 | T31: 26 | U31: =S31+T31 -> 51 | V31: =VLOOKUP(U31,$B$43:$C$51,2) -> D | W31: 26 | X31: 29 | Y31: =W31+X31 -> 55 | Z31: =VLOOKUP(Y31,$B$43:$C$51,2) -> D | AA31: 7 | AB31: 22 | AD31: =VLOOKUP(AC31,$B$43:$C$51,2) -> U | AE31: 29 | AF31: 43 | AG31: 72 | AH31: =VLOOKUP(AG31,$B$43:$C$51,2) -> B | AI31: 17 | AJ31: 16 | AK31: =AI31+AJ31 -> 33 | AL31: =VLOOKUP(AK31,$B$43:$C$51,2) -> F | AM31: 21 | AN31: 46 | AO31: =AM31+AN31 -> 67 | AP31: =VLOOKUP(AO31,$B$43:$C$51,2) -> C | AR31: =AVERAGE(E31,I31,M31,Q31,U31,Y31,AC31,AG31,AK31,AO31) -> 43.333333 | AS31: =RANK(AR31,$AR$5:$AR$32) -> 27 | AT31: B | AU31: A | AV31: A | AW31: A+ | AX31: A+ | AY31: Ethan conducts himself well but his frequent absences significantly disrupt his learning in key subjects. When in class, he struggles with focus and side conversations. To improve, he must prioritize regular attendance and active participation. A structured study routine at home will also be vital for reinforcing concepts and improving concentration. With consistent effort, Ethan can make meaningful academic progress.
B35: Average | E35: =AVERAGE(E5:E31) -> 65.962963 | I35: =AVERAGE(I5:I31) -> 52.555556 | M35: =AVERAGE(M5:M31) -> 58.937037 | Q35: =AVERAGE(Q5:Q31) -> 61.666667 | U35: =AVERAGE(U5:U31) -> 68.777778 | Y35: =AVERAGE(Y5:Y31) -> 70.888889 | AC35: =AVERAGE(AC5:AC31) -> 70.076923 | AG35: =AVERAGE(AG5:AG31) -> 75.740741 | AK35: =AVERAGE(AK5:AK31) -> 68.814815 | AO35: =AVERAGE(AO5:AO31) -> 66.862963
B36: NO. Students | E36: =COUNT(E5:E31) -> 27 | I36: =COUNT(I5:I31) -> 27 | M36: =COUNT(M5:M31) -> 27 | Q36: =COUNT(Q5:Q31) -> 27 | U36: =COUNT(U5:U31) -> 27 | Y36: =COUNT(Y5:Y31) -> 27 | AC36: =COUNT(AC5:AC31) -> 26 | AG36: =COUNT(AG5:AG31) -> 27 | AK36: =COUNT(AK5:AK31) -> 27 | AO36: =COUNT(AO5:AO31) -> 27
B37: Pass | E37: =COUNTIF(E5:E31,">49") -> 26 | I37: =COUNTIF(I5:I31,">49") -> 17 | M37: =COUNTIF(M5:M31,">49") -> 19 | Q37: =COUNTIF(Q5:Q31,">49") -> 23 | U37: =COUNTIF(U5:U31,">49") -> 26 | Y37: =COUNTIF(Y5:Y31,">49") -> 26 | AC37: =COUNTIF(AC5:AC31,">49") -> 21 | AG37: =COUNTIF(AG5:AG31,">49") -> 27 | AK37: =COUNTIF(AK5:AK31,">49") -> 24 | AO37: =COUNTIF(AO5:AO31,">49") -> 27
B38: Fail | E38: =COUNTIF(E5:E31,"<50") -> 1 | I38: =COUNTIF(I5:I31,"<50") -> 10 | M38: =COUNTIF(M5:M31,"<50") -> 8 | Q38: =COUNTIF(Q5:Q31,"<50") -> 4 | U38: =COUNTIF(U5:U31,"<50") -> 1 | Y38: =COUNTIF(Y5:Y31,"<50") -> 1 | AC38: =COUNTIF(AC5:AC31,"<50") -> 5 | AG38: =COUNTIF(AG5:AG31,"<50") -> 0 | AK38: =COUNTIF(AK5:AK31,"<50") -> 3 | AO38: =COUNTIF(AO5:AO31,"<50") -> 0
B39: Pass Rate % | E39: =E37*100/E36 -> 96.296296 | I39: =I37*100/I36 -> 62.962963 | M39: =M37*100/M36 -> 70.37037 | Q39: =Q37*100/Q36 -> 85.185185 | U39: =U37*100/U36 -> 96.296296 | Y39: =Y37*100/Y36 -> 96.296296 | AC39: =AC37*100/AC36 -> 80.769231 | AG39: =AG37*100/AG36 -> 100 | AK39: =AK37*100/AK36 -> 88.888889 | AO39: =AO37*100/AO36 -> 100
A43: 00-19 | B43: 0 | C43: U
A44: 20-29 | B44: 20 | C44: G
A45: 30-39 | B45: 30 | C45: F
A46: 40-49 | B46: 40 | C46: E
A47: 50-59 | B47: 50 | C47: D
A48: 60-69 | B48: 60 | C48: C
A49: 70-79 | B49: 70 | C49: B
A50: 80-89 | B50: 80 | C50: A
A51: 90-100 | B51: 90 | C51: A*

Sheet LS2A
A1: HOME
A3: Roll N0. | B3: Name | C3: English | G3: Mathematics | K3: Science | O3: Global Perspectives | S3: New Computing | W3: Business Studies | AA3: French | AE3: Art | AI3: MDD | AM3: PE | AR3: AVERAGE | AS3: POSITION | AT3: CREATIVITY | AU3: RESPECT | AV3: EXCELLENCE | AW3: EMPATHY | AX3: DISCPLINE | AY3: CLASS TEACHER'S COMMENT
C4: Formative | D4: Summative | E4: Final Mark | F4: Grade | G4: Formative | H4: Summative | I4: Final Mark | J4: Grade | K4: Formative | L4: Summative | M4: Final Mark | N4: Grade | O4: Formative | P4: Summative | Q4: Final Mark | R4: Grade | S4: Formative | T4: Summative | U4: Final Mark | V4: Grade | W4: Formative | X4: Summative | Y4: Final Mark | Z4: Grade | AA4: Formative | AB4: Summative | AC4: Final Mark | AD4: Grade | AE4: Formative | AF4: Summative | AG4: Final Mark | AH4: Grade | AI4: Formative | AJ4: Summative | AK4: Final Mark | AL4: Grade | AM4: Formative | AN4: Summative | AO4: Final Mark | AP4: Grade
A5: 1 | B5: Dakwa Isia Yanis | C5: 6 | D5: 11 | E5: =C5+D5 -> 17 | F5: =VLOOKUP(E5,$B$42:$C$50,2) -> U | G5: 21 | H5: 19 | I5: =G5+H5 -> 40 | J5: =VLOOKUP(I5,$B$42:$C$50,2) -> E | K5: 23 | L5: 23 | M5: =K5+L5 -> 46 | N5: =VLOOKUP(M5,$B$42:$C$50,2) -> E | O5: 9 | P5: 36 | Q5: =O5+P5 -> 45 | R5: =VLOOKUP(Q5,$B$42:$C$50,2) -> E | S5: 33 | T5: 22 | U5: =S5+T5 -> 55 | V5: =VLOOKUP(U5,$B$42:$C$50,2) -> D | W5: 18 | X5: 40 | Y5: =W5+X5 -> 58 | Z5: =VLOOKUP(Y5,$B$42:$C$50,2) -> D | AA5: 34 | AB5: 46 | AC5: =AA5+AB5 -> 80 | AD5: =VLOOKUP(AC5,$B$42:$C$50,2) -> A | AE5: 28 | AF5: 42 | AG5: =AE5+AF5 -> 70 | AH5: =VLOOKUP(AG5,$B$42:$C$50,2) -> B | AI5: 30 | AJ5: 36 | AK5: =AI5+AJ5 -> 66 | AL5: =VLOOKUP(AK5,$B$42:$C$50,2) -> C | AM5: 20.7 | AN5: 53 | AO5: =AM5+AN5 -> 73.7 | AP5: =VLOOKUP(AO5,$B$42:$C$50,2) -> B | AR5: =AVERAGE(E5,I5,M5,Q5,U5,Y5,AC5,AG5,AK5,AO5) -> 55.07 | AS5: =RANK(AR5,$AR$5:$AR$30) -> 22 | AT5: B | AU5: B | AV5: C | AW5: C | AX5: C | AY5: Yanis is a polite and cooperative learner who shows effort in class activities. He performs better in practical and creative subjects such as Art and MDD. Core subjects like English and Mathematics require significant improvement. With regular support and consistent effort, Dakwa can make steady progress.
A6: 2 | B6: Heald Z'bella | C6: 26 | D6: 36 | E6: =C6+D6 -> 62 | F6: =VLOOKUP(E6,$B$42:$C$50,2) -> C | G6: 34 | H6: 41 | I6: =G6+H6 -> 75 | J6: =VLOOKUP(I6,$B$42:$C$50,2) -> B | K6: 36 | L6: 47 | M6: =K6+L6 -> 83 | N6: =VLOOKUP(M6,$B$42:$C$50,2) -> A | O6: 33 | P6: 47 | Q6: =O6+P6 -> 80 | R6: =VLOOKUP(Q6,$B$42:$C$50,2) -> A | S6: 38 | T6: 57 | U6: =S6+T6 -> 95 | V6: =VLOOKUP(U6,$B$42:$C$50,2) -> A* | W6: 37 | X6: 51 | Y6: =W6+X6 -> 88 | Z6: =VLOOKUP(Y6,$B$42:$C$50,2) -> A | AA6: 35 | AB6: 59 | AC6: =AA6+AB6 -> 94 | AD6: =VLOOKUP(AC6,$B$42:$C$50,2) -> A* | AE6: 33 | AF6: 50 | AG6: =AE6+AF6 -> 83 | AH6: =VLOOKUP(AG6,$B$42:$C$50,2) -> A | AI6: 35 | AJ6: 55 | AK6: =AI6+AJ6 -> 90 | AL6: =VLOOKUP(AK6,$B$42:$C$50,2) -> A* | AM6: 20 | AN6: 47 | AO6: =AM6+AN6 -> 67 | AP6: =VLOOKUP(AO6,$B$42:$C$50,2) -> C | AR6: =AVERAGE(E6,I6,M6,Q6,U6,Y6,AC6,AG6,AK6,AO6) -> 81.7 | AS6: =RANK(AR6,$AR$5:$AR$30) -> 1 | AT6: A | AU6: A | AV6: A | AW6: A | AX6: A | AY6: Z’bella is a highly motivated and disciplined student who consistently strives for excellence. She has shown remarkable performance across subjects, with consistently strong results. She should continue challenging herself with advanced reading and extension tasks. Overall, she is an exemplary learner and a role model. Her interest in debate and public speaking is commendable and enables her to develop research skills; let us encourage her to continue on this path.
A7: 3 | B7: De-miranda Stella | C7: 30 | D7: 31 | E7: =C7+D7 -> 61 | F7: =VLOOKUP(E7,$B$42:$C$50,2) -> C | G7: 19 | H7: 18 | I7: =G7+H7 -> 37 | J7: =VLOOKUP(I7,$B$42:$C$50,2) -> F | K7: 27 | L7: 33 | M7: =K7+L7 -> 60 | N7: =VLOOKUP(M7,$B$42:$C$50,2) -> C | O7: 34 | P7: 48 | Q7: =O7+P7 -> 82 | R7: =VLOOKUP(Q7,$B$42:$C$50,2) -> A | S7: 33 | T7: 41 | U7: =S7+T7 -> 74 | V7: =VLOOKUP(U7,$B$42:$C$50,2) -> B | W7: 30 | X7: 35 | Y7: =W7+X7 -> 65 | Z7: =VLOOKUP(Y7,$B$42:$C$50,2) -> C | AA7: 27 | AB7: 39 | AC7: =AA7+AB7 -> 66 | AD7: =VLOOKUP(AC7,$B$42:$C$50,2) -> C | AE7: 31 | AF7: 45 | AG7: =AE7+AF7 -> 76 | AH7: =VLOOKUP(AG7,$B$42:$C$50,2) -> B | AI7: 35 | AJ7: 41 | AK7: =AI7+AJ7 -> 76 | AL7: =VLOOKUP(AK7,$B$42:$C$50,2) -> B | AM7: 19.5 | AN7: 39 | AO7: =AM7+AN7 -> 58.5 | AP7: =VLOOKUP(AO7,$B$42:$C$50,2) -> D | AR7: =AVERAGE(E7,I7,M7,Q7,U7,Y7,AC7,AG7,AK7,AO7) -> 65.55 | AS7: =RANK(AR7,$AR$5:$AR$30) -> 18 | AT7: B | AU7: B | AV7: B | AW7: A | AX7: A | AY7: Stella is a dedicated student who generally performs well. However, she needs to intensify her effort in Mathematics and Science to achieve balanced progress. With targeted practice and continued support, she can improve further. Her interest in debate and public speaking is commendable and enables her to develop research skills; let us encourage her to continue on this path.
A8: 4 | B8: Vlasonjic Andrej | C8: 14 | D8: 0 | E8: =C8+D8 -> 14 | F8: =VLOOKUP(E8,$B$42:$C$50,2) -> U | I8: =G8+H8 -> 0 | J8: =VLOOKUP(I8,$B$42:$C$50,2) -> U | K8: 0 | L8: 0 | M8: =K8+L8 -> 0 | N8: =VLOOKUP(M8,$B$42:$C$50,2) -> U | O8: 15 | P8: 0 | Q8: =O8+P8 -> 15 | R8: =VLOOKUP(Q8,$B$42:$C$50,2) -> U | U8: =S8+T8 -> 0 | V8: =VLOOKUP(U8,$B$42:$C$50,2) -> U | W8: 15 | Y8: =W8+X8 -> 15 | Z8: =VLOOKUP(Y8,$B$42:$C$50,2) -> U | AA8: 10 | AC8: =AA8+AB8 -> 10 | AD8: =VLOOKUP(AC8,$B$42:$C$50,2) -> U | AE8: 12 | AG8: =AE8+AF8 -> 12 | AH8: =VLOOKUP(AG8,$B$42:$C$50,2) -> U | AI8: 14 | AJ8: 0 | AK8: =AI8+AJ8 -> 14 | AL8: =VLOOKUP(AK8,$B$42:$C$50,2) -> U | AM8: 20 | AN8: 41 | AO8: =AM8+AN8 -> 61 | AP8: =VLOOKUP(AO8,$B$42:$C$50,2) -> C | AR8: =AVERAGE(E8,I8,M8,Q8,U8,Y8,AC8,AG8,AK8,AO8) -> 14.1 | AS8: =RANK(AR8,$AR$5:$AR$30) -> 24 | AT8: B | AU8: C | AV8: C | AW8: C | AX8: C | AY8: Andrej has had limited engagement with schoolwork this term, which has affected his performance. He requires strong support to re-engage with learning. Close cooperation between home and school is essential for improvement.
A9: 5 | B9: Kalala Enoch | C9: 24 | D9: 29 | E9: =C9+D9 -> 53 | F9: =VLOOKUP(E9,$B$42:$C$50,2) -> D | G9: 31 | H9: 38 | I9: =G9+H9 -> 69 | J9: =VLOOKUP(I9,$B$42:$C$50,2) -> C | K9: 37 | L9: 43 | M9: =K9+L9 -> 80 | N9: =VLOOKUP(M9,$B$42:$C$50,2) -> A | O9: 28 | P9: 24 | Q9: =O9+P9 -> 52 | R9: =VLOOKUP(Q9,$B$42:$C$50,2) -> D | S9: 25 | T9: 46 | U9: =S9+T9 -> 71 | V9: =VLOOKUP(U9,$B$42:$C$50,2) -> B | W9: 19 | X9: 35 | Y9: =W9+X9 -> 54 | Z9: =VLOOKUP(Y9,$B$42:$C$50,2) -> D | AA9: 32 | AB9: 42 | AC9: =AA9+AB9 -> 74 | AD9: =VLOOKUP(AC9,$B$42:$C$50,2) -> B | AE9: 26 | AF9: 44 | AG9: =AE9+AF9 -> 70 | AH9: =VLOOKUP(AG9,$B$42:$C$50,2) -> B | AI9: 28 | AJ9: 38 | AK9: =AI9+AJ9 -> 66 | AL9: =VLOOKUP(AK9,$B$42:$C$50,2) -> C | AM9: 23.7 | AN9: 47 | AO9: =AM9+AN9 -> 70.7 | AP9: =VLOOKUP(AO9,$B$42:$C$50,2) -> B | AR9: =AVERAGE(E9,I9,M9,Q9,U9,Y9,AC9,AG9,AK9,AO9) -> 65.97 | AS9: =RANK(AR9,$AR$5:$AR$30) -> 16 | AT9: B | AU9: B | AV9: C | AW9: B | AX9: C | AY9: Enoch is a calm and responsible student who has shown steady performance this term. While he performs well overall, Mathematics and Science still require strengthened practice. Regular revision will greatly benefit him.
A10: 6 | B10: Rovira Phiri Lucas | C10: 26 | D10: 37 | E10: =C10+D10 -> 63 | F10: =VLOOKUP(E10,$B$42:$C$50,2) -> C | G10: 10 | H10: 22 | I10: =G10+H10 -> 32 | J10: =VLOOKUP(I10,$B$42:$C$50,2) -> F | K10: 32 | L10: 41 | M10: =K10+L10 -> 73 | N10: =VLOOKUP(M10,$B$42:$C$50,2) -> B | O10: 26 | P10: 37 | Q10: =O10+P10 -> 63 | R10: =VLOOKUP(Q10,$B$42:$C$50,2) -> C | S10: 25 | T10: 32 | U10: =S10+T10 -> 57 | V10: =VLOOKUP(U10,$B$42:$C$50,2) -> D | W10: 31 | X10: 49 | Y10: =W10+X10 -> 80 | Z10: =VLOOKUP(Y10,$B$42:$C$50,2) -> A | AA10: 24 | AB10: 27 | AC10: =AA10+AB10 -> 51 | AD10: =VLOOKUP(AC10,$B$42:$C$50,2) -> D | AE10: 31 | AF10: 41 | AG10: =AE10+AF10 -> 72 | AH10: =VLOOKUP(AG10,$B$42:$C$50,2) -> B | AI10: 30 | AJ10: 43 | AK10: =AI10+AJ10 -> 73 | AL10: =VLOOKUP(AK10,$B$42:$C$50,2) -> B | AM10: 25.5 | AN10: 53 | AO10: =AM10+AN10 -> 78.5 | AP10: =VLOOKUP(AO10,$B$42:$C$50,2) -> B | AR10: =AVERAGE(E10,I10,M10,Q10,U10,Y10,AC10,AG10,AK10,AO10) -> 64.25 | AS10: =RANK(AR10,$AR$5:$AR$30) -> 20 | AT10: B | AU10: C | AV10: C | AW10: B | AX10: C | AY10: Lucas is a learning to be a more focused, dependable and responsible student. He has continued to perform well in Science and MDD. Mathematics remains a challenge and needs extra attention. Continued effort and support at home will help him progress well in semester 2.
A11: 7 | B11: Sialwindi Maria | C11: 6 | D11: 13 | E11: =C11+D11 -> 19 | F11: =VLOOKUP(E11,$B$42:$C$50,2) -> U | G11: 8 | H11: 9 | I11: =G11+H11 -> 17 | J11: =VLOOKUP(I11,$B$42:$C$50,2) -> U | K11: 0 | L11: 11 | M11: =K11+L11 -> 11 | N11: =VLOOKUP(M11,$B$42:$C$50,2) -> U | O11: 0 | P11: 11 | Q11: =O11+P11 -> 11 | R11: =VLOOKUP(Q11,$B$42:$C$50,2) -> U | S11: 21 | T11: 18 | U11: =S11+T11 -> 39 | V11: =VLOOKUP(U11,$B$42:$C$50,2) -> F | W11: 14 | X11: 18 | Y11: =W11+X11 -> 32 | Z11: =VLOOKUP(Y11,$B$42:$C$50,2) -> F | AA11: 9 | AB11: 15 | AC11: =AA11+AB11 -> 24 | AD11: =VLOOKUP(AC11,$B$42:$C$50,2) -> G | AE11: 27 | AF11: 41 | AG11: =AE11+AF11 -> 68 | AH11: =VLOOKUP(AG11,$B$42:$C$50,2) -> C | AI11: 29 | AJ11: 37 | AK11: =AI11+AJ11 -> 66 | AL11: =VLOOKUP(AK11,$B$42:$C$50,2) -> C | AM11: 20 | AN11: 40 | AO11: =AM11+AN11 -> 60 | AP11: =VLOOKUP(AO11,$B$42:$C$50,2) -> C | AR11: =AVERAGE(E11,I11,M11,Q11,U11,Y11,AC11,AG11,AK11,AO11) -> 34.7 | AS11: =RANK(AR11,$AR$5:$AR$30) -> 23 | AT11: B | AU11: B | AV11: B | AW11: B | AX11: B | AY11: Maria is a friendly learner who participates willingly but is struggling academically. She requires strong support, particularly in English and Mathematics. Regular revision and close monitoring are strongly recommended.
A12: 8 | B12: Temba Nicholas | C12: 21 | D12: 25 | E12: =C12+D12 -> 46 | F12: =VLOOKUP(E12,$B$42:$C$50,2) -> E | G12: 15 | H12: 25 | I12: =G12+H12 -> 40 | J12: =VLOOKUP(I12,$B$42:$C$50,2) -> E | K12: 23 | L12: 40 | M12: =K12+L12 -> 63 | N12: =VLOOKUP(M12,$B$42:$C$50,2) -> C | O12: 25 | P12: 34 | Q12: =O12+P12 -> 59 | R12: =VLOOKUP(Q12,$B$42:$C$50,2) -> D | S12: 20 | T12: 33 | U12: =S12+T12 -> 53 | V12: =VLOOKUP(U12,$B$42:$C$50,2) -> D | W12: 24 | X12: 38 | Y12: =W12+X12 -> 62 | Z12: =VLOOKUP(Y12,$B$42:$C$50,2) -> C | AA12: 17 | AB12: 25 | AC12: =AA12+AB12 -> 42 | AD12: =VLOOKUP(AC12,$B$42:$C$50,2) -> E | AE12: 26 | AF12: 42 | AG12: =AE12+AF12 -> 68 | AH12: =VLOOKUP(AG12,$B$42:$C$50,2) -> C | AI12: 27 | AJ12: 39 | AK12: =AI12+AJ12 -> 66 | AL12: =VLOOKUP(AK12,$B$42:$C$50,2) -> C | AM12: 20 | AN12: 49 | AO12: =AM12+AN12 -> 69 | AP12: =VLOOKUP(AO12,$B$42:$C$50,2) -> C | AR12: =AVERAGE(E12,I12,M12,Q12,U12,Y12,AC12,AG12,AK12,AO12) -> 56.8 | AS12: =RANK(AR12,$AR$5:$AR$30) -> 21 | AT12: B | AU12: A | AV12: B | AW12: B | AX12: B | AY12: Nicholas is a steady learner who shows effort across subjects. His performance is average, with room for improvement in English and Mathematics. With consistent revision and parental support, he can improve.
A13: 9 | B13: Mavhunga Mufaro | C13: 18 | D13: 28 | E13: =C13+D13 -> 46 | F13: =VLOOKUP(E13,$B$42:$C$50,2) -> E | G13: 33 | H13: 47 | I13: =G13+H13 -> 80 | J13: =VLOOKUP(I13,$B$42:$C$50,2) -> A | K13: 31 | L13: 35 | M13: =K13+L13 -> 66 | N13: =VLOOKUP(M13,$B$42:$C$50,2) -> C | O13: 31 | P13: 37 | Q13: =O13+P13 -> 68 | R13: =VLOOKUP(Q13,$B$42:$C$50,2) -> C | S13: 36 | T13: 53 | U13: =S13+T13 -> 89 | V13: =VLOOKUP(U13,$B$42:$C$50,2) -> A | W13: 30 | X13: 46 | Y13: =W13+X13 -> 76 | Z13: =VLOOKUP(Y13,$B$42:$C$50,2) -> B | AA13: 32 | AB13: 33 | AC13: =AA13+AB13 -> 65 | AD13: =VLOOKUP(AC13,$B$42:$C$50,2) -> C | AE13: 31 | AF13: 48 | AG13: =AE13+AF13 -> 79 | AH13: =VLOOKUP(AG13,$B$42:$C$50,2) -> B | AI13: 34 | AJ13: 47 | AK13: =AI13+AJ13 -> 81 | AL13: =VLOOKUP(AK13,$B$42:$C$50,2) -> A | AM13: 20 | AN13: 50 | AO13: =AM13+AN13 -> 70 | AP13: =VLOOKUP(AO13,$B$42:$C$50,2) -> B | AR13: =AVERAGE(E13,I13,M13,Q13,U13,Y13,AC13,AG13,AK13,AO13) -> 72 | AS13: =RANK(AR13,$AR$5:$AR$30) -> 9 | AT13: B | AU13: A | AV13: A | AW13: B | AX13: A | AY13: Mufaro is a bright and responsible student who has performed strongly this term. He shows great potential and engages meaningfully in learning activities. With continued effort, he will excel even further. His interest in debate and public speaking is commendable and enables him to develop research skills; let us encourage him to continue on this path.
A14: 10 | B14: Aori Ryan | C14: 22 | D14: 35 | E14: =C14+D14 -> 57 | F14: =VLOOKUP(E14,$B$42:$C$50,2) -> D | G14: 25 | H14: 43 | I14: =G14+H14 -> 68 | J14: =VLOOKUP(I14,$B$42:$C$50,2) -> C | K14: 33 | L14: 43 | M14: =K14+L14 -> 76 | N14: =VLOOKUP(M14,$B$42:$C$50,2) -> B | O14: 37 | P14: 42 | Q14: =O14+P14 -> 79 | R14: =VLOOKUP(Q14,$B$42:$C$50,2) -> B | S14: 34 | T14: 53 | U14: =S14+T14 -> 87 | V14: =VLOOKUP(U14,$B$42:$C$50,2) -> A | W14: 38 | X14: 54 | Y14: =W14+X14 -> 92 | Z14: =VLOOKUP(Y14,$B$42:$C$50,2) -> A* | AA14: 28 | AB14: 35 | AC14: =AA14+AB14 -> 63 | AD14: =VLOOKUP(AC14,$B$42:$C$50,2) -> C | AE14: 28 | AF14: 42 | AG14: =AE14+AF14 -> 70 | AH14: =VLOOKUP(AG14,$B$42:$C$50,2) -> B | AI14: 30 | AJ14: 55 | AK14: =AI14+AJ14 -> 85 | AL14: =VLOOKUP(AK14,$B$42:$C$50,2) -> A | AM14: 21.7 | AN14: 48 | AO14: =AM14+AN14 -> 69.7 | AP14: =VLOOKUP(AO14,$B$42:$C$50,2) -> C | AR14: =AVERAGE(E14,I14,M14,Q14,U14,Y14,AC14,AG14,AK14,AO14) -> 74.67 | AS14: =RANK(AR14,$AR$5:$AR$30) -> 6 | AT14: A | AU14: B | AV14: B | AW14: B | AX14: B | AY14: Ryan is a disciplined and enthusiastic student who performs very well. His results show solid understanding across subjects. He should continue practising regularly to refine higher-order skills. A very impressive learner. His interest in debate and public speaking as demonstrated through is participation in the TedX Youth is commendable and enables him to develop research skills; let us encourage him to continue on this path.
A15: 11 | B15: Chulu Chaulela | C15: 28 | D15: 34 | E15: =C15+D15 -> 62 | F15: =VLOOKUP(E15,$B$42:$C$50,2) -> C | G15: 26 | H15: 41 | I15: =G15+H15 -> 67 | J15: =VLOOKUP(I15,$B$42:$C$50,2) -> C | K15: 28 | L15: 38 | M15: =K15+L15 -> 66 | N15: =VLOOKUP(M15,$B$42:$C$50,2) -> C | O15: 35 | P15: 34 | Q15: =O15+P15 -> 69 | R15: =VLOOKUP(Q15,$B$42:$C$50,2) -> C | S15: 27 | T15: 44 | U15: =S15+T15 -> 71 | V15: =VLOOKUP(U15,$B$42:$C$50,2) -> B | W15: 12 | X15: 39 | Y15: =W15+X15 -> 51 | Z15: =VLOOKUP(Y15,$B$42:$C$50,2) -> D | AA15: 16 | AB15: 34 | AC15: =AA15+AB15 -> 50 | AD15: =VLOOKUP(AC15,$B$42:$C$50,2) -> D | AE15: 23 | AF15: 46 | AG15: =AE15+AF15 -> 69 | AH15: =VLOOKUP(AG15,$B$42:$C$50,2) -> C | AI15: 29 | AJ15: 42 | AK15: =AI15+AJ15 -> 71 | AL15: =VLOOKUP(AK15,$B$42:$C$50,2) -> B | AM15: 27 | AN15: 52 | AO15: =AM15+AN15 -> 79 | AP15: =VLOOKUP(AO15,$B$42:$C$50,2) -> B | AR15: =AVERAGE(E15,I15,M15,Q15,U15,Y15,AC15,AG15,AK15,AO15) -> 65.5 | AS15: =RANK(AR15,$AR$5:$AR$30) -> 19 | AT15: B | AU15: B | AV15: C | AW15: B | AX15: B | AY15: Chaulela is a calm and respectful student who works steadily in class. He would benefit from pushing himself further, particularly in Mathematics and English. Increased participation will support his progress.
A16: 12 | B16: Khanve Lakshya | C16: 25 | D16: 35 | E16: =C16+D16 -> 60 | F16: =VLOOKUP(E16,$B$42:$C$50,2) -> C | G16: 29 | H16: 42 | I16: =G16+H16 -> 71 | J16: =VLOOKUP(I16,$B$42:$C$50,2) -> B | K16: 19 | L16: 49 | M16: =K16+L16 -> 68 | N16: =VLOOKUP(M16,$B$42:$C$50,2) -> C | O16: 35 | P16: 48 | Q16: =O16+P16 -> 83 | R16: =VLOOKUP(Q16,$B$42:$C$50,2) -> A | S16: 36 | T16: 57 | U16: =S16+T16 -> 93 | V16: =VLOOKUP(U16,$B$42:$C$50,2) -> A* | W16: 40 | X16: 59 | Y16: =W16+X16 -> 99 | Z16: =VLOOKUP(Y16,$B$42:$C$50,2) -> A* | AA16: 30 | AB16: 40 | AC16: =AA16+AB16 -> 70 | AD16: =VLOOKUP(AC16,$B$42:$C$50,2) -> B | AE16: 25 | AF16: 46 | AG16: =AE16+AF16 -> 71 | AH16: =VLOOKUP(AG16,$B$42:$C$50,2) -> B | AI16: 26 | AJ16: 53 | AK16: =AI16+AJ16 -> 79 | AL16: =VLOOKUP(AK16,$B$42:$C$50,2) -> B | AM16: 24 | AN16: 47 | AO16: =AM16+AN16 -> 71 | AP16: =VLOOKUP(AO16,$B$42:$C$50,2) -> B | AR16: =AVERAGE(E16,I16,M16,Q16,U16,Y16,AC16,AG16,AK16,AO16) -> 76.5 | AS16: =RANK(AR16,$AR$5:$AR$30) -> 5 | AT16: B | AU16: B | AV16: C | AW16: C | AX16: B | AY16: Lakshya is an excellent and highly disciplined learner who consistently achieves outstanding results across subjects. His work ethic and enthusiasm are commendable. He is a model student.
A17: 13 | B17: Shalak Walid | C17: 24 | D17: 36 | E17: =C17+D17 -> 60 | F17: =VLOOKUP(E17,$B$42:$C$50,2) -> C | G17: 29 | H17: 50 | I17: =G17+H17 -> 79 | J17: =VLOOKUP(I17,$B$42:$C$50,2) -> B | K17: 36 | L17: 52 | M17: =K17+L17 -> 88 | N17: =VLOOKUP(M17,$B$42:$C$50,2) -> A | O17: 29 | P17: 46 | Q17: =O17+P17 -> 75 | R17: =VLOOKUP(Q17,$B$42:$C$50,2) -> B | S17: 33 | T17: 51 | U17: =S17+T17 -> 84 | V17: =VLOOKUP(U17,$B$42:$C$50,2) -> A | W17: 39 | X17: 54 | Y17: =W17+X17 -> 93 | Z17: =VLOOKUP(Y17,$B$42:$C$50,2) -> A* | AA17: 34 | AB17: 59 | AC17: =AA17+AB17 -> 93 | AD17: =VLOOKUP(AC17,$B$42:$C$50,2) -> A* | AE17: 27 | AF17: 44 | AG17: =AE17+AF17 -> 71 | AH17: =VLOOKUP(AG17,$B$42:$C$50,2) -> B | AI17: 35 | AJ17: 48 | AK17: =AI17+AJ17 -> 83 | AL17: =VLOOKUP(AK17,$B$42:$C$50,2) -> A | AM17: 24 | AN17: 49 | AO17: =AM17+AN17 -> 73 | AP17: =VLOOKUP(AO17,$B$42:$C$50,2) -> B | AR17: =AVERAGE(E17,I17,M17,Q17,U17,Y17,AC17,AG17,AK17,AO17) -> 79.9 | AS17: =RANK(AR17,$AR$5:$AR$30) -> 2 | AT17: B | AU17: B | AV17: B | AW17: C | AX17: B | AY17: Walid is a focused and ambitious student who has demonstrated strong performance, especially in Science and Business Studies. Continued attention to English will help maintain balance. He has had a strong term.
A18: 14 | B18: Sikasula Gladys | D18: 0 | E18: =C18+D18 -> 0 | F18: =VLOOKUP(E18,$B$42:$C$50,2) -> U | G18: 12 | I18: =G18+H18 -> 12 | J18: =VLOOKUP(I18,$B$42:$C$50,2) -> U | K18: 0 | L18: 0 | M18: =K18+L18 -> 0 | N18: =VLOOKUP(M18,$B$42:$C$50,2) -> U | O18: 0 | P18: 0 | Q18: =O18+P18 -> 0 | R18: =VLOOKUP(Q18,$B$42:$C$50,2) -> U | U18: =S18+T18 -> 0 | V18: =VLOOKUP(U18,$B$42:$C$50,2) -> U | W18: 11 | Y18: =W18+X18 -> 11 | Z18: =VLOOKUP(Y18,$B$42:$C$50,2) -> U | AA18: 17 | AC18: =AA18+AB18 -> 17 | AD18: =VLOOKUP(AC18,$B$42:$C$50,2) -> U | AE18: 15 | AG18: =AE18+AF18 -> 15 | AH18: =VLOOKUP(AG18,$B$42:$C$50,2) -> U | AI18: 0 | AJ18: 0 | AK18: =AI18+AJ18 -> 0 | AL18: =VLOOKUP(AK18,$B$42:$C$50,2) -> U | AO18: =AM18+AN18 -> 0 | AP18: =VLOOKUP(AO18,$B$42:$C$50,2) -> U | AR18: =AVERAGE(E18,I18,M18,Q18,U18,Y18,AC18,AG18,AK18,AO18) -> 5.5 | AS18: =RANK(AR18,$AR$5:$AR$30) -> 25 | AT18: B | AU18: A | AV18: B | AW18: A | AX18: B
A19: 15 | B19: Siame Kayla | C19: 27 | D19: 35 | E19: =C19+D19 -> 62 | F19: =VLOOKUP(E19,$B$42:$C$50,2) -> C | G19: 31 | H19: 49 | I19: =G19+H19 -> 80 | J19: =VLOOKUP(I19,$B$42:$C$50,2) -> A | K19: 39 | L19: 45 | M19: =K19+L19 -> 84 | N19: =VLOOKUP(M19,$B$42:$C$50,2) -> A | O19: 37 | P19: 48 | Q19: =O19+P19 -> 85 | R19: =VLOOKUP(Q19,$B$42:$C$50,2) -> A | S19: 40 | T19: 53 | U19: =S19+T19 -> 93 | V19: =VLOOKUP(U19,$B$42:$C$50,2) -> A* | W19: 34 | X19: 46 | Y19: =W19+X19 -> 80 | Z19: =VLOOKUP(Y19,$B$42:$C$50,2) -> A | AA19: 32 | AB19: 52 | AC19: =AA19+AB19 -> 84 | AD19: =VLOOKUP(AC19,$B$42:$C$50,2) -> A | AE19: 26 | AF19: 43 | AG19: =AE19+AF19 -> 69 | AH19: =VLOOKUP(AG19,$B$42:$C$50,2) -> C | AI19: 36 | AJ19: 51 | AK19: =AI19+AJ19 -> 87 | AL19: =VLOOKUP(AK19,$B$42:$C$50,2) -> A | AM19: 23.5 | AN19: 49 | AO19: =AM19+AN19 -> 72.5 | AP19: =VLOOKUP(AO19,$B$42:$C$50,2) -> B | AR19: =AVERAGE(E19,I19,M19,Q19,U19,Y19,AC19,AG19,AK19,AO19) -> 79.65 | AS19: =RANK(AR19,$AR$5:$AR$30) -> 3 | AT19: B | AU19: A | AV19: B | AW19: B | AX19: B | AY19: Kayla is an excellent student who demonstrates strong academic ability and admirable focus. Her participation in class is impressive, and her results reflect consistent hard work. She should continue extending herself through advanced practice. A commendable achiever. Her interest in debate and public speaking is commendable and enables her to develop research skills; let us encourage her to continue on this path.
A20: 16 | B20: Ngoshi Jayden | C20: 21 | D20: 36 | E20: =C20+D20 -> 57 | F20: =VLOOKUP(E20,$B$42:$C$50,2) -> D | G20: 24 | H20: 39 | I20: =G20+H20 -> 63 | J20: =VLOOKUP(I20,$B$42:$C$50,2) -> C | K20: 35 | L20: 50 | M20: =K20+L20 -> 85 | N20: =VLOOKUP(M20,$B$42:$C$50,2) -> A | O20: 21 | P20: 44 | Q20: =O20+P20 -> 65 | R20: =VLOOKUP(Q20,$B$42:$C$50,2) -> C | S20: 36 | T20: 49 | U20: =S20+T20 -> 85 | V20: =VLOOKUP(U20,$B$42:$C$50,2) -> A | W20: 40 | X20: 56 | Y20: =W20+X20 -> 96 | Z20: =VLOOKUP(Y20,$B$42:$C$50,2) -> A* | AA20: 32 | AB20: 54 | AC20: =AA20+AB20 -> 86 | AD20: =VLOOKUP(AC20,$B$42:$C$50,2) -> A | AE20: 27 | AF20: 38 | AG20: =AE20+AF20 -> 65 | AH20: =VLOOKUP(AG20,$B$42:$C$50,2) -> C | AI20: 30 | AJ20: 46 | AK20: =AI20+AJ20 -> 76 | AL20: =VLOOKUP(AK20,$B$42:$C$50,2) -> B | AM20: 19 | AN20: 43 | AO20: =AM20+AN20 -> 62 | AP20: =VLOOKUP(AO20,$B$42:$C$50,2) -> C | AR20: =AVERAGE(E20,I20,M20,Q20,U20,Y20,AC20,AG20,AK20,AO20) -> 74 | AS20: =RANK(AR20,$AR$5:$AR$30) -> 7 | AT20: B | AU20: A | AV20: B | AW20: B | AX20: A | AY20: Jayden is a confident and well-organised student whose performance this term is impressive. He demonstrates strong understanding across subjects. Continued extension work will help push him even further.
A21: 17 | B21: Chiwoni Isabella | C21: 24 | D21: 38 | E21: =C21+D21 -> 62 | F21: =VLOOKUP(E21,$B$42:$C$50,2) -> C | G21: 25 | H21: 20 | I21: =G21+H21 -> 45 | J21: =VLOOKUP(I21,$B$42:$C$50,2) -> E | K21: 33 | L21: 38 | M21: =K21+L21 -> 71 | N21: =VLOOKUP(M21,$B$42:$C$50,2) -> B | O21: 32 | P21: 38 | Q21: =O21+P21 -> 70 | R21: =VLOOKUP(Q21,$B$42:$C$50,2) -> B | S21: 38 | T21: 51 | U21: =S21+T21 -> 89 | V21: =VLOOKUP(U21,$B$42:$C$50,2) -> A | W21: 36 | X21: 51 | Y21: =W21+X21 -> 87 | Z21: =VLOOKUP(Y21,$B$42:$C$50,2) -> A | AA21: 32 | AB21: 39 | AC21: =AA21+AB21 -> 71 | AD21: =VLOOKUP(AC21,$B$42:$C$50,2) -> B | AE21: 29 | AF21: 43 | AG21: =AE21+AF21 -> 72 | AH21: =VLOOKUP(AG21,$B$42:$C$50,2) -> B | AI21: 30 | AJ21: 46 | AK21: =AI21+AJ21 -> 76 | AL21: =VLOOKUP(AK21,$B$42:$C$50,2) -> B | AM21: 22.7 | AN21: 51 | AO21: =AM21+AN21 -> 73.7 | AP21: =VLOOKUP(AO21,$B$42:$C$50,2) -> B | AR21: =AVERAGE(E21,I21,M21,Q21,U21,Y21,AC21,AG21,AK21,AO21) -> 71.67 | AS21: =RANK(AR21,$AR$5:$AR$30) -> 10 | AT21: B | AU21: B | AV21: B | AW21: B | AX21: B | AY21: Isabella is a diligent and attentive learner who continues to perform well. Her results across subjects show strong effort and ability. She is encouraged to maintain consistent revision and keep pushing for excellence. Her interest in expressive arts as demonstrated through her participation in the End of Year Production is commendable; let us encourage her to continue on this path.
A22: 18 | B22: Vergeer Aiden | C22: 23 | D22: 43 | E22: =C22+D22 -> 66 | F22: =VLOOKUP(E22,$B$42:$C$50,2) -> C | G22: 23 | H22: 37 | I22: =G22+H22 -> 60 | J22: =VLOOKUP(I22,$B$42:$C$50,2) -> C | K22: 26 | L22: 34 | M22: =K22+L22 -> 60 | N22: =VLOOKUP(M22,$B$42:$C$50,2) -> C | O22: 38 | P22: 43 | Q22: =O22+P22 -> 81 | R22: =VLOOKUP(Q22,$B$42:$C$50,2) -> A | S22: 28 | T22: 46 | U22: =S22+T22 -> 74 | V22: =VLOOKUP(U22,$B$42:$C$50,2) -> B | W22: 32 | X22: 45 | Y22: =W22+X22 -> 77 | Z22: =VLOOKUP(Y22,$B$42:$C$50,2) -> B | AA22: 26 | AB22: 28 | AC22: =AA22+AB22 -> 54 | AD22: =VLOOKUP(AC22,$B$42:$C$50,2) -> D | AE22: 30 | AF22: 35 | AG22: =AE22+AF22 -> 65 | AH22: =VLOOKUP(AG22,$B$42:$C$50,2) -> C | AI22: 35 | AJ22: 46 | AK22: =AI22+AJ22 -> 81 | AL22: =VLOOKUP(AK22,$B$42:$C$50,2) -> A | AM22: 21.7 | AN22: 48 | AO22: =AM22+AN22 -> 69.7 | AP22: =VLOOKUP(AO22,$B$42:$C$50,2) -> C | AR22: =AVERAGE(E22,I22,M22,Q22,U22,Y22,AC22,AG22,AK22,AO22) -> 68.77 | AS22: =RANK(AR22,$AR$5:$AR$30) -> 14 | AT22: B | AU22: B | AV22: A | AW22: B | AX22: B | AY22: Aiden is a well-behaved and responsible learner who demonstrates a positive attitude. His performance has been steady, with strengths in several subjects. Mathematics and Science require additional practice. With focused revision and continued support, he has the potential to excel.
A23: 19 | B23: Mustafa Amina | C23: 20 | D23: 27 | E23: =C23+D23 -> 47 | F23: =VLOOKUP(E23,$B$42:$C$50,2) -> E | G23: 28 | H23: 21 | I23: =G23+H23 -> 49 | J23: =VLOOKUP(I23,$B$42:$C$50,2) -> E | K23: 21 | L23: 38 | M23: =K23+L23 -> 59 | N23: =VLOOKUP(M23,$B$42:$C$50,2) -> D | O23: 31 | P23: 41 | Q23: =O23+P23 -> 72 | R23: =VLOOKUP(Q23,$B$42:$C$50,2) -> B | S23: 36 | T23: 24 | U23: =S23+T23 -> 60 | V23: =VLOOKUP(U23,$B$42:$C$50,2) -> C | W23: 38 | X23: 42 | Y23: =W23+X23 -> 80 | Z23: =VLOOKUP(Y23,$B$42:$C$50,2) -> A | AA23: 32 | AB23: 33 | AC23: =AA23+AB23 -> 65 | AD23: =VLOOKUP(AC23,$B$42:$C$50,2) -> C | AE23: 31 | AF23: 42 | AG23: =AE23+AF23 -> 73 | AH23: =VLOOKUP(AG23,$B$42:$C$50,2) -> B | AI23: 32 | AJ23: 47 | AK23: =AI23+AJ23 -> 79 | AL23: =VLOOKUP(AK23,$B$42:$C$50,2) -> B | AM23: 24.9 | AN23: 51 | AO23: =AM23+AN23 -> 75.9 | AP23: =VLOOKUP(AO23,$B$42:$C$50,2) -> B | AR23: =AVERAGE(E23,I23,M23,Q23,U23,Y23,AC23,AG23,AK23,AO23) -> 65.99 | AS23: =RANK(AR23,$AR$5:$AR$30) -> 15 | AT23: B | AU23: B | AV23: B | AW23: C | AX23: C | AY23: Amina is a well-mannered learner who needs to work on speakingly responsibly. She has performed steadily across subjects, though Mathematics needs more focused attention. She is encouraged to practise regularly and attend support sessions to achieve even better balance. Her interest in debate and public speaking is commendable and enables her to develop research skills; let us encourage her to continue on this path.
A24: 20 | B24: Chinyemba Asia Adele | C24: 27 | D24: 36 | E24: =C24+D24 -> 63 | F24: =VLOOKUP(E24,$B$42:$C$50,2) -> C | G24: 26 | H24: 22 | I24: =G24+H24 -> 48 | J24: =VLOOKUP(I24,$B$42:$C$50,2) -> E | K24: 29 | L24: 37 | M24: =K24+L24 -> 66 | N24: =VLOOKUP(M24,$B$42:$C$50,2) -> C | O24: 34 | P24: 37 | Q24: =O24+P24 -> 71 | R24: =VLOOKUP(Q24,$B$42:$C$50,2) -> B | S24: 37 | T24: 38 | U24: =S24+T24 -> 75 | V24: =VLOOKUP(U24,$B$42:$C$50,2) -> B | W24: 32 | X24: 43 | Y24: =W24+X24 -> 75 | Z24: =VLOOKUP(Y24,$B$42:$C$50,2) -> B | AA24: 28 | AB24: 31 | AC24: =AA24+AB24 -> 59 | AD24: =VLOOKUP(AC24,$B$42:$C$50,2) -> D | AE24: 31 | AF24: 48 | AG24: =AE24+AF24 -> 79 | AH24: =VLOOKUP(AG24,$B$42:$C$50,2) -> B | AI24: 35 | AJ24: 49 | AK24: =AI24+AJ24 -> 84 | AL24: =VLOOKUP(AK24,$B$42:$C$50,2) -> A | AM24: 27.7 | AN24: 49 | AO24: =AM24+AN24 -> 76.7 | AP24: =VLOOKUP(AO24,$B$42:$C$50,2) -> B | AR24: =AVERAGE(E24,I24,M24,Q24,U24,Y24,AC24,AG24,AK24,AO24) -> 69.67 | AS24: =RANK(AR24,$AR$5:$AR$30) -> 12 | AT24: B | AU24: B | AV24: A | AW24: B | AX24: B | AY24: Asia is a quiet but hardworking student who approaches tasks with seriousness. Her performance is strong overall. She is encouraged to build more confidence in group work and discussion tasks. Continued support at home will boost her learning further. Her interest in expressive arts as demonstrated through her participation in the End of Year Production is commendable; let us encourage her to continue on this path.
A25: 21 | B25: Khalifeh Julia | C25: 12 | D25: 31 | E25: =C25+D25 -> 43 | F25: =VLOOKUP(E25,$B$42:$C$50,2) -> E | G25: 24 | H25: 30 | I25: =G25+H25 -> 54 | J25: =VLOOKUP(I25,$B$42:$C$50,2) -> D | K25: 27 | L25: 29 | M25: =K25+L25 -> 56 | N25: =VLOOKUP(M25,$B$42:$C$50,2) -> D | O25: 30 | P25: 40 | Q25: =O25+P25 -> 70 | R25: =VLOOKUP(Q25,$B$42:$C$50,2) -> B | S25: 29 | T25: 44 | U25: =S25+T25 -> 73 | V25: =VLOOKUP(U25,$B$42:$C$50,2) -> B | W25: 38 | X25: 40 | Y25: =W25+X25 -> 78 | Z25: =VLOOKUP(Y25,$B$42:$C$50,2) -> B | AA25: 30 | AB25: 32 | AC25: =AA25+AB25 -> 62 | AD25: =VLOOKUP(AC25,$B$42:$C$50,2) -> C | AE25: 32 | AF25: 53 | AG25: =AE25+AF25 -> 85 | AH25: =VLOOKUP(AG25,$B$42:$C$50,2) -> A | AI25: 31 | AJ25: 38 | AK25: =AI25+AJ25 -> 69 | AL25: =VLOOKUP(AK25,$B$42:$C$50,2) -> C | AM25: 20.5 | AN25: 48 | AO25: =AM25+AN25 -> 68.5 | AP25: =VLOOKUP(AO25,$B$42:$C$50,2) -> C | AR25: =AVERAGE(E25,I25,M25,Q25,U25,Y25,AC25,AG25,AK25,AO25) -> 65.85 | AS25: =RANK(AR25,$AR$5:$AR$30) -> 17 | AT25: B | AU25: B | AV25: B | AW25: A | AX25: B | AY25: Julia is a friendly and cooperative student with average performance. She shows strengths in creative subjects, while English and Mathematics require more practice. Encouragement and revision will help her progress.
A26: 22 | B26: Dubey Navya | C26: 20 | D26: 37 | E26: =C26+D26 -> 57 | F26: =VLOOKUP(E26,$B$42:$C$50,2) -> D | G26: 30 | H26: 39 | I26: =G26+H26 -> 69 | J26: =VLOOKUP(I26,$B$42:$C$50,2) -> C | K26: 32 | L26: 44 | M26: =K26+L26 -> 76 | N26: =VLOOKUP(M26,$B$42:$C$50,2) -> B | O26: 33 | P26: 43 | Q26: =O26+P26 -> 76 | R26: =VLOOKUP(Q26,$B$42:$C$50,2) -> B | S26: 37 | T26: 44 | U26: =S26+T26 -> 81 | V26: =VLOOKUP(U26,$B$42:$C$50,2) -> A | W26: 27 | X26: 47 | Y26: =W26+X26 -> 74 | Z26: =VLOOKUP(Y26,$B$42:$C$50,2) -> B | AA26: 32 | AB26: 31 | AC26: =AA26+AB26 -> 63 | AD26: =VLOOKUP(AC26,$B$42:$C$50,2) -> C | AE26: 34 | AF26: 55 | AG26: =AE26+AF26 -> 89 | AH26: =VLOOKUP(AG26,$B$42:$C$50,2) -> A | AI26: 34 | AJ26: 40 | AK26: =AI26+AJ26 -> 74 | AL26: =VLOOKUP(AK26,$B$42:$C$50,2) -> B | AM26: 28.5 | AN26: 52 | AO26: =AM26+AN26 -> 80.5 | AP26: =VLOOKUP(AO26,$B$42:$C$50,2) -> A | AR26: =AVERAGE(E26,I26,M26,Q26,U26,Y26,AC26,AG26,AK26,AO26) -> 73.95 | AS26: =RANK(AR26,$AR$5:$AR$30) -> 8 | AT26: A | AU26: A | AV26: A | AW26: B | AX26: B | AY26: Navya is a focused and hardworking student who consistently produces quality work. She excels in several subjects and shows strong commitment. Continuing to challenge herself with advanced tasks will further strengthen her progress.
A27: 23 | B27: Jane Shane | C27: 26 | D27: 44 | E27: =C27+D27 -> 70 | F27: =VLOOKUP(E27,$B$42:$C$50,2) -> B | G27: 27 | H27: 38 | I27: =G27+H27 -> 65 | J27: =VLOOKUP(I27,$B$42:$C$50,2) -> C | K27: 36 | L27: 41 | M27: =K27+L27 -> 77 | N27: =VLOOKUP(M27,$B$42:$C$50,2) -> B | O27: 32 | P27: 50 | Q27: =O27+P27 -> 82 | R27: =VLOOKUP(Q27,$B$42:$C$50,2) -> A | S27: 36 | T27: 48 | U27: =S27+T27 -> 84 | V27: =VLOOKUP(U27,$B$42:$C$50,2) -> A | W27: 38 | X27: 51 | Y27: =W27+X27 -> 89 | Z27: =VLOOKUP(Y27,$B$42:$C$50,2) -> A | AA27: 35 | AB27: 31 | AC27: =AA27+AB27 -> 66 | AD27: =VLOOKUP(AC27,$B$42:$C$50,2) -> C | AE27: 30 | AF27: 48 | AG27: =AE27+AF27 -> 78 | AH27: =VLOOKUP(AG27,$B$42:$C$50,2) -> B | AI27: 34 | AJ27: 54 | AK27: =AI27+AJ27 -> 88 | AL27: =VLOOKUP(AK27,$B$42:$C$50,2) -> A | AM27: 19 | AN27: 48 | AO27: =AM27+AN27 -> 67 | AP27: =VLOOKUP(AO27,$B$42:$C$50,2) -> C | AR27: =AVERAGE(E27,I27,M27,Q27,U27,Y27,AC27,AG27,AK27,AO27) -> 76.6 | AS27: =RANK(AR27,$AR$5:$AR$30) -> 4 | AT27: B | AU27: B | AV27: B | AW27: B | AX27: B | AY27: Shane is a committed student who continues to produce excellent work. His strong performance across subjects is commendable. To maintain this trajectory, he is encouraged to continue practising regularly and engaging in extension activities. Shane's enthusiastic participation in TEDx LOTS demonstrated growing confidence and a willingness to engage beyond the classroom. He is an exemplary learner. His interest in debate and public speaking as demonstrated through is participation in the TedX Youth is commendable and enables him to develop research skills; let us encourage him to continue on this path.
A28: 24 | B28: Chileshe Chebo | C28: 27 | D28: 31 | E28: =C28+D28 -> 58 | F28: =VLOOKUP(E28,$B$42:$C$50,2) -> D | G28: 29 | H28: 34 | I28: =G28+H28 -> 63 | J28: =VLOOKUP(I28,$B$42:$C$50,2) -> C | K28: 24 | L28: 35 | M28: =K28+L28 -> 59 | N28: =VLOOKUP(M28,$B$42:$C$50,2) -> D | O28: 30 | P28: 35 | Q28: =O28+P28 -> 65 | R28: =VLOOKUP(Q28,$B$42:$C$50,2) -> C | S28: 35 | T28: 48 | U28: =S28+T28 -> 83 | V28: =VLOOKUP(U28,$B$42:$C$50,2) -> A | W28: 35 | X28: 52 | Y28: =W28+X28 -> 87 | Z28: =VLOOKUP(Y28,$B$42:$C$50,2) -> A | AA28: 29 | AB28: 49 | AC28: =AA28+AB28 -> 78 | AD28: =VLOOKUP(AC28,$B$42:$C$50,2) -> B | AE28: 32 | AF28: 43 | AG28: =AE28+AF28 -> 75 | AH28: =VLOOKUP(AG28,$B$42:$C$50,2) -> B | AI28: 36 | AJ28: 43 | AK28: =AI28+AJ28 -> 79 | AL28: =VLOOKUP(AK28,$B$42:$C$50,2) -> B | AM28: 19 | AN28: 48 | AO28: =AM28+AN28 -> 67 | AP28: =VLOOKUP(AO28,$B$42:$C$50,2) -> C | AR28: =AVERAGE(E28,I28,M28,Q28,U28,Y28,AC28,AG28,AK28,AO28) -> 71.4 | AS28: =RANK(AR28,$AR$5:$AR$30) -> 11 | AT28: B | AU28: A | AV28: A | AW28: A | AX28: A | AY28: Chebo is a polite and hardworking student who performs well in several subjects. Her consistent effort is evident in her results. Strengthening areas of slight weakness through more practice will help her excel even more.
A29: 25 | B29: Ahmed Hussein Ali | C29: 23 | D29: 34 | E29: =C29+D29 -> 57 | F29: =VLOOKUP(E29,$B$42:$C$50,2) -> D | G29: 19 | H29: 36 | I29: =G29+H29 -> 55 | J29: =VLOOKUP(I29,$B$42:$C$50,2) -> D | K29: 25 | L29: 39 | M29: =K29+L29 -> 64 | N29: =VLOOKUP(M29,$B$42:$C$50,2) -> C | O29: 32 | P29: 37 | Q29: =O29+P29 -> 69 | R29: =VLOOKUP(Q29,$B$42:$C$50,2) -> C | S29: 33 | T29: 41 | U29: =S29+T29 -> 74 | V29: =VLOOKUP(U29,$B$42:$C$50,2) -> B | W29: 34 | X29: 48 | Y29: =W29+X29 -> 82 | Z29: =VLOOKUP(Y29,$B$42:$C$50,2) -> A | AA29: 24 | AB29: 34 | AC29: =AA29+AB29 -> 58 | AD29: =VLOOKUP(AC29,$B$42:$C$50,2) -> D | AE29: 23 | AF29: 45 | AG29: =AE29+AF29 -> 68 | AH29: =VLOOKUP(AG29,$B$42:$C$50,2) -> C | AI29: 34 | AJ29: 49 | AK29: =AI29+AJ29 -> 83 | AL29: =VLOOKUP(AK29,$B$42:$C$50,2) -> A | AM29: 29 | AN29: 50 | AO29: =AM29+AN29 -> 79 | AP29: =VLOOKUP(AO29,$B$42:$C$50,2) -> B | AR29: =AVERAGE(E29,I29,M29,Q29,U29,Y29,AC29,AG29,AK29,AO29) -> 68.9 | AS29: =RANK(AR29,$AR$5:$AR$30) -> 13 | AT29: A | AU29: B | AV29: B | AW29: B | AX29: C | AY29: Hussein is an enthusiastic learner who participates actively in class. His performance is generally strong, though he needs to give more focused effort to Mathematics. With consistent revision, he will continue to improve.
A30: 26
A31: 27
B34: Average | E34: =AVERAGE(E4:E29) -> 50.48 | I34: =AVERAGE(I5:I29) -> 53.52 | M34: =AVERAGE(M4:M29) -> 61.48 | Q34: =AVERAGE(Q4:Q29) -> 63.48 | U34: =AVERAGE(U4:U29) -> 69.56 | Y34: =AVERAGE(Y4:Y29) -> 71.24 | AC34: =AVERAGE(AC4:AC29) -> 61.8 | AG34: =AVERAGE(AG4:AG29) -> 68.48 | AK34: =AVERAGE(AK4:AK29) -> 71.68 | AO34: =AVERAGE(AO4:AO29) -> 67.744
B35: NO. Students | E35: =COUNT(E4:E29) -> 25 | I35: =COUNT(I5:I29) -> 25 | M35: =COUNT(M4:M29) -> 25 | Q35: =COUNT(Q4:Q29) -> 25 | U35: =COUNT(U4:U29) -> 25 | Y35: =COUNT(Y4:Y29) -> 25 | AC35: =COUNT(AC4:AC29) -> 25 | AG35: =COUNT(AG4:AG29) -> 25 | AK35: =COUNT(AK4:AK29) -> 25 | AO35: =COUNT(AO4:AO29) -> 25
B36: Pass | E36: =COUNTIF(E4:E29,">49") -> 17 | I36: =COUNTIF(I5:I29,">49") -> 15 | M36: =COUNTIF(M4:M29,">49") -> 21 | Q36: =COUNTIF(Q4:Q29,">49") -> 21 | U36: =COUNTIF(U4:U29,">49") -> 22 | Y36: =COUNTIF(Y4:Y29,">49") -> 22 | AC36: =COUNTIF(AC4:AC29,">49") -> 21 | AG36: =COUNTIF(AG4:AG29,">49") -> 23 | AK36: =COUNTIF(AK4:AK29,">49") -> 23 | AO36: =COUNTIF(AO4:AO29,">49") -> 24
B37: Fail | E37: =COUNTIF(E4:E29,"<50") -> 8 | I37: =COUNTIF(I5:I29,"<50") -> 10 | M37: =COUNTIF(M4:M29,"<50") -> 4 | Q37: =COUNTIF(Q4:Q29,"<50") -> 4 | U37: =COUNTIF(U4:U29,"<50") -> 3 | Y37: =COUNTIF(Y4:Y29,"<50") -> 3 | AC37: =COUNTIF(AC4:AC29,"<50") -> 4 | AG37: =COUNTIF(AG4:AG29,"<50") -> 2 | AK37: =COUNTIF(AK4:AK29,"<50") -> 2 | AO37: =COUNTIF(AO4:AO29,"<50") -> 1
B38: Pass Rate % | E38: =E36*100/E35 -> 68 | I38: =I36*100/I35 -> 60 | M38: =M36*100/M35 -> 84 | Q38: =Q36*100/Q35 -> 84 | U38: =U36*100/U35 -> 88 | Y38: =Y36*100/Y35 -> 88 | AC38: =AC36*100/AC35 -> 84 | AG38: =AG36*100/AG35 -> 92 | AK38: =AK36*100/AK35 -> 92 | AO38: =AO36*100/AO35 -> 96
A42: 00-19 | B42: 0 | C42: U
A43: 20-29 | B43: 20 | C43: G
A44: 30-39 | B44: 30 | C44: F
A45: 40-49 | B45: 40 | C45: E
A46: 50-59 | B46: 50 | C46: D
A47: 60-69 | B47: 60 | C47: C
A48: 70-79 | B48: 70 | C48: B
A49: 80-89 | B49: 80 | C49: A
A50: 90-100 | B50: 90 | C50: A*

Sheet LS2B
A3: Roll N0. | B3: Name | C3: English | G3: Mathematics | K3: Science | O3: Global Perspectives | S3: New Computing | W3: Business Studies | AA3: French | AE3: Art | AI3: MDD | AM3: PE | AR3: AVERAGE | AS3: POSITION | AT3: CREATIVITY | AU3: RESPECT | AV3: EXCELLENCE | AW3: EMPATHY | AX3: DISCPLINE | AY3: CLASS TEACHER'S COMMENT
C4: Formative | D4: Summative | E4: Final Mark | F4: Grade | G4: Formative | H4: Summative | I4: Final Mark | J4: Grade | K4: Formative | L4: Summative | M4: Final Mark | N4: Grade | O4: Formative | P4: Summative | Q4: Final Mark | R4: Grade | S4: Formative | T4: Summative | U4: Final Mark | V4: Grade | W4: Formative | X4: Summative | Y4: Final Mark | Z4: Grade | AA4: Formative | AB4: Summative | AC4: Final Mark | AD4: Grade | AE4: Formative | AF4: Summative | AG4: Final Mark | AH4: Grade | AI4: Formative | AJ4: Summative | AK4: Final Mark | AL4: Grade | AM4: Formative | AN4: Summative | AO4: Final Mark | AP4: Grade
A5: 1 | B5: Mathur Sumay | C5: 24 | D5: 31 | E5: =C5+D5 -> 55 | F5: =VLOOKUP(E5,$B$38:$C$46,2) -> D | G5: 22 | H5: 40 | I5: =G5+H5 -> 62 | J5: =VLOOKUP(I5,$B$38:$C$46,2) -> C | K5: 33 | L5: 41 | M5: =K5+L5 -> 74 | N5: =VLOOKUP(M5,$B$38:$C$46,2) -> B | O5: 29 | P5: 52 | Q5: =O5+P5 -> 81 | R5: =VLOOKUP(Q5,$B$38:$C$46,2) -> A | S5: 36 | T5: 56 | U5: =S5+T5 -> 92 | V5: =VLOOKUP(U5,$B$38:$C$46,2) -> A* | W5: 39 | X5: 47 | Y5: =W5+X5 -> 86 | Z5: =VLOOKUP(Y5,$B$38:$C$46,2) -> A | AA5: 34 | AB5: 33 | AC5: =AA5+AB5 -> 67 | AD5: =VLOOKUP(AC5,$B$38:$C$46,2) -> C | AE5: 27 | AF5: 46 | AG5: =AE5+AF5 -> 73 | AH5: =VLOOKUP(AG5,$B$38:$C$46,2) -> B | AI5: 34 | AJ5: 46 | AK5: =AI5+AJ5 -> 80 | AL5: =VLOOKUP(AK5,$B$38:$C$46,2) -> A | AM5: 26.7 | AN5: 48 | AO5: =AM5+AN5 -> 74.7 | AP5: =VLOOKUP(AO5,$B$38:$C$46,2) -> B | AR5: =AVERAGE(E5,I5,M5,Q5,U5,Y5,AC5,AG5,AK5,AO5) -> 74.47 | AS5: =RANK(AR5,$AR$5:$AR$27) -> 7 | AT5: B | AU5: A | AV5: C | AW5: B | AX5: B | AY5: Sumay is a well-behaved and responsible learner who consistently demonstrates a positive attitude. He participates actively in lessons and works well with his peers. His performance this term has been steady; however, English and French require additional attention. I recommend regular practice and consistency in written work. With continued support, Sumay has the potential to excel across all subjects. Beyond the classroom, Sumay has also demonstrated impressive leadership and communication skills by actively participating in MUN activities. His ability to express his ideas clearly and persuasively is truly outstanding.
A6: 2 | B6: Muhire Blair | C6: 32 | D6: 35 | E6: =C6+D6 -> 67 | F6: =VLOOKUP(E6,$B$38:$C$46,2) -> C | G6: 30 | H6: 41 | I6: =G6+H6 -> 71 | J6: =VLOOKUP(I6,$B$38:$C$46,2) -> B | K6: 32 | L6: 48 | M6: =K6+L6 -> 80 | N6: =VLOOKUP(M6,$B$38:$C$46,2) -> A | O6: 33 | P6: 41 | Q6: =O6+P6 -> 74 | R6: =VLOOKUP(Q6,$B$38:$C$46,2) -> B | S6: 39 | T6: 56 | U6: =S6+T6 -> 95 | V6: =VLOOKUP(U6,$B$38:$C$46,2) -> A* | W6: 33 | X6: 44 | Y6: =W6+X6 -> 77 | Z6: =VLOOKUP(Y6,$B$38:$C$46,2) -> B | AA6: 36 | AB6: 52 | AC6: =AA6+AB6 -> 88 | AD6: =VLOOKUP(AC6,$B$38:$C$46,2) -> A | AE6: 34 | AF6: 55 | AG6: =AE6+AF6 -> 89 | AH6: =VLOOKUP(AG6,$B$38:$C$46,2) -> A | AI6: 31 | AJ6: 48 | AK6: =AI6+AJ6 -> 79 | AL6: =VLOOKUP(AK6,$B$38:$C$46,2) -> B | AM6: 27.6 | AN6: 48 | AO6: =AM6+AN6 -> 75.6 | AP6: =VLOOKUP(AO6,$B$38:$C$46,2) -> B | AR6: =AVERAGE(E6,I6,M6,Q6,U6,Y6,AC6,AG6,AK6,AO6) -> 79.56 | AS6: =RANK(AR6,$AR$5:$AR$27) -> 4 | AT6: A | AU6: A | AV6: B | AW6: B | AX6: B | AY6: Blair is a self motivated and disciplined student who consistently strives to excel in his academic work. He has performed well in all subjects and his engagement in class discussions is commendable. To further strengthen his learning, he should continue challenging himself with advanced reading and extension activities. Beyond the classroom, Blair has also demonstrated impressive leadership and communication skills by actively participating in MUN and debate activities. His ability to express his ideas clearly and persuasively is truly outstanding.
A7: 3 | B7: Ncube Zanele | C7: 30 | D7: 33 | E7: =C7+D7 -> 63 | F7: =VLOOKUP(E7,$B$38:$C$46,2) -> C | G7: 20 | H7: 35 | I7: =G7+H7 -> 55 | J7: =VLOOKUP(I7,$B$38:$C$46,2) -> D | K7: 37 | L7: 42 | M7: =K7+L7 -> 79 | N7: =VLOOKUP(M7,$B$38:$C$46,2) -> B | O7: 30 | P7: 37 | Q7: =O7+P7 -> 67 | R7: =VLOOKUP(Q7,$B$38:$C$46,2) -> C | S7: 35 | T7: 54 | U7: =S7+T7 -> 89 | V7: =VLOOKUP(U7,$B$38:$C$46,2) -> A | W7: 30 | X7: 40 | Y7: =W7+X7 -> 70 | Z7: =VLOOKUP(Y7,$B$38:$C$46,2) -> B | AA7: 24 | AB7: 46 | AC7: =AA7+AB7 -> 70 | AD7: =VLOOKUP(AC7,$B$38:$C$46,2) -> B | AE7: 32 | AF7: 48 | AG7: =AE7+AF7 -> 80 | AH7: =VLOOKUP(AG7,$B$38:$C$46,2) -> A | AI7: 30 | AJ7: 45 | AK7: =AI7+AJ7 -> 75 | AL7: =VLOOKUP(AK7,$B$38:$C$46,2) -> B | AM7: 24 | AN7: 56 | AO7: =AM7+AN7 -> 80 | AP7: =VLOOKUP(AO7,$B$38:$C$46,2) -> A | AR7: =AVERAGE(E7,I7,M7,Q7,U7,Y7,AC7,AG7,AK7,AO7) -> 72.8 | AS7: =RANK(AR7,$AR$5:$AR$27) -> 8 | AT7: A | AU7: A | AV7: B | AW7: B | AX7: B | AY7: Zanele has performed quite well and is a creative and imaginative learner who enjoys expressing ideas through art and storytelling. She excels in practical and expressive subjects. However, she needs to focus on time management in Math and improving the retrieval of information during English comprehension tasks.
A8: 4 | B8: Kandela Elisha | C8: 23 | D8: 24 | E8: =C8+D8 -> 47 | F8: =VLOOKUP(E8,$B$38:$C$46,2) -> E | G8: 31 | H8: 33 | I8: =G8+H8 -> 64 | J8: =VLOOKUP(I8,$B$38:$C$46,2) -> C | K8: 20 | L8: 29 | M8: =K8+L8 -> 49 | N8: =VLOOKUP(M8,$B$38:$C$46,2) -> E | O8: 32 | P8: 40 | Q8: =O8+P8 -> 72 | R8: =VLOOKUP(Q8,$B$38:$C$46,2) -> B | S8: 34 | T8: 56 | U8: =S8+T8 -> 90 | V8: =VLOOKUP(U8,$B$38:$C$46,2) -> A* | W8: 35 | X8: 48 | Y8: =W8+X8 -> 83 | Z8: =VLOOKUP(Y8,$B$38:$C$46,2) -> A | AA8: 28 | AB8: 54 | AC8: =AA8+AB8 -> 82 | AD8: =VLOOKUP(AC8,$B$38:$C$46,2) -> A | AE8: 31 | AF8: 49 | AG8: =AE8+AF8 -> 80 | AH8: =VLOOKUP(AG8,$B$38:$C$46,2) -> A | AI8: 35 | AJ8: 49 | AK8: =AI8+AJ8 -> 84 | AL8: =VLOOKUP(AK8,$B$38:$C$46,2) -> A | AM8: 23 | AN8: 39 | AO8: =AM8+AN8 -> 62 | AP8: =VLOOKUP(AO8,$B$38:$C$46,2) -> C | AR8: =AVERAGE(E8,I8,M8,Q8,U8,Y8,AC8,AG8,AK8,AO8) -> 71.3 | AS8: =RANK(AR8,$AR$5:$AR$27) -> 11 | AT8: C | AU8: A | AV8: C | AW8: B | AX8: B | AY8: Elisha is a polite and cooperative student. Although there has been a slight decline in his English and Science performance this term, he continues to show potential. With regular revision, strengthened foundational skills, and improved organisation during assessments, Elisha can make steady progress.
A9: 5 | B9: Gichinga Anaya | C9: 30 | D9: 34 | E9: =C9+D9 -> 64 | F9: =VLOOKUP(E9,$B$38:$C$46,2) -> C | G9: 33 | H9: 48 | I9: =G9+H9 -> 81 | J9: =VLOOKUP(I9,$B$38:$C$46,2) -> A | K9: 38 | L9: 45 | M9: =K9+L9 -> 83 | N9: =VLOOKUP(M9,$B$38:$C$46,2) -> A | O9: 33 | P9: 51 | Q9: =O9+P9 -> 84 | R9: =VLOOKUP(Q9,$B$38:$C$46,2) -> A | S9: 39 | T9: 56 | U9: =S9+T9 -> 95 | V9: =VLOOKUP(U9,$B$38:$C$46,2) -> A* | W9: 38 | X9: 58 | Y9: =W9+X9 -> 96 | Z9: =VLOOKUP(Y9,$B$38:$C$46,2) -> A* | AA9: 33 | AB9: 58 | AC9: =AA9+AB9 -> 91 | AD9: =VLOOKUP(AC9,$B$38:$C$46,2) -> A* | AE9: 30 | AF9: 50 | AG9: =AE9+AF9 -> 80 | AH9: =VLOOKUP(AG9,$B$38:$C$46,2) -> A | AI9: 31 | AJ9: 50 | AK9: =AI9+AJ9 -> 81 | AL9: =VLOOKUP(AK9,$B$38:$C$46,2) -> A | AM9: 23.5 | AN9: 54 | AO9: =AM9+AN9 -> 77.5 | AP9: =VLOOKUP(AO9,$B$38:$C$46,2) -> B | AR9: =AVERAGE(E9,I9,M9,Q9,U9,Y9,AC9,AG9,AK9,AO9) -> 83.25 | AS9: =RANK(AR9,$AR$5:$AR$27) -> 2 | AT9: B | AU9: A | AV9: B | AW9: B | AX9: B | AY9: Anaya has had an excellent term and has performed very well across all subjects. She is a diligent and motivated learner who approaches tasks with enthusiasm and focus. Her participation in class is consistent, and she collaborates effectively with her peers. Anaya demonstrates a strong understanding of concepts and applies knowledge confidently in both practical and theoretical work.
A10: 6 | B10: Young Jessica | C10: 29 | D10: 30 | E10: =C10+D10 -> 59 | F10: =VLOOKUP(E10,$B$38:$C$46,2) -> D | G10: 13 | H10: 23 | I10: =G10+H10 -> 36 | J10: =VLOOKUP(I10,$B$38:$C$46,2) -> F | K10: 27 | L10: 37 | M10: =K10+L10 -> 64 | N10: =VLOOKUP(M10,$B$38:$C$46,2) -> C | O10: 28 | P10: 40 | Q10: =O10+P10 -> 68 | R10: =VLOOKUP(Q10,$B$38:$C$46,2) -> C | S10: 33 | T10: 52 | U10: =S10+T10 -> 85 | V10: =VLOOKUP(U10,$B$38:$C$46,2) -> A | W10: 35 | X10: 46 | Y10: =W10+X10 -> 81 | Z10: =VLOOKUP(Y10,$B$38:$C$46,2) -> A | AA10: 31 | AB10: 30 | AC10: =AA10+AB10 -> 61 | AD10: =VLOOKUP(AC10,$B$38:$C$46,2) -> C | AE10: 31 | AF10: 47 | AG10: =AE10+AF10 -> 78 | AH10: =VLOOKUP(AG10,$B$38:$C$46,2) -> B | AI10: 30 | AJ10: 46 | AK10: =AI10+AJ10 -> 76 | AL10: =VLOOKUP(AK10,$B$38:$C$46,2) -> B | AM10: 24.8 | AN10: 51 | AO10: =AM10+AN10 -> 75.8 | AP10: =VLOOKUP(AO10,$B$38:$C$46,2) -> B | AR10: =AVERAGE(E10,I10,M10,Q10,U10,Y10,AC10,AG10,AK10,AO10) -> 68.38 | AS10: =RANK(AR10,$AR$5:$AR$27) -> 14 | AT10: B | AU10: A | AV10: B | AW10: B | AX10: B | AY10: Jessica shows steady progress and has the potential to achieve stronger results. She should focus on improving consistency, revising regularly, and seeking clarification whenever concepts are unclear. She is encouraged to work hard in Mathematics, enhance her retrieval of information in English, and develop greater organisation and consistency in her written work.
A11: 7 | B11: Sanoj Sephania | C11: 27 | D11: 31 | E11: =C11+D11 -> 58 | F11: =VLOOKUP(E11,$B$38:$C$46,2) -> D | G11: 35 | H11: 46 | I11: =G11+H11 -> 81 | J11: =VLOOKUP(I11,$B$38:$C$46,2) -> A | K11: 34 | L11: 31 | M11: =K11+L11 -> 65 | N11: =VLOOKUP(M11,$B$38:$C$46,2) -> C | O11: 32 | P11: 38 | Q11: =O11+P11 -> 70 | R11: =VLOOKUP(Q11,$B$38:$C$46,2) -> B | S11: 35 | T11: 47 | U11: =S11+T11 -> 82 | V11: =VLOOKUP(U11,$B$38:$C$46,2) -> A | W11: 36 | X11: 53 | Y11: =W11+X11 -> 89 | Z11: =VLOOKUP(Y11,$B$38:$C$46,2) -> A | AA11: 28 | AB11: 35 | AC11: =AA11+AB11 -> 63 | AD11: =VLOOKUP(AC11,$B$38:$C$46,2) -> C | AE11: 29 | AF11: 46 | AG11: =AE11+AF11 -> 75 | AH11: =VLOOKUP(AG11,$B$38:$C$46,2) -> B | AI11: 24 | AJ11: 38 | AK11: =AI11+AJ11 -> 62 | AL11: =VLOOKUP(AK11,$B$38:$C$46,2) -> C | AM11: 24 | AN11: 49 | AO11: =AM11+AN11 -> 73 | AP11: =VLOOKUP(AO11,$B$38:$C$46,2) -> B | AR11: =AVERAGE(E11,I11,M11,Q11,U11,Y11,AC11,AG11,AK11,AO11) -> 71.8 | AS11: =RANK(AR11,$AR$5:$AR$27) -> 9 | AT11: B | AU11: A | AV11: B | AW11: B | AX11: B | AY11: Sephania has shown notable improvement this term and is beginning to take greater responsibility for her learning. She benefits from individual guidance and should continue studying and challenging herself. Her enthusiastic participation in TEDx LOTS demonstrated growing confidence and a willingness to engage beyond the classroom. With consistent effort and continued support, she is likely to make further progress.
A12: 8 | B12: Sharma Shivik | C12: 24 | D12: 34 | E12: =C12+D12 -> 58 | F12: =VLOOKUP(E12,$B$38:$C$46,2) -> D | G12: 39 | H12: 56 | I12: =G12+H12 -> 95 | J12: =VLOOKUP(I12,$B$38:$C$46,2) -> A* | K12: 38 | L12: 49 | M12: =K12+L12 -> 87 | N12: =VLOOKUP(M12,$B$38:$C$46,2) -> A | O12: 38 | P12: 51 | Q12: =O12+P12 -> 89 | R12: =VLOOKUP(Q12,$B$38:$C$46,2) -> A | S12: 40 | T12: 60 | U12: =S12+T12 -> 100 | V12: =VLOOKUP(U12,$B$38:$C$46,2) -> A* | W12: 35 | X12: 52 | Y12: =W12+X12 -> 87 | Z12: =VLOOKUP(Y12,$B$38:$C$46,2) -> A | AA12: 39 | AB12: 60 | AC12: =AA12+AB12 -> 99 | AD12: =VLOOKUP(AC12,$B$38:$C$46,2) -> A* | AE12: 31 | AF12: 43 | AG12: =AE12+AF12 -> 74 | AH12: =VLOOKUP(AG12,$B$38:$C$46,2) -> B | AI12: 28 | AJ12: 38 | AK12: =AI12+AJ12 -> 66 | AL12: =VLOOKUP(AK12,$B$38:$C$46,2) -> C | AM12: 23 | AN12: 39 | AO12: =AM12+AN12 -> 62 | AP12: =VLOOKUP(AO12,$B$38:$C$46,2) -> C | AR12: =AVERAGE(E12,I12,M12,Q12,U12,Y12,AC12,AG12,AK12,AO12) -> 81.7 | AS12: =RANK(AR12,$AR$5:$AR$27) -> 3 | AT12: C | AU12: A | AV12: B | AW12: B | AX12: B | AY12: Shivik is a new member of the class who has settled in well. He is a self-motivated and disciplined student who consistently strives in his academic work. He has performed well across all subjects, and his engagement in class discussions is commendable. To further strengthen his learning, he should continue challenging himself with advanced reading and extension activities. Additionally, he needs to focus on improving his work layout and the presentation of well-structured work in English.
A13: 9 | B13: Sebaiindira Abdul-Ahad | C13: 25 | D13: 34 | E13: =C13+D13 -> 59 | F13: =VLOOKUP(E13,$B$38:$C$46,2) -> D | G13: 36 | H13: 47 | I13: 83 | J13: =VLOOKUP(I13,$B$38:$C$46,2) -> A | K13: 32 | L13: 40 | M13: =K13+L13 -> 72 | N13: =VLOOKUP(M13,$B$38:$C$46,2) -> B | O13: 28 | P13: 48 | Q13: =O13+P13 -> 76 | R13: =VLOOKUP(Q13,$B$38:$C$46,2) -> B | S13: 28 | T13: 47 | U13: =S13+T13 -> 75 | V13: =VLOOKUP(U13,$B$38:$C$46,2) -> B | W13: 27 | X13: 35 | Y13: =W13+X13 -> 62 | Z13: =VLOOKUP(Y13,$B$38:$C$46,2) -> C | AA13: 23 | AB13: 29 | AC13: =AA13+AB13 -> 52 | AD13: =VLOOKUP(AC13,$B$38:$C$46,2) -> D | AE13: 28 | AF13: 52 | AG13: =AE13+AF13 -> 80 | AH13: =VLOOKUP(AG13,$B$38:$C$46,2) -> A | AI13: 21 | AJ13: 35 | AK13: =AI13+AJ13 -> 56 | AL13: =VLOOKUP(AK13,$B$38:$C$46,2) -> D | AM13: 16 | AN13: 35 | AO13: =AM13+AN13 -> 51 | AP13: =VLOOKUP(AO13,$B$38:$C$46,2) -> D | AR13: =AVERAGE(E13,I13,M13,Q13,U13,Y13,AC13,AG13,AK13,AO13) -> 66.6 | AS13: =RANK(AR13,$AR$5:$AR$27) -> 16 | AT13: B | AU13: A | AV13: C | AW13: B | AX13: B | AY13: Abdul-Ahad has settled in well this term and demonstrates a positive attitude towards learning. He is polite and interacts well with his peers. He has performed fairly well across all subjects achieving good scores.However, in English, he needs to improve in punctuation, accurately retrieving information, and carefully reading questions before attempting them.
A14: 10 | B14: Nebhwani Jay | C14: 20 | D14: 32 | E14: =C14+D14 -> 52 | F14: =VLOOKUP(E14,$B$38:$C$46,2) -> D | G14: 20 | H14: 45 | I14: =G14+H14 -> 65 | J14: =VLOOKUP(I14,$B$38:$C$46,2) -> C | K14: 29 | L14: 32 | M14: =K14+L14 -> 61 | N14: =VLOOKUP(M14,$B$38:$C$46,2) -> C | O14: 31 | P14: 46 | Q14: =O14+P14 -> 77 | R14: =VLOOKUP(Q14,$B$38:$C$46,2) -> B | S14: 37 | T14: 52 | U14: =S14+T14 -> 89 | V14: =VLOOKUP(U14,$B$38:$C$46,2) -> A | W14: 32 | X14: 53 | Y14: =W14+X14 -> 85 | Z14: =VLOOKUP(Y14,$B$38:$C$46,2) -> A | AA14: 24 | AB14: 37 | AC14: =AA14+AB14 -> 61 | AD14: =VLOOKUP(AC14,$B$38:$C$46,2) -> C | AE14: 28 | AF14: 42 | AG14: =AE14+AF14 -> 70 | AH14: =VLOOKUP(AG14,$B$38:$C$46,2) -> B | AI14: 20 | AJ14: 43 | AK14: =AI14+AJ14 -> 63 | AL14: =VLOOKUP(AK14,$B$38:$C$46,2) -> C | AM14: 24.5 | AN14: 40 | AO14: =AM14+AN14 -> 64.5 | AP14: =VLOOKUP(AO14,$B$38:$C$46,2) -> C | AR14: =AVERAGE(E14,I14,M14,Q14,U14,Y14,AC14,AG14,AK14,AO14) -> 68.75 | AS14: =RANK(AR14,$AR$5:$AR$27) -> 13 | AT14: C | AU14: A | AV14: B | AW14: C | AX14: B | AY14: Jay has made steady progress this term and demonstrates a positive attitude towards learning. He participates well in class and interacts positively with his peers. He has performed well in some subjects; however, in English, his results indicate that he needs to focus on consolidating concepts and improving consistency. With continued effort and support, Jay has the potential to make further progress and achieve even stronger results across all subjects.
A15: 11 | B15: Yff Samuel | C15: 22 | D15: 28 | E15: =C15+D15 -> 50 | F15: =VLOOKUP(E15,$B$38:$C$46,2) -> D | G15: 14 | H15: 28 | I15: =G15+H15 -> 42 | J15: =VLOOKUP(I15,$B$38:$C$46,2) -> E | K15: 26 | L15: 29 | M15: =K15+L15 -> 55 | N15: =VLOOKUP(M15,$B$38:$C$46,2) -> D | O15: 18 | P15: 34 | Q15: =O15+P15 -> 52 | R15: =VLOOKUP(Q15,$B$38:$C$46,2) -> D | S15: 22 | T15: 46 | U15: =S15+T15 -> 68 | V15: =VLOOKUP(U15,$B$38:$C$46,2) -> C | W15: 28 | X15: 37 | Y15: =W15+X15 -> 65 | Z15: =VLOOKUP(Y15,$B$38:$C$46,2) -> C | AA15: 15 | AB15: 29 | AC15: =AA15+AB15 -> 44 | AD15: =VLOOKUP(AC15,$B$38:$C$46,2) -> E | AE15: 25 | AF15: 44 | AG15: =AE15+AF15 -> 69 | AH15: =VLOOKUP(AG15,$B$38:$C$46,2) -> C | AI15: 24 | AJ15: 33 | AK15: =AI15+AJ15 -> 57 | AL15: =VLOOKUP(AK15,$B$38:$C$46,2) -> D | AM15: 24.5 | AN15: 49 | AO15: =AM15+AN15 -> 73.5 | AP15: =VLOOKUP(AO15,$B$38:$C$46,2) -> B | AR15: =AVERAGE(E15,I15,M15,Q15,U15,Y15,AC15,AG15,AK15,AO15) -> 57.55 | AS15: =RANK(AR15,$AR$5:$AR$27) -> 17 | AT15: C | AU15: C | AV15: D | AW15: B | AX15: C | AY15: Samuel is a student who demonstrates potential; however, his academic performance requires improvement, particularly across all subjects. In English, he struggles with comprehension and retrieving information. He would benefit greatly from close monitoring, regular revision, and attending support classes.
A16: 12 | B16: Katupisha Mwambuye | C16: 28 | D16: 39 | E16: =C16+D16 -> 67 | F16: =VLOOKUP(E16,$B$38:$C$46,2) -> C | G16: 25 | H16: 40 | I16: =G16+H16 -> 65 | J16: =VLOOKUP(I16,$B$38:$C$46,2) -> C | K16: 29 | L16: 39 | M16: =K16+L16 -> 68 | N16: =VLOOKUP(M16,$B$38:$C$46,2) -> C | O16: 30 | P16: 35 | Q16: =O16+P16 -> 65 | R16: =VLOOKUP(Q16,$B$38:$C$46,2) -> C | S16: 35 | T16: 53 | U16: =S16+T16 -> 88 | V16: =VLOOKUP(U16,$B$38:$C$46,2) -> A | W16: 33 | X16: 52 | Y16: =W16+X16 -> 85 | Z16: =VLOOKUP(Y16,$B$38:$C$46,2) -> A | AA16: 29 | AB16: 38 | AC16: =AA16+AB16 -> 67 | AD16: =VLOOKUP(AC16,$B$38:$C$46,2) -> C | AE16: 23 | AF16: 40 | AG16: =AE16+AF16 -> 63 | AH16: =VLOOKUP(AG16,$B$38:$C$46,2) -> C | AI16: 24 | AJ16: 45 | AK16: =AI16+AJ16 -> 69 | AL16: =VLOOKUP(AK16,$B$38:$C$46,2) -> C | AM16: 31 | AN16: 50 | AO16: =AM16+AN16 -> 81 | AP16: =VLOOKUP(AO16,$B$38:$C$46,2) -> A | AR16: =AVERAGE(E16,I16,M16,Q16,U16,Y16,AC16,AG16,AK16,AO16) -> 71.8 | AS16: =RANK(AR16,$AR$5:$AR$27) -> 9 | AT16: B | AU16: A | AV16: B | AW16: B | AX16: B | AY16: Mwambuye is a polite and respectful member of the class who demonstrates strong commitment to his studies. He has achieved good results and can further improve by refining his organisational skills and consistently reviewing class notes across all subjects.
A17: 13 | B17: Kaonga Walusungu | C17: 24 | D17: 26 | E17: =C17+D17 -> 50 | F17: =VLOOKUP(E17,$B$38:$C$46,2) -> D | G17: 19 | H17: 31 | I17: =G17+H17 -> 50 | J17: =VLOOKUP(I17,$B$38:$C$46,2) -> D | K17: 28 | L17: 39 | M17: =K17+L17 -> 67 | N17: =VLOOKUP(M17,$B$38:$C$46,2) -> C | O17: 36 | P17: 45 | Q17: =O17+P17 -> 81 | R17: =VLOOKUP(Q17,$B$38:$C$46,2) -> A | S17: 35 | T17: 49 | U17: =S17+T17 -> 84 | V17: =VLOOKUP(U17,$B$38:$C$46,2) -> A | W17: 28 | X17: 49 | Y17: =W17+X17 -> 77 | Z17: =VLOOKUP(Y17,$B$38:$C$46,2) -> B | AA17: 22 | AB17: 30 | AC17: =AA17+AB17 -> 52 | AD17: =VLOOKUP(AC17,$B$38:$C$46,2) -> D | AE17: 24 | AF17: 53 | AG17: =AE17+AF17 -> 77 | AH17: =VLOOKUP(AG17,$B$38:$C$46,2) -> B | AI17: 32 | AJ17: 41 | AK17: =AI17+AJ17 -> 73 | AL17: =VLOOKUP(AK17,$B$38:$C$46,2) -> B | AM17: 29.5 | AN17: 50 | AO17: =AM17+AN17 -> 79.5 | AP17: =VLOOKUP(AO17,$B$38:$C$46,2) -> B | AR17: =AVERAGE(E17,I17,M17,Q17,U17,Y17,AC17,AG17,AK17,AO17) -> 69.05 | AS17: =RANK(AR17,$AR$5:$AR$27) -> 12 | AT17: C | AU17: B | AV17: B | AW17: C | AX17: B | AY17: Walusungu is a capable learner who shows clear potential; however, his performance has been inconsistent throughout the term. He performs well when focused but tends to lose track when distracted. Subjects that require regular practice, such as Mathematics and Science, are particularly affected. I recommend that he establish a steady study routine and attend support lessons. With improved consistency, his performance will rise significantly.
A18: 14 | B18: Dube Ryan | C18: 28 | D18: 38 | E18: =C18+D18 -> 66 | F18: =VLOOKUP(E18,$B$38:$C$46,2) -> C | G18: 22 | H18: 37 | I18: =G18+H18 -> 59 | J18: =VLOOKUP(I18,$B$38:$C$46,2) -> D | K18: 36 | L18: 48 | M18: =K18+L18 -> 84 | N18: =VLOOKUP(M18,$B$38:$C$46,2) -> A | O18: 27 | P18: 48 | Q18: =O18+P18 -> 75 | R18: =VLOOKUP(Q18,$B$38:$C$46,2) -> B | S18: 36 | T18: 55 | U18: =S18+T18 -> 91 | V18: =VLOOKUP(U18,$B$38:$C$46,2) -> A* | W18: 39 | X18: 54 | Y18: =W18+X18 -> 93 | Z18: =VLOOKUP(Y18,$B$38:$C$46,2) -> A* | AA18: 37 | AB18: 55 | AC18: =AA18+AB18 -> 92 | AD18: =VLOOKUP(AC18,$B$38:$C$46,2) -> A* | AE18: 26 | AF18: 48 | AG18: =AE18+AF18 -> 74 | AH18: =VLOOKUP(AG18,$B$38:$C$46,2) -> B | AI18: 35 | AJ18: 44 | AK18: =AI18+AJ18 -> 79 | AL18: =VLOOKUP(AK18,$B$38:$C$46,2) -> B | AM18: 22 | AN18: 44 | AO18: =AM18+AN18 -> 66 | AP18: =VLOOKUP(AO18,$B$38:$C$46,2) -> C | AR18: =AVERAGE(E18,I18,M18,Q18,U18,Y18,AC18,AG18,AK18,AO18) -> 77.9 | AS18: =RANK(AR18,$AR$5:$AR$27) -> 5 | AT18: B | AU18: A | AV18: B | AW18: B | AX18: B | AY18: Ryan has shown good progress in several subjects. To improve further, he should focus on improving consistency and strengthening revision techniques for greater accuracy.
A19: 15 | B19: Sinyangwe James | C19: 26 | D19: 30 | E19: =C19+D19 -> 56 | F19: =VLOOKUP(E19,$B$38:$C$46,2) -> D | G19: 22 | H19: 29 | I19: =G19+H19 -> 51 | J19: =VLOOKUP(I19,$B$38:$C$46,2) -> D | K19: 30 | L19: 40 | M19: =K19+L19 -> 70 | N19: =VLOOKUP(M19,$B$38:$C$46,2) -> B | O19: 31 | P19: 37 | Q19: =O19+P19 -> 68 | R19: =VLOOKUP(Q19,$B$38:$C$46,2) -> C | S19: 40 | T19: 52 | U19: =S19+T19 -> 92 | V19: =VLOOKUP(U19,$B$38:$C$46,2) -> A* | W19: 25 | X19: 48 | Y19: =W19+X19 -> 73 | Z19: =VLOOKUP(Y19,$B$38:$C$46,2) -> B | AA19: 21 | AB19: 44 | AC19: =AA19+AB19 -> 65 | AD19: =VLOOKUP(AC19,$B$38:$C$46,2) -> C | AE19: 22 | AF19: 47 | AG19: =AE19+AF19 -> 69 | AH19: =VLOOKUP(AG19,$B$38:$C$46,2) -> C | AI19: 25 | AJ19: 46 | AK19: =AI19+AJ19 -> 71 | AL19: =VLOOKUP(AK19,$B$38:$C$46,2) -> B | AM19: 24.9 | AN19: 42 | AO19: =AM19+AN19 -> 66.9 | AP19: =VLOOKUP(AO19,$B$38:$C$46,2) -> C | AR19: =AVERAGE(E19,I19,M19,Q19,U19,Y19,AC19,AG19,AK19,AO19) -> 68.19 | AS19: =RANK(AR19,$AR$5:$AR$27) -> 15 | AT19: C | AU19: B | AV19: B | AW19: C | AX19: B | AY19: James is a well-behaved and responsible learner who consistently demonstrates a positive attitude. His performance this term has been steady; however, Mathematics and English require additional attention. I recommend regular practice and close monitoring at home. With continued support, James has the potential to excel across all subjects.
A20: 16 | B20: Swima Rabbi | C20: 14 | D20: 22 | E20: =C20+D20 -> 36 | F20: =VLOOKUP(E20,$B$38:$C$46,2) -> F | G20: 23 | H20: 28 | I20: =G20+H20 -> 51 | J20: =VLOOKUP(I20,$B$38:$C$46,2) -> D | K20: 9 | L20: 16 | M20: =K20+L20 -> 25 | N20: =VLOOKUP(M20,$B$38:$C$46,2) -> G | O20: 15 | P20: 19 | Q20: =O20+P20 -> 34 | R20: =VLOOKUP(Q20,$B$38:$C$46,2) -> F | S20: 18 | T20: 26 | U20: =S20+T20 -> 44 | V20: =VLOOKUP(U20,$B$38:$C$46,2) -> E | W20: 15 | X20: 18 | Y20: =W20+X20 -> 33 | Z20: =VLOOKUP(Y20,$B$38:$C$46,2) -> F | AA20: 33 | AB20: 36 | AC20: =AA20+AB20 -> 69 | AD20: =VLOOKUP(AC20,$B$38:$C$46,2) -> C | AE20: 24 | AF20: 43 | AG20: =AE20+AF20 -> 67 | AH20: =VLOOKUP(AG20,$B$38:$C$46,2) -> C | AI20: 23 | AJ20: 33 | AK20: =AI20+AJ20 -> 56 | AL20: =VLOOKUP(AK20,$B$38:$C$46,2) -> D | AM20: 30 | AN20: 54 | AO20: =AM20+AN20 -> 84 | AP20: =VLOOKUP(AO20,$B$38:$C$46,2) -> A | AR20: =AVERAGE(E20,I20,M20,Q20,U20,Y20,AC20,AG20,AK20,AO20) -> 49.9 | AS20: =RANK(AR20,$AR$5:$AR$27) -> 18 | AT20: D | AU20: A | AV20: B | AW20: B | AX20: B | AY20: Rabbi is a polite and cooperative student who has shown some effort this term. However, his academic performance requires improvement, particularly in English. He struggles with comprehension and retrieving of information, and would benefit greatly from close monitoring, regular revision, and attending support classes.
A21: 17 | B21: Chisupa Mwila | C21: 23 | D21: 39 | E21: =C21+D21 -> 62 | F21: =VLOOKUP(E21,$B$38:$C$46,2) -> C | G21: 29 | H21: 41 | I21: =G21+H21 -> 70 | J21: =VLOOKUP(I21,$B$38:$C$46,2) -> B | K21: 35 | L21: 47 | M21: =K21+L21 -> 82 | N21: =VLOOKUP(M21,$B$38:$C$46,2) -> A | O21: 34 | P21: 45 | Q21: =O21+P21 -> 79 | R21: =VLOOKUP(Q21,$B$38:$C$46,2) -> B | S21: 40 | T21: 53 | U21: =S21+T21 -> 93 | V21: =VLOOKUP(U21,$B$38:$C$46,2) -> A* | W21: 35 | X21: 52 | Y21: =W21+X21 -> 87 | Z21: =VLOOKUP(Y21,$B$38:$C$46,2) -> A | AA21: 34 | AB21: 60 | AC21: =AA21+AB21 -> 94 | AD21: =VLOOKUP(AC21,$B$38:$C$46,2) -> A* | AE21: 28 | AF21: 44 | AG21: =AE21+AF21 -> 72 | AH21: =VLOOKUP(AG21,$B$38:$C$46,2) -> B | AI21: 31 | AJ21: 39 | AK21: =AI21+AJ21 -> 70 | AL21: =VLOOKUP(AK21,$B$38:$C$46,2) -> B | AM21: 23.7 | AN21: 38 | AO21: =AM21+AN21 -> 61.7 | AP21: =VLOOKUP(AO21,$B$38:$C$46,2) -> C | AR21: =AVERAGE(E21,I21,M21,Q21,U21,Y21,AC21,AG21,AK21,AO21) -> 77.07 | AS21: =RANK(AR21,$AR$5:$AR$27) -> 6 | AT21: B | AU21: A | AV21: B | AW21: A | AX21: B | AY21: Mwila is a quiet and respectful student who approaches all tasks with dedication. She has performed well across most subjects and displays strong organizational skills. However, she needs to build confidence during class discussions. I encourage her to participate more actively so she can fully benefit from collaborative learning. Continued support at home will help strengthen her confidence.
A22: 18 | B22: Sakala Ethan | C22: 25 | D22: 41 | E22: =C22+D22 -> 66 | F22: =VLOOKUP(E22,$B$38:$C$46,2) -> C | G22: 34 | H22: 52 | I22: =G22+H22 -> 86 | J22: =VLOOKUP(I22,$B$38:$C$46,2) -> A | K22: 35 | L22: 52 | M22: =K22+L22 -> 87 | N22: =VLOOKUP(M22,$B$38:$C$46,2) -> A | O22: 31 | P22: 52 | Q22: =O22+P22 -> 83 | R22: =VLOOKUP(Q22,$B$38:$C$46,2) -> A | S22: 37 | T22: 59 | U22: =S22+T22 -> 96 | V22: =VLOOKUP(U22,$B$38:$C$46,2) -> A* | W22: 38 | X22: 50 | Y22: =W22+X22 -> 88 | Z22: =VLOOKUP(Y22,$B$38:$C$46,2) -> A | AA22: 39 | AB22: 59 | AC22: =AA22+AB22 -> 98 | AD22: =VLOOKUP(AC22,$B$38:$C$46,2) -> A* | AE22: 29 | AF22: 45 | AG22: =AE22+AF22 -> 74 | AH22: =VLOOKUP(AG22,$B$38:$C$46,2) -> B | AI22: 40 | AJ22: 53 | AK22: =AI22+AJ22 -> 93 | AL22: =VLOOKUP(AK22,$B$38:$C$46,2) -> A* | AM22: 26.8 | AN22: 52 | AO22: =AM22+AN22 -> 78.8 | AP22: =VLOOKUP(AO22,$B$38:$C$46,2) -> B | AR22: =AVERAGE(E22,I22,M22,Q22,U22,Y22,AC22,AG22,AK22,AO22) -> 84.98 | AS22: =RANK(AR22,$AR$5:$AR$27) -> 1 | AT22: B | AU22: A | AV22: B | AW22: A | AX22: B | AY22: Ethan is a highly motivated and disciplined student who consistently strives to excel in his academic work. He has performed well in all subjects, and his engagement in class discussions is commendable. To further extend his potential, Ethan should continue exploring enrichment opportunities and focus on developing higher-level critical thinking skills.
A26: 22 | AJ26: 35
A27: 23
B30: Average | E30: =AVERAGE(E5:E22) -> 57.5 | I30: =AVERAGE(I5:I22) -> 64.833333 | M30: =AVERAGE(M5:M22) -> 69.555556 | Q30: =AVERAGE(Q5:Q22) -> 71.944444 | U30: =AVERAGE(U5:U22) -> 86 | Y30: =AVERAGE(Y5:Y22) -> 78.722222 | AC30: =AVERAGE(AC5:AC22) -> 73.055556 | AG30: =AVERAGE(AG5:AG22) -> 74.666667 | AK30: =AVERAGE(AK5:AK22) -> 71.666667 | AO30: =AVERAGE(AO5:AO22) -> 71.527778
B31: NO. Students | E31: =COUNT(E5:E22) -> 18 | I31: =COUNT(I5:I22) -> 18 | M31: =COUNT(M5:M22) -> 18 | Q31: =COUNT(Q5:Q22) -> 18 | U31: =COUNT(U5:U22) -> 18 | Y31: =COUNT(Y5:Y22) -> 18 | AC31: =COUNT(AC5:AC22) -> 18 | AG31: =COUNT(AG5:AG22) -> 18 | AK31: =COUNT(AK5:AK22) -> 18 | AO31: =COUNT(AO5:AO22) -> 18
B32: Pass | E32: =COUNTIF(E5:E22,">49") -> 16 | I32: =COUNTIF(I5:I22,">49") -> 16 | M32: =COUNTIF(M5:M22,">49") -> 16 | Q32: =COUNTIF(Q5:Q22,">49") -> 17 | U32: =COUNTIF(U5:U22,">49") -> 17 | Y32: =COUNTIF(Y5:Y22,">49") -> 17 | AC32: =COUNTIF(AC5:AC22,">49") -> 17 | AG32: =COUNTIF(AG5:AG22,">49") -> 18 | AK32: =COUNTIF(AK5:AK22,">49") -> 18 | AO32: =COUNTIF(AO5:AO22,">49") -> 18
B33: Fail | E33: =COUNTIF(E5:E22,"<50") -> 2 | I33: =COUNTIF(I5:I22,"<50") -> 2 | M33: =COUNTIF(M5:M22,"<50") -> 2 | Q33: =COUNTIF(Q5:Q22,"<50") -> 1 | U33: =COUNTIF(U5:U22,"<50") -> 1 | Y33: =COUNTIF(Y5:Y22,"<50") -> 1 | AC33: =COUNTIF(AC5:AC22,"<50") -> 1 | AG33: =COUNTIF(AG5:AG22,"<50") -> 0 | AK33: =COUNTIF(AK5:AK22,"<50") -> 0 | AO33: =COUNTIF(AO5:AO22,"<50") -> 0
B34: Pass Rate % | E34: =E32*100/E31 -> 88.888889 | I34: =I32*100/I31 -> 88.888889 | M34: =M32*100/M31 -> 88.888889 | Q34: =Q32*100/Q31 -> 94.444444 | U34: =U32*100/U31 -> 94.444444 | Y34: =Y32*100/Y31 -> 94.444444 | AC34: =AC32*100/AC31 -> 94.444444 | AG34: =AG32*100/AG31 -> 100 | AK34: =AK32*100/AK31 -> 100 | AO34: =AO32*100/AO31 -> 100
A38: 00-19 | B38: 0 | C38: U
A39: 20-29 | B39: 20 | C39: G
A40: 30-39 | B40: 30 | C40: F
A41: 40-49 | B41: 40 | C41: E
A42: 50-59 | B42: 50 | C42: D
A43: 60-69 | B43: 60 | C43: C
A44: 70-79 | B44: 70 | C44: B
A45: 80-89 | B45: 80 | C45: A
A46: 90-100 | B46: 90 | C46: A*

Sheet LS3A
A3: Roll N0. | B3: Name | C3: English | G3: Mathematics | K3: Science | O3: Global Pesperctive | S3: New Computing | W3: Business Studies | AA3: French | AE3: Art | AI3: MDD | AM3: PE | AR3: AVERAGE | AS3: POSITION | AT3: CREATIVITY | AU3: RESPECT | AV3: EXCELLENCE | AW3: EMPATHY | AX3: DISCPLINE | AY3: CLASS TEACHER'S COMMENT
C4: Formative | D4: Summative | E4: Final Mark | F4: Grade | G4: Formative | H4: Summative | I4: Final Mark | J4: Grade | K4: Formative | L4: Summative | M4: Final Mark | N4: Grade | O4: Formative | P4: Summative | Q4: Final Mark | R4: Grade | S4: Formative | T4: Summative | U4: Final Mark | V4: Grade | W4: Formative | X4: Summative | Y4: Final Mark | Z4: Grade | AA4: Formative | AB4: Summative | AC4: Final Mark | AD4: Grade | AE4: Formative | AF4: Summative | AG4: Final Mark | AH4: Grade | AI4: Formative | AJ4: Summative | AK4: Final Mark | AL4: Grade | AM4: Formative | AN4: Summative | AO4: Final Mark | AP4: Grade
A5: 1 | B5: Lemba Yahya | C5: 19 | D5: 22 | E5: =C5+D5 -> 41 | F5: =VLOOKUP(E5,$B$39:$C$47,2) -> E | G5: 24 | H5: 35 | I5: =G5+H5 -> 59 | J5: =VLOOKUP(I5,$B$39:$C$47,2) -> D | K5: 25 | L5: 39 | M5: =K5+L5 -> 64 | N5: =VLOOKUP(M5,$B$39:$C$47,2) -> C | O5: 31 | P5: 47 | Q5: =O5+P5 -> 78 | R5: =VLOOKUP(Q5,$B$39:$C$47,2) -> B | S5: 27 | T5: 41 | U5: =S5+T5 -> 68 | V5: =VLOOKUP(U5,$B$39:$C$47,2) -> C | W5: 27 | X5: 45 | Y5: =W5+X5 -> 72 | Z5: =VLOOKUP(Y5,$B$39:$C$47,2) -> B | AA5: 22 | AB5: 24 | AC5: =AA5+AB5 -> 46 | AD5: =VLOOKUP(AC5,$B$39:$C$47,2) -> E | AE5: 29 | AF5: 49 | AG5: =AE5+AF5 -> 78 | AH5: =VLOOKUP(AG5,$B$39:$C$47,2) -> B | AI5: 33 | AJ5: 42 | AK5: =AI5+AJ5 -> 75 | AL5: =VLOOKUP(AK5,$B$39:$C$47,2) -> B | AM5: 20 | AN5: 43 | AO5: =AM5+AN5 -> 63 | AP5: =VLOOKUP(AO5,$B$39:$C$47,2) -> C | AR5: =AVERAGE(E5,I5,M5,Q5,U5,Y5,AC5,AG5,AK5,AO5) -> 64.4 | AS5: =RANK(AR5,$AR$5:$AR$27) -> 10 | AT5: C | AU5: B | AV5: C | AW5: C | AX5: C | AY5: Yahya shows a strong understanding of the material and participates confidently. However Mathematics requires additional attention. With continued support Yahya has the potential to excel across all subjects and taking on further challenges will help him advance even more.
A6: 2 | B6: Milestead Tiago | C6: 18 | D6: 31 | E6: =C6+D6 -> 49 | F6: =VLOOKUP(E6,$B$39:$C$47,2) -> E | G6: 10 | H6: 35 | I6: =G6+H6 -> 45 | J6: =VLOOKUP(I6,$B$39:$C$47,2) -> E | K6: 29 | L6: 30 | M6: =K6+L6 -> 59 | N6: =VLOOKUP(M6,$B$39:$C$47,2) -> D | P6: 32 | Q6: =O6+P6 -> 32 | R6: =VLOOKUP(Q6,$B$39:$C$47,2) -> F | S6: 29 | T6: 47 | U6: =S6+T6 -> 76 | V6: =VLOOKUP(U6,$B$39:$C$47,2) -> B | W6: 18 | X6: 39 | Y6: =W6+X6 -> 57 | Z6: =VLOOKUP(Y6,$B$39:$C$47,2) -> D | AA6: 35 | AB6: 31 | AC6: =AA6+AB6 -> 66 | AD6: =VLOOKUP(AC6,$B$39:$C$47,2) -> C | AE6: 29 | AF6: 28 | AG6: =AE6+AF6 -> 57 | AH6: =VLOOKUP(AG6,$B$39:$C$47,2) -> D | AI6: 33 | AJ6: 47 | AK6: =AI6+AJ6 -> 80 | AL6: =VLOOKUP(AK6,$B$39:$C$47,2) -> A | AM6: 0 | AN6: 39 | AO6: =AM6+AN6 -> 39 | AP6: =VLOOKUP(AO6,$B$39:$C$47,2) -> F | AR6: =AVERAGE(E6,I6,M6,Q6,U6,Y6,AC6,AG6,AK6,AO6) -> 56 | AS6: =RANK(AR6,$AR$5:$AR$27) -> 20 | AT6: C | AU6: D | AV6: D | AW6: E | AX6: D | AY6: Tiago, is a capable learner who shows potential, however he should work on maintaining personal space and respecting boundaries to help create a positive classroom atmosphere. Subjects requiring consistent practice such as English, mathematics and science, I recommend establishing steady study routine and attend support lessons.
A7: 3 | B7: Rezk Macarius | C7: 20 | D7: 27 | E7: =C7+D7 -> 47 | F7: =VLOOKUP(E7,$B$39:$C$47,2) -> E | G7: 26 | H7: 33 | I7: =G7+H7 -> 59 | J7: =VLOOKUP(I7,$B$39:$C$47,2) -> D | K7: 27 | L7: 34 | M7: =K7+L7 -> 61 | N7: =VLOOKUP(M7,$B$39:$C$47,2) -> C | O7: 24 | P7: 36 | Q7: =O7+P7 -> 60 | R7: =VLOOKUP(Q7,$B$39:$C$47,2) -> C | S7: 33 | T7: 35 | U7: =S7+T7 -> 68 | V7: =VLOOKUP(U7,$B$39:$C$47,2) -> C | W7: 20 | X7: 43 | Y7: =W7+X7 -> 63 | Z7: =VLOOKUP(Y7,$B$39:$C$47,2) -> C | AA7: 26 | AB7: 30 | AC7: =AA7+AB7 -> 56 | AD7: =VLOOKUP(AC7,$B$39:$C$47,2) -> D | AE7: 26 | AF7: 36 | AG7: =AE7+AF7 -> 62 | AH7: =VLOOKUP(AG7,$B$39:$C$47,2) -> C | AI7: 30 | AJ7: 36 | AK7: =AI7+AJ7 -> 66 | AL7: =VLOOKUP(AK7,$B$39:$C$47,2) -> C | AM7: 28 | AN7: 40 | AO7: =AM7+AN7 -> 68 | AP7: =VLOOKUP(AO7,$B$39:$C$47,2) -> C | AR7: =AVERAGE(E7,I7,M7,Q7,U7,Y7,AC7,AG7,AK7,AO7) -> 61 | AS7: =RANK(AR7,$AR$5:$AR$27) -> 14 | AT7: C | AU7: D | AV7: D | AW7: D | AX7: D | AY7: Macarius, has strong potential that has yet to be fully realized, he is energetic and friendly learner who enjoys interacting with peers. With encouragement to challenge himself, he can make significant progress.
A8: 4 | B8: Kashoka Susanna | C8: 18 | D8: 39 | E8: =C8+D8 -> 57 | F8: =VLOOKUP(E8,$B$39:$C$47,2) -> D | G8: 18 | H8: 40 | I8: =G8+H8 -> 58 | J8: =VLOOKUP(I8,$B$39:$C$47,2) -> D | K8: 29.5 | L8: 32 | M8: =K8+L8 -> 61.5 | N8: =VLOOKUP(M8,$B$39:$C$47,2) -> C | O8: 30 | P8: 41 | Q8: =O8+P8 -> 71 | R8: =VLOOKUP(Q8,$B$39:$C$47,2) -> B | S8: 26 | T8: 47 | U8: =S8+T8 -> 73 | V8: =VLOOKUP(U8,$B$39:$C$47,2) -> B | W8: 35 | X8: 50 | Y8: =W8+X8 -> 85 | Z8: =VLOOKUP(Y8,$B$39:$C$47,2) -> A | AA8: 32 | AB8: 42 | AC8: =AA8+AB8 -> 74 | AD8: =VLOOKUP(AC8,$B$39:$C$47,2) -> B | AE8: 29 | AF8: 39 | AG8: =AE8+AF8 -> 68 | AH8: =VLOOKUP(AG8,$B$39:$C$47,2) -> C | AI8: 33 | AJ8: 48 | AK8: =AI8+AJ8 -> 81 | AL8: =VLOOKUP(AK8,$B$39:$C$47,2) -> A | AM8: 24 | AN8: 41 | AO8: =AM8+AN8 -> 65 | AP8: =VLOOKUP(AO8,$B$39:$C$47,2) -> C | AR8: =AVERAGE(E8,I8,M8,Q8,U8,Y8,AC8,AG8,AK8,AO8) -> 69.35 | AS8: =RANK(AR8,$AR$5:$AR$27) -> 5 | AT8: C | AU8: B | AV8: C | AW8: C | AX8: D | AY8: Susanna is very sociable and friendly. To improve her learning, she should focus more consistently on staying on task during lessons especially in Mathematics.
A9: 5 | B9: Yadav Pallavi | C9: 24 | D9: 38 | E9: =C9+D9 -> 62 | F9: =VLOOKUP(E9,$B$39:$C$47,2) -> C | G9: 32 | H9: 42 | I9: =G9+H9 -> 74 | J9: =VLOOKUP(I9,$B$39:$C$47,2) -> B | K9: 31 | L9: 43 | M9: =K9+L9 -> 74 | N9: =VLOOKUP(M9,$B$39:$C$47,2) -> B | O9: 35 | P9: 31.5 | Q9: =O9+P9 -> 66.5 | R9: =VLOOKUP(Q9,$B$39:$C$47,2) -> C | S9: 26 | T9: 51 | U9: =S9+T9 -> 77 | V9: =VLOOKUP(U9,$B$39:$C$47,2) -> B | W9: 38 | X9: 47 | Y9: =W9+X9 -> 85 | Z9: =VLOOKUP(Y9,$B$39:$C$47,2) -> A | AA9: 38 | AB9: 51 | AC9: =AA9+AB9 -> 89 | AD9: =VLOOKUP(AC9,$B$39:$C$47,2) -> A | AE9: 34 | AF9: 52 | AG9: =AE9+AF9 -> 86 | AH9: =VLOOKUP(AG9,$B$39:$C$47,2) -> A | AI9: 35 | AJ9: 53 | AK9: =AI9+AJ9 -> 88 | AL9: =VLOOKUP(AK9,$B$39:$C$47,2) -> A | AM9: 24 | AN9: 40 | AO9: =AM9+AN9 -> 64 | AP9: =VLOOKUP(AO9,$B$39:$C$47,2) -> C | AR9: =AVERAGE(E9,I9,M9,Q9,U9,Y9,AC9,AG9,AK9,AO9) -> 76.55 | AS9: =RANK(AR9,$AR$5:$AR$27) -> 3 | AT9: B | AU9: B | AV9: C | AW9: C | AX9: C | AY9: Pallavi, has settled well into school and has also shown notable progress this term, further she is also a capable learner who would benefit from building her confidence and developing strategies to overcome challenges.
A10: 6 | B10: Nair Aadhya | C10: 31 | D10: 42 | E10: =C10+D10 -> 73 | F10: =VLOOKUP(E10,$B$39:$C$47,2) -> B | G10: 34 | H10: 40 | I10: =G10+H10 -> 74 | J10: =VLOOKUP(I10,$B$39:$C$47,2) -> B | K10: 29.5 | L10: 38.4 | M10: =K10+L10 -> 67.9 | N10: =VLOOKUP(M10,$B$39:$C$47,2) -> C | O10: 35 | P10: 31.5 | Q10: =O10+P10 -> 66.5 | R10: =VLOOKUP(Q10,$B$39:$C$47,2) -> C | S10: 32 | T10: 53 | U10: =S10+T10 -> 85 | V10: =VLOOKUP(U10,$B$39:$C$47,2) -> A | W10: 35 | X10: 46 | Y10: =W10+X10 -> 81 | Z10: =VLOOKUP(Y10,$B$39:$C$47,2) -> A | AA10: 38 | AB10: 57 | AC10: =AA10+AB10 -> 95 | AD10: =VLOOKUP(AC10,$B$39:$C$47,2) -> A* | AE10: 37 | AF10: 56 | AG10: =AE10+AF10 -> 93 | AH10: =VLOOKUP(AG10,$B$39:$C$47,2) -> A* | AI10: 38 | AJ10: 54 | AK10: =AI10+AJ10 -> 92 | AL10: =VLOOKUP(AK10,$B$39:$C$47,2) -> A* | AM10: 20 | AN10: 41 | AO10: =AM10+AN10 -> 61 | AP10: =VLOOKUP(AO10,$B$39:$C$47,2) -> C | AR10: =AVERAGE(E10,I10,M10,Q10,U10,Y10,AC10,AG10,AK10,AO10) -> 78.84 | AS10: =RANK(AR10,$AR$5:$AR$27) -> 1 | AT10: A | AU10: A | AV10: B | AW10: B | AX10: B | AY10: Aadhya, is a cooperative team player who readily collaborates and helps her classmates. She performs well in practical and expressive subjects. I recommend structured revision, practice exercises and closer follow up at home.
A11: 7 | B11: Niu Yitong | C11: 7 | D11: 37 | E11: =C11+D11 -> 44 | F11: =VLOOKUP(E11,$B$39:$C$47,2) -> E | G11: 35 | H11: 57 | I11: =G11+H11 -> 92 | J11: =VLOOKUP(I11,$B$39:$C$47,2) -> A* | K11: 0 | L11: 35 | M11: =K11+L11 -> 35 | N11: =VLOOKUP(M11,$B$39:$C$47,2) -> F | O11: 18 | P11: 32 | Q11: =O11+P11 -> 50 | R11: =VLOOKUP(Q11,$B$39:$C$47,2) -> D | S11: 11 | T11: 39 | U11: =S11+T11 -> 50 | V11: =VLOOKUP(U11,$B$39:$C$47,2) -> D | W11: 19 | X11: 26 | Y11: =W11+X11 -> 45 | Z11: =VLOOKUP(Y11,$B$39:$C$47,2) -> E | AA11: 22 | AB11: 42 | AC11: 42 | AD11: =VLOOKUP(AC11,$B$39:$C$47,2) -> E | AE11: 25 | AF11: 44 | AG11: =AE11+AF11 -> 69 | AH11: =VLOOKUP(AG11,$B$39:$C$47,2) -> C | AI11: 37 | AJ11: 53 | AK11: =AI11+AJ11 -> 90 | AL11: =VLOOKUP(AK11,$B$39:$C$47,2) -> A* | AM11: 0 | AN11: 39 | AO11: =AM11+AN11 -> 39 | AP11: =VLOOKUP(AO11,$B$39:$C$47,2) -> F | AR11: =AVERAGE(E11,I11,M11,Q11,U11,Y11,AC11,AG11,AK11,AO11) -> 55.6 | AS11: =RANK(AR11,$AR$5:$AR$27) -> 21 | AT11: C | AU11: C | AV11: C | AW11: D | AX11: D | AY11: Yitong is bright and capable but tends to hold back due to lack of effort. Encouraging consistent motivation will help him excel in sciences. I recommend consistent practice, attending targeted support lessons and parental reinforcement at home. With balanced efforts, he can improve significantly.
A12: 8 | B12: Nsenje Joanna | C12: 18 | D12: 38 | E12: =C12+D12 -> 56 | F12: =VLOOKUP(E12,$B$39:$C$47,2) -> D | G12: 16 | H12: 21 | I12: =G12+H12 -> 37 | J12: =VLOOKUP(I12,$B$39:$C$47,2) -> F | K12: 27 | L12: 22 | M12: =K12+L12 -> 49 | N12: =VLOOKUP(M12,$B$39:$C$47,2) -> E | O12: 29 | P12: 31 | Q12: =O12+P12 -> 60 | R12: =VLOOKUP(Q12,$B$39:$C$47,2) -> C | S12: 19 | T12: 13 | U12: =S12+T12 -> 32 | V12: =VLOOKUP(U12,$B$39:$C$47,2) -> F | W12: 19 | X12: 32 | Y12: =W12+X12 -> 51 | Z12: =VLOOKUP(Y12,$B$39:$C$47,2) -> D | AA12: 26 | AB12: 49 | AC12: =AA12+AB12 -> 75 | AD12: =VLOOKUP(AC12,$B$39:$C$47,2) -> B | AE12: 27 | AF12: 43 | AG12: =AE12+AF12 -> 70 | AH12: =VLOOKUP(AG12,$B$39:$C$47,2) -> B | AI12: 31 | AJ12: 45 | AK12: =AI12+AJ12 -> 76 | AL12: =VLOOKUP(AK12,$B$39:$C$47,2) -> B | AM12: 24 | AN12: 42 | AO12: =AM12+AN12 -> 66 | AP12: =VLOOKUP(AO12,$B$39:$C$47,2) -> C | AR12: =AVERAGE(E12,I12,M12,Q12,U12,Y12,AC12,AG12,AK12,AO12) -> 57.2 | AS12: =RANK(AR12,$AR$5:$AR$27) -> 19 | AT12: C | AU12: C | AV12: C | AW12: C | AX12: D | AY12: Joanna is enthusiastic about outdoor activities, but she is encouraged to give more attention to her school tasks and remain engaged in lessons. Subjects like English and Mathematics requires improvement, I recommend structured revision, limited distractions at home and regular teacher-parent follow-ups.
A13: 9 | B13: Dejohn Lucas | C13: 15 | D13: 35 | E13: =C13+D13 -> 50 | F13: =VLOOKUP(E13,$B$39:$C$47,2) -> D | G13: 25 | H13: 29 | I13: =G13+H13 -> 54 | J13: =VLOOKUP(I13,$B$39:$C$47,2) -> D | K13: 23 | L13: 31 | M13: =K13+L13 -> 54 | N13: =VLOOKUP(M13,$B$39:$C$47,2) -> D | O13: 24 | P13: 41 | Q13: =O13+P13 -> 65 | R13: =VLOOKUP(Q13,$B$39:$C$47,2) -> C | S13: 22 | T13: 46 | U13: =S13+T13 -> 68 | V13: =VLOOKUP(U13,$B$39:$C$47,2) -> C | W13: 31 | X13: 46 | Y13: =W13+X13 -> 77 | Z13: =VLOOKUP(Y13,$B$39:$C$47,2) -> B | AA13: 32 | AB13: 33 | AC13: =AA13+AB13 -> 65 | AD13: =VLOOKUP(AC13,$B$39:$C$47,2) -> C | AE13: 24 | AF13: 39 | AG13: =AE13+AF13 -> 63 | AH13: =VLOOKUP(AG13,$B$39:$C$47,2) -> C | AI13: 32 | AJ13: 42 | AK13: =AI13+AJ13 -> 74 | AL13: =VLOOKUP(AK13,$B$39:$C$47,2) -> B | AM13: 24 | AN13: 43 | AO13: =AM13+AN13 -> 67 | AP13: =VLOOKUP(AO13,$B$39:$C$47,2) -> C | AR13: =AVERAGE(E13,I13,M13,Q13,U13,Y13,AC13,AG13,AK13,AO13) -> 63.7 | AS13: =RANK(AR13,$AR$5:$AR$27) -> 11 | AT13: C | AU13: C | AV13: C | AW13: D | AX13: D | AY13: Lucas, has a good understanding of the subject and participates actively. However his academic performance requires improvement particularly in Mathematics, PE and Science. Taking on more challenging tasks will help him continue to grow academically.
A14: 10 | B14: Naniso Dannelle Dauramanzi | C14: 21 | D14: 40 | E14: =C14+D14 -> 61 | F14: =VLOOKUP(E14,$B$39:$C$47,2) -> C | G14: 7 | H14: 35 | I14: =G14+H14 -> 42 | J14: =VLOOKUP(I14,$B$39:$C$47,2) -> E | K14: 30 | L14: 34 | M14: =K14+L14 -> 64 | N14: =VLOOKUP(M14,$B$39:$C$47,2) -> C | O14: 31 | P14: 44 | Q14: =O14+P14 -> 75 | R14: =VLOOKUP(Q14,$B$39:$C$47,2) -> B | S14: 25 | T14: 32 | U14: =S14+T14 -> 57 | V14: =VLOOKUP(U14,$B$39:$C$47,2) -> D | W14: 26 | X14: 44 | Y14: =W14+X14 -> 70 | Z14: =VLOOKUP(Y14,$B$39:$C$47,2) -> B | AA14: 21 | AB14: 44 | AC14: =AA14+AB14 -> 65 | AD14: =VLOOKUP(AC14,$B$39:$C$47,2) -> C | AE14: 16 | AF14: 46 | AG14: =AE14+AF14 -> 62 | AH14: =VLOOKUP(AG14,$B$39:$C$47,2) -> C | AI14: 34 | AJ14: 45 | AK14: =AI14+AJ14 -> 79 | AL14: =VLOOKUP(AK14,$B$39:$C$47,2) -> B | AM14: 20 | AN14: 41 | AO14: =AM14+AN14 -> 61 | AP14: =VLOOKUP(AO14,$B$39:$C$47,2) -> C | AR14: =AVERAGE(E14,I14,M14,Q14,U14,Y14,AC14,AG14,AK14,AO14) -> 63.6 | AS14: =RANK(AR14,$AR$5:$AR$27) -> 12 | AT14: B | AU14: A | AV14: B | AW14: B | AX14: B | AY14: Naniso, has settled very well into school. She consistently displays excellent manners and is a pleasure to teach. However her academic performance requires improvement particularly in Mathematics. I encourage strong cooperation between home and school to help Naniso progress.
A15: 11 | B15: Simango Natasha | C15: 22 | D15: 33 | E15: =C15+D15 -> 55 | F15: =VLOOKUP(E15,$B$39:$C$47,2) -> D | G15: 11 | H15: 19 | I15: =G15+H15 -> 30 | J15: =VLOOKUP(I15,$B$39:$C$47,2) -> F | K15: 29 | L15: 26 | M15: =K15+L15 -> 55 | N15: =VLOOKUP(M15,$B$39:$C$47,2) -> D | O15: 28 | P15: 29 | Q15: =O15+P15 -> 57 | R15: =VLOOKUP(Q15,$B$39:$C$47,2) -> D | S15: 29 | T15: 25 | U15: =S15+T15 -> 54 | V15: =VLOOKUP(U15,$B$39:$C$47,2) -> D | W15: 27 | X15: 41 | Y15: =W15+X15 -> 68 | Z15: =VLOOKUP(Y15,$B$39:$C$47,2) -> C | AA15: 31 | AB15: 47 | AC15: =AA15+AB15 -> 78 | AD15: =VLOOKUP(AC15,$B$39:$C$47,2) -> B | AE15: 31 | AF15: 40 | AG15: =AE15+AF15 -> 71 | AH15: =VLOOKUP(AG15,$B$39:$C$47,2) -> B | AI15: 31 | AJ15: 43 | AK15: =AI15+AJ15 -> 74 | AL15: =VLOOKUP(AK15,$B$39:$C$47,2) -> B | AM15: 16 | AN15: 41 | AO15: =AM15+AN15 -> 57 | AP15: =VLOOKUP(AO15,$B$39:$C$47,2) -> D | AR15: =AVERAGE(E15,I15,M15,Q15,U15,Y15,AC15,AG15,AK15,AO15) -> 59.9 | AS15: =RANK(AR15,$AR$5:$AR$27) -> 15 | AT15: C | AU15: C | AV15: D | AW15: C | AX15: D | AY15: Natasha, has settled well in class, however, she can be overly talkative at times, which may distract herself and others. She needs to put more effort into her academic work particularly in Mathematics and science. Developing active listening will support her progress.
A16: 12 | B16: Chowdhary Trishna | C16: 36 | D16: 48 | E16: =C16+D16 -> 84 | F16: =VLOOKUP(E16,$B$39:$C$47,2) -> A | G16: 21 | H16: 44 | I16: =G16+H16 -> 65 | J16: =VLOOKUP(I16,$B$39:$C$47,2) -> C | K16: 17 | L16: 52 | M16: =K16+L16 -> 69 | N16: =VLOOKUP(M16,$B$39:$C$47,2) -> C | O16: 31 | P16: 40 | Q16: =O16+P16 -> 71 | R16: =VLOOKUP(Q16,$B$39:$C$47,2) -> B | S16: 31 | T16: 46 | U16: =S16+T16 -> 77 | V16: =VLOOKUP(U16,$B$39:$C$47,2) -> B | W16: 36 | X16: 57 | Y16: =W16+X16 -> 93 | Z16: =VLOOKUP(Y16,$B$39:$C$47,2) -> A* | AA16: 32 | AB16: 41 | AC16: =AA16+AB16 -> 73 | AD16: =VLOOKUP(AC16,$B$39:$C$47,2) -> B | AE16: 36 | AF16: 59 | AG16: =AE16+AF16 -> 95 | AH16: =VLOOKUP(AG16,$B$39:$C$47,2) -> A* | AI16: 36 | AJ16: 51 | AK16: =AI16+AJ16 -> 87 | AL16: =VLOOKUP(AK16,$B$39:$C$47,2) -> A | AM16: 20 | AN16: 42 | AO16: =AM16+AN16 -> 62 | AP16: =VLOOKUP(AO16,$B$39:$C$47,2) -> C | AR16: =AVERAGE(E16,I16,M16,Q16,U16,Y16,AC16,AG16,AK16,AO16) -> 77.6 | AS16: =RANK(AR16,$AR$5:$AR$27) -> 2 | AT16: B | AU16: B | AV16: C | AW16: B | AX16: C | AY16: Trishna, has adapted well to the class environment. She is a quiet student, considerate and always willing to support others.She has performed well in most of the subjects. However she should be active in PE, I encourage her to participate more actively so she can fully benefit from collaborative learning.
A17: 13 | B17: Malan Chellah | C17: 21 | D17: 32 | E17: =C17+D17 -> 53 | F17: =VLOOKUP(E17,$B$39:$C$47,2) -> D | G17: 28 | H17: 31 | I17: =G17+H17 -> 59 | J17: =VLOOKUP(I17,$B$39:$C$47,2) -> D | K17: 29 | L17: 27 | M17: =K17+L17 -> 56 | N17: =VLOOKUP(M17,$B$39:$C$47,2) -> D | O17: 30 | P17: 42 | Q17: =O17+P17 -> 72 | R17: =VLOOKUP(Q17,$B$39:$C$47,2) -> B | S17: 31 | T17: 40 | U17: =S17+T17 -> 71 | V17: =VLOOKUP(U17,$B$39:$C$47,2) -> B | W17: 22 | X17: 41 | Y17: =W17+X17 -> 63 | Z17: =VLOOKUP(Y17,$B$39:$C$47,2) -> C | AA17: 33 | AB17: 50 | AC17: =AA17+AB17 -> 83 | AD17: =VLOOKUP(AC17,$B$39:$C$47,2) -> A | AE17: 33 | AF17: 46 | AG17: =AE17+AF17 -> 79 | AH17: =VLOOKUP(AG17,$B$39:$C$47,2) -> B | AI17: 32 | AJ17: 53 | AK17: =AI17+AJ17 -> 85 | AL17: =VLOOKUP(AK17,$B$39:$C$47,2) -> A | AM17: 24 | AN17: 40 | AO17: =AM17+AN17 -> 64 | AP17: =VLOOKUP(AO17,$B$39:$C$47,2) -> C | AR17: =AVERAGE(E17,I17,M17,Q17,U17,Y17,AC17,AG17,AK17,AO17) -> 68.5 | AS17: =RANK(AR17,$AR$5:$AR$27) -> 6 | AT17: B | AU17: B | AV17: C | AW17: C | AX17: C | AY17: Chellah, demonstrates a solid understanding of classwork and contributes well in lessons. However subjects like Science and Mathematics need more focused attention. Encouraging her to tackle more advanced challenges could further develop her skills.
A18: 14 | B18: Woods Caiden | C18: 23 | D18: 31 | E18: =C18+D18 -> 54 | F18: =VLOOKUP(E18,$B$39:$C$47,2) -> D | G18: 26 | H18: 38 | I18: =G18+H18 -> 64 | J18: =VLOOKUP(I18,$B$39:$C$47,2) -> C | K18: 28 | L18: 38 | M18: =K18+L18 -> 66 | N18: =VLOOKUP(M18,$B$39:$C$47,2) -> C | O18: 33 | P18: 33 | Q18: =O18+P18 -> 66 | R18: =VLOOKUP(Q18,$B$39:$C$47,2) -> C | S18: 27 | T18: 40 | U18: =S18+T18 -> 67 | V18: =VLOOKUP(U18,$B$39:$C$47,2) -> C | W18: 25 | X18: 37 | Y18: =W18+X18 -> 62 | Z18: =VLOOKUP(Y18,$B$39:$C$47,2) -> C | AA18: 24 | AB18: 46 | AC18: =AA18+AB18 -> 70 | AD18: =VLOOKUP(AC18,$B$39:$C$47,2) -> B | AE18: 27 | AF18: 48 | AG18: =AE18+AF18 -> 75 | AH18: =VLOOKUP(AG18,$B$39:$C$47,2) -> B | AI18: 32 | AJ18: 42 | AK18: =AI18+AJ18 -> 74 | AL18: =VLOOKUP(AK18,$B$39:$C$47,2) -> B | AM18: 28 | AN18: 37 | AO18: =AM18+AN18 -> 65 | AP18: =VLOOKUP(AO18,$B$39:$C$47,2) -> C | AR18: =AVERAGE(E18,I18,M18,Q18,U18,Y18,AC18,AG18,AK18,AO18) -> 66.3 | AS18: =RANK(AR18,$AR$5:$AR$27) -> 7 | AT18: C | AU18: C | AV18: C | AW18: D | AX18: D | AY18: Caiden, is encouraged to improve his awareness of personal space and boundaries to ensure a comfortable and inclusive environment for everyone. Although he has the potential to perform well, he must improve his concentration and develop consistent study habits. I encourage strong cooperation between home and school to help Caiden progress.
A19: 15 | B19: Simutende Themba | C19: 22 | D19: 30 | E19: =C19+D19 -> 52 | F19: =VLOOKUP(E19,$B$39:$C$47,2) -> D | G19: 22 | H19: 30 | I19: =G19+H19 -> 52 | J19: =VLOOKUP(I19,$B$39:$C$47,2) -> D | K19: 23 | L19: 25 | M19: =K19+L19 -> 48 | N19: =VLOOKUP(M19,$B$39:$C$47,2) -> E | O19: 25 | P19: 32 | Q19: =O19+P19 -> 57 | R19: =VLOOKUP(Q19,$B$39:$C$47,2) -> D | S19: 21 | T19: 15 | U19: =S19+T19 -> 36 | V19: =VLOOKUP(U19,$B$39:$C$47,2) -> F | W19: 19 | X19: 37 | Y19: =W19+X19 -> 56 | Z19: =VLOOKUP(Y19,$B$39:$C$47,2) -> D | AA19: 26 | AB19: 17 | AC19: =AA19+AB19 -> 43 | AD19: =VLOOKUP(AC19,$B$39:$C$47,2) -> E | AE19: 26 | AF19: 35 | AG19: =AE19+AF19 -> 61 | AH19: =VLOOKUP(AG19,$B$39:$C$47,2) -> C | AI19: 32 | AJ19: 43 | AK19: =AI19+AJ19 -> 75 | AL19: =VLOOKUP(AK19,$B$39:$C$47,2) -> B | AM19: 24 | AN19: 36 | AO19: =AM19+AN19 -> 60 | AP19: =VLOOKUP(AO19,$B$39:$C$47,2) -> C | AR19: =AVERAGE(E19,I19,M19,Q19,U19,Y19,AC19,AG19,AK19,AO19) -> 54 | AS19: =RANK(AR19,$AR$5:$AR$27) -> 22 | AT19: B | AU19: A | AV19: C | AW19: B | AX19: B | AY19: Themba, is working consistently and understands the material fairly well. However his academic performance requires improvement, particularly in Mathematics and Science. Increased effort and focus would help him reach higher levels of achievement.
A20: 16 | B20: Sakala Mumbilwe | C20: 21 | D20: 31 | E20: =C20+D20 -> 52 | F20: =VLOOKUP(E20,$B$39:$C$47,2) -> D | G20: 25 | H20: 31 | I20: =G20+H20 -> 56 | J20: =VLOOKUP(I20,$B$39:$C$47,2) -> D | K20: 22.5 | L20: 28 | M20: =K20+L20 -> 50.5 | N20: =VLOOKUP(M20,$B$39:$C$47,2) -> D | O20: 30 | P20: 38 | Q20: =O20+P20 -> 68 | R20: =VLOOKUP(Q20,$B$39:$C$47,2) -> C | S20: 27 | T20: 28 | U20: =S20+T20 -> 55 | V20: =VLOOKUP(U20,$B$39:$C$47,2) -> D | W20: 27 | X20: 27 | Y20: =W20+X20 -> 54 | Z20: =VLOOKUP(Y20,$B$39:$C$47,2) -> D | AA20: 25 | AB20: 35 | AC20: =AA20+AB20 -> 60 | AD20: =VLOOKUP(AC20,$B$39:$C$47,2) -> C | AE20: 24 | AF20: 46 | AG20: =AE20+AF20 -> 70 | AH20: =VLOOKUP(AG20,$B$39:$C$47,2) -> B | AI20: 30 | AJ20: 45 | AK20: =AI20+AJ20 -> 75 | AL20: =VLOOKUP(AK20,$B$39:$C$47,2) -> B | AM20: 20 | AN20: 37 | AO20: =AM20+AN20 -> 57 | AP20: =VLOOKUP(AO20,$B$39:$C$47,2) -> D | AR20: =AVERAGE(E20,I20,M20,Q20,U20,Y20,AC20,AG20,AK20,AO20) -> 59.75 | AS20: =RANK(AR20,$AR$5:$AR$27) -> 16 | AT20: C | AU20: B | AV20: C | AW20: C | AX20: C | AY20: Mumbilwe, is progressing steadily and demonstrates a fair grasp of the content. However Mathematics and Science requires additional attention. With improved engagement and motivation, he can perform even better.
A21: 17 | B21: Mhlanga Thandulenge | C21: 14 | D21: 23 | E21: =C21+D21 -> 37 | F21: =VLOOKUP(E21,$B$39:$C$47,2) -> F | G21: 14 | H21: 19 | I21: =G21+H21 -> 33 | J21: =VLOOKUP(I21,$B$39:$C$47,2) -> F | L21: 10 | M21: =K21+L21 -> 10 | N21: =VLOOKUP(M21,$B$39:$C$47,2) -> U | O21: 7 | P21: 10 | Q21: =O21+P21 -> 17 | R21: =VLOOKUP(Q21,$B$39:$C$47,2) -> U | S21: 26 | T21: 29 | U21: =S21+T21 -> 55 | V21: =VLOOKUP(U21,$B$39:$C$47,2) -> D | W21: 24 | X21: 20 | Y21: =W21+X21 -> 44 | Z21: =VLOOKUP(Y21,$B$39:$C$47,2) -> E | AA21: 12 | AB21: 22 | AC21: =AA21+AB21 -> 34 | AD21: =VLOOKUP(AC21,$B$39:$C$47,2) -> F | AE21: 29 | AF21: 38 | AG21: =AE21+AF21 -> 67 | AH21: =VLOOKUP(AG21,$B$39:$C$47,2) -> C | AI21: 14 | AJ21: 43 | AK21: =AI21+AJ21 -> 57 | AL21: =VLOOKUP(AK21,$B$39:$C$47,2) -> D | AM21: 28 | AN21: 40 | AO21: =AM21+AN21 -> 68 | AP21: =VLOOKUP(AO21,$B$39:$C$47,2) -> C | AR21: =AVERAGE(E21,I21,M21,Q21,U21,Y21,AC21,AG21,AK21,AO21) -> 42.2 | AS21: =RANK(AR21,$AR$5:$AR$27) -> 23 | AT21: D | AU21: C | AV21: D | AW21: D | AX21: D | AY21: Thandi, needs to stay more engaged and motivated in class to achieve improved outcomes. However she must improve her consistency to improve grades in most subjects. With consistent effort and continued support from home and school, she will continue progressing well.
A22: 18 | B22: Saadi Zahraa | C22: 20 | D22: 28 | E22: =C22+D22 -> 48 | F22: =VLOOKUP(E22,$B$39:$C$47,2) -> E | G22: 20 | H22: 32 | I22: =G22+H22 -> 52 | J22: =VLOOKUP(I22,$B$39:$C$47,2) -> D | K22: 25 | L22: 26 | M22: =K22+L22 -> 51 | N22: =VLOOKUP(M22,$B$39:$C$47,2) -> D | O22: 25 | P22: 21 | Q22: =O22+P22 -> 46 | R22: =VLOOKUP(Q22,$B$39:$C$47,2) -> E | S22: 19 | T22: 34 | U22: =S22+T22 -> 53 | V22: =VLOOKUP(U22,$B$39:$C$47,2) -> D | W22: 19 | X22: 30 | Y22: =W22+X22 -> 49 | Z22: =VLOOKUP(Y22,$B$39:$C$47,2) -> E | AA22: 25 | AB22: 35 | AC22: =AA22+AB22 -> 60 | AD22: =VLOOKUP(AC22,$B$39:$C$47,2) -> C | AE22: 33 | AF22: 47 | AG22: =AE22+AF22 -> 80 | AH22: =VLOOKUP(AG22,$B$39:$C$47,2) -> A | AI22: 30 | AJ22: 45 | AK22: =AI22+AJ22 -> 75 | AL22: =VLOOKUP(AK22,$B$39:$C$47,2) -> B | AM22: 20 | AN22: 39 | AO22: =AM22+AN22 -> 59 | AP22: =VLOOKUP(AO22,$B$39:$C$47,2) -> D | AR22: =AVERAGE(E22,I22,M22,Q22,U22,Y22,AC22,AG22,AK22,AO22) -> 57.3 | AS22: =RANK(AR22,$AR$5:$AR$27) -> 18 | AT22: D | AU22: C | AV22: D | AW22: D | AX22: D | AY22: Zahraa, is making steady progress and shows a reasonable understanding of the work. However her academic performance requires improvement in most subjects particularly Mathematics and Science. Greater focus and motivation will help her achieve stronger results.
A23: 19 | B23: Abdulle Abdiasis | C23: 21 | D23: 35 | E23: =C23+D23 -> 56 | F23: =VLOOKUP(E23,$B$39:$C$47,2) -> D | G23: 21 | H23: 46 | I23: =G23+H23 -> 67 | J23: =VLOOKUP(I23,$B$39:$C$47,2) -> C | K23: 30.5 | L23: 45 | M23: =K23+L23 -> 75.5 | N23: =VLOOKUP(M23,$B$39:$C$47,2) -> B | O23: 25 | P23: 34 | Q23: =O23+P23 -> 59 | R23: =VLOOKUP(Q23,$B$39:$C$47,2) -> D | S23: 27 | T23: 37 | U23: =S23+T23 -> 64 | V23: =VLOOKUP(U23,$B$39:$C$47,2) -> C | W23: 25 | X23: 45 | Y23: =W23+X23 -> 70 | Z23: =VLOOKUP(Y23,$B$39:$C$47,2) -> B | AA23: 32 | AB23: 21 | AC23: =AA23+AB23 -> 53 | AD23: =VLOOKUP(AC23,$B$39:$C$47,2) -> D | AE23: 28 | AF23: 48 | AG23: =AE23+AF23 -> 76 | AH23: =VLOOKUP(AG23,$B$39:$C$47,2) -> B | AI23: 32 | AJ23: 48 | AK23: =AI23+AJ23 -> 80 | AL23: =VLOOKUP(AK23,$B$39:$C$47,2) -> A | AM23: 20 | AN23: 40 | AO23: =AM23+AN23 -> 60 | AP23: =VLOOKUP(AO23,$B$39:$C$47,2) -> C | AR23: =AVERAGE(E23,I23,M23,Q23,U23,Y23,AC23,AG23,AK23,AO23) -> 66.05 | AS23: =RANK(AR23,$AR$5:$AR$27) -> 8 | AT23: C | AU23: C | AV23: D | AW23: C | AX23: C | AY23: Abdiasis, works steadily and shows a fair understanding of the work. With increased focus, he has the potential to improve further. I encourage him to participate more actively so he can fully benefit from collaboration learning.
A24: 20 | B24: Bath Iman | C24: 21 | D24: 40 | E24: =C24+D24 -> 61 | F24: =VLOOKUP(E24,$B$39:$C$47,2) -> C | G24: 16 | H24: 30 | I24: =G24+H24 -> 46 | J24: =VLOOKUP(I24,$B$39:$C$47,2) -> E | K24: 20.5 | L24: 20 | M24: =K24+L24 -> 40.5 | N24: =VLOOKUP(M24,$B$39:$C$47,2) -> E | O24: 26 | P24: 31 | Q24: =O24+P24 -> 57 | R24: =VLOOKUP(Q24,$B$39:$C$47,2) -> D | S24: 23 | T24: 43 | U24: =S24+T24 -> 66 | V24: =VLOOKUP(U24,$B$39:$C$47,2) -> C | W24: 30 | X24: 50 | Y24: =W24+X24 -> 80 | Z24: =VLOOKUP(Y24,$B$39:$C$47,2) -> A | AA24: 29 | AB24: 35 | AC24: =AA24+AB24 -> 64 | AD24: =VLOOKUP(AC24,$B$39:$C$47,2) -> C | AE24: 28 | AF24: 42 | AG24: =AE24+AF24 -> 70 | AH24: =VLOOKUP(AG24,$B$39:$C$47,2) -> B | AI24: 37 | AJ24: 47 | AK24: =AI24+AJ24 -> 84 | AL24: =VLOOKUP(AK24,$B$39:$C$47,2) -> A | AM24: 20 | AN24: 41 | AO24: =AM24+AN24 -> 61 | AP24: =VLOOKUP(AO24,$B$39:$C$47,2) -> C | AR24: =AVERAGE(E24,I24,M24,Q24,U24,Y24,AC24,AG24,AK24,AO24) -> 62.95 | AS24: =RANK(AR24,$AR$5:$AR$27) -> 13 | AT24: C | AU24: C | AV24: D | AW24: D | AX24: D | AY24: Iman should continue developing self-regulation and maintaining focus during lessons to make the most of her learning opportunities. Although she has potential to perform well, she still needs focused efforts. Close collaboration between home and school will help her unlock her potential.
A25: 21 | B25: Chunga Nomasizwe | C25: 26 | D25: 34 | E25: =C25+D25 -> 60 | F25: =VLOOKUP(E25,$B$39:$C$47,2) -> C | G25: 13 | H25: 17 | I25: =G25+H25 -> 30 | J25: =VLOOKUP(I25,$B$39:$C$47,2) -> F | K25: 0 | L25: 36 | M25: =K25+L25 -> 36 | N25: =VLOOKUP(M25,$B$39:$C$47,2) -> F | O25: 33 | P25: 26 | Q25: =O25+P25 -> 59 | R25: =VLOOKUP(Q25,$B$39:$C$47,2) -> D | S25: 26 | T25: 25 | U25: =S25+T25 -> 51 | V25: =VLOOKUP(U25,$B$39:$C$47,2) -> D | W25: 33 | X25: 34 | Y25: =W25+X25 -> 67 | Z25: =VLOOKUP(Y25,$B$39:$C$47,2) -> C | AA25: 30 | AB25: 26 | AC25: =AA25+AB25 -> 56 | AD25: =VLOOKUP(AC25,$B$39:$C$47,2) -> D | AE25: 34 | AF25: 44 | AG25: =AE25+AF25 -> 78 | AH25: =VLOOKUP(AG25,$B$39:$C$47,2) -> B | AI25: 31 | AJ25: 47 | AK25: =AI25+AJ25 -> 78 | AL25: =VLOOKUP(AK25,$B$39:$C$47,2) -> B | AM25: 20 | AN25: 42 | AO25: =AM25+AN25 -> 62 | AP25: =VLOOKUP(AO25,$B$39:$C$47,2) -> C | AR25: =AVERAGE(E25,I25,M25,Q25,U25,Y25,AC25,AG25,AK25,AO25) -> 57.7 | AS25: =RANK(AR25,$AR$5:$AR$27) -> 17 | AT25: C | AU25: B | AV25: C | AW25: C | AX25: C | AY25: Nomasizwe, should continue developing self-regulation and maintaining focus during lessons to make the most of her learning opportunities. Despite her good behaviour she needs to put more efforts into her academic work, particularly Mathematics and science. She must develop stronger study habits and complete assignments more thoroughly. Close collaboration between home and school will help her unlock her potential.
A26: 22 | B26: Mulenga Katlego | C26: 24 | D26: 31 | E26: =C26+D26 -> 55 | F26: =VLOOKUP(E26,$B$39:$C$47,2) -> D | G26: 18 | H26: 23 | I26: =G26+H26 -> 41 | J26: =VLOOKUP(I26,$B$39:$C$47,2) -> E | K26: 32.5 | L26: 40 | M26: =K26+L26 -> 72.5 | N26: =VLOOKUP(M26,$B$39:$C$47,2) -> B | O26: 26 | P26: 38 | Q26: =O26+P26 -> 64 | R26: =VLOOKUP(Q26,$B$39:$C$47,2) -> C | S26: 30 | T26: 33 | U26: =S26+T26 -> 63 | V26: =VLOOKUP(U26,$B$39:$C$47,2) -> C | W26: 24 | X26: 40 | Y26: =W26+X26 -> 64 | Z26: =VLOOKUP(Y26,$B$39:$C$47,2) -> C | AA26: 30 | AB26: 43 | AC26: =AA26+AB26 -> 73 | AD26: =VLOOKUP(AC26,$B$39:$C$47,2) -> B | AE26: 29 | AF26: 47 | AG26: =AE26+AF26 -> 76 | AH26: =VLOOKUP(AG26,$B$39:$C$47,2) -> B | AI26: 35 | AJ26: 43 | AK26: =AI26+AJ26 -> 78 | AL26: =VLOOKUP(AK26,$B$39:$C$47,2) -> B | AM26: 24 | AN26: 41 | AO26: =AM26+AN26 -> 65 | AP26: =VLOOKUP(AO26,$B$39:$C$47,2) -> C | AR26: =AVERAGE(E26,I26,M26,Q26,U26,Y26,AC26,AG26,AK26,AO26) -> 65.15 | AS26: =RANK(AR26,$AR$5:$AR$27) -> 9 | AT26: B | AU26: C | AV26: C | AW26: D | AX26: D | AY26: Katlego, is an energetic and friendly learner who enjoys interacting with peers. Although he has the potential to perform well, his distractibility affects the quality of his work. He must improve his concentration and develop study habits. Mathemtics especially require additional support. I recommend structured revision, limited distractions at home and regular teacher-parent follow-ups.
A27: 23 | B27: Sampa Asher | C27: 22 | D27: 42 | E27: =C27+D27 -> 64 | F27: =VLOOKUP(E27,$B$39:$C$47,2) -> C | G27: 30 | H27: 32 | I27: =G27+H27 -> 62 | J27: =VLOOKUP(I27,$B$39:$C$47,2) -> C | K27: 32.5 | L27: 46 | M27: =K27+L27 -> 78.5 | N27: =VLOOKUP(M27,$B$39:$C$47,2) -> B | O27: 31 | P27: 33 | Q27: =O27+P27 -> 64 | R27: =VLOOKUP(Q27,$B$39:$C$47,2) -> C | S27: 33 | T27: 48 | U27: =S27+T27 -> 81 | V27: =VLOOKUP(U27,$B$39:$C$47,2) -> A | W27: 33 | X27: 49 | Y27: =W27+X27 -> 82 | Z27: =VLOOKUP(Y27,$B$39:$C$47,2) -> A | AA27: 24 | AB27: 39 | AC27: =AA27+AB27 -> 63 | AD27: =VLOOKUP(AC27,$B$39:$C$47,2) -> C | AE27: 35 | AF27: 58 | AG27: =AE27+AF27 -> 93 | AH27: =VLOOKUP(AG27,$B$39:$C$47,2) -> A* | AI27: 31 | AJ27: 53 | AK27: =AI27+AJ27 -> 84 | AL27: =VLOOKUP(AK27,$B$39:$C$47,2) -> A | AM27: 40 | AN27: 41 | AO27: =AM27+AN27 -> 81 | AP27: =VLOOKUP(AO27,$B$39:$C$47,2) -> A | AR27: =AVERAGE(E27,I27,M27,Q27,U27,Y27,AC27,AG27,AK27,AO27) -> 75.25 | AS27: =RANK(AR27,$AR$5:$AR$27) -> 4 | AT27: A | AU27: B | AV27: B | AW27: C | AX27: B | AY27: Asher, is a well behaved and responsible learner who consistently demonstrates a positive attitude. He participates actively an works well with his peers. His performance this term has been steady, with particular strengths in Mathematics and science. With continued support, Asher has the potential to excel across all subjects.
B31: Average | E31: =AVERAGE(E5:E27) -> 55.26087 | I31: =AVERAGE(I5:I27) -> 54.391304 | M31: =AVERAGE(M5:M27) -> 56.430435 | Q31: =AVERAGE(Q5:Q27) -> 60.043478 | U31: =AVERAGE(U5:U27) -> 62.913043 | Y31: =AVERAGE(Y5:Y27) -> 66.869565 | AC31: =AVERAGE(AC5:AC27) -> 64.478261 | AG31: =AVERAGE(AG5:AG27) -> 73.869565 | AK31: =AVERAGE(AK5:AK27) -> 78.565217 | AO31: =AVERAGE(AO5:AO27) -> 61.478261
B32: NO. Students | E32: =COUNT(E5:E27) -> 23 | I32: =COUNT(I5:I27) -> 23 | M32: =COUNT(M5:M27) -> 23 | Q32: =COUNT(Q5:Q27) -> 23 | U32: =COUNT(U5:U27) -> 23 | Y32: =COUNT(Y5:Y27) -> 23 | AC32: =COUNT(AC5:AC27) -> 23 | AG32: =COUNT(AG5:AG27) -> 23 | AK32: =COUNT(AK5:AK27) -> 23 | AO32: =COUNT(AO5:AO27) -> 23
B33: Pass | E33: =COUNTIF(E5:E27,">49") -> 17 | I33: =COUNTIF(I5:I27,">49") -> 15 | M33: =COUNTIF(M5:M27,">49") -> 17 | Q33: =COUNTIF(Q5:Q27,">49") -> 20 | U33: =COUNTIF(U5:U27,">49") -> 21 | Y33: =COUNTIF(Y5:Y27,">49") -> 20 | AC33: =COUNTIF(AC5:AC27,">49") -> 19 | AG33: =COUNTIF(AG5:AG27,">49") -> 23 | AK33: =COUNTIF(AK5:AK27,">49") -> 23 | AO33: =COUNTIF(AO5:AO27,">49") -> 21
B34: Fail | E34: =COUNTIF(E5:E27,"<50") -> 6 | I34: =COUNTIF(I5:I27,"<50") -> 8 | M34: =COUNTIF(M5:M27,"<50") -> 6 | Q34: =COUNTIF(Q5:Q27,"<50") -> 3 | U34: =COUNTIF(U5:U27,"<50") -> 2 | Y34: =COUNTIF(Y5:Y27,"<50") -> 3 | AC34: =COUNTIF(AC5:AC27,"<50") -> 4 | AG34: =COUNTIF(AG5:AG27,"<50") -> 0 | AK34: =COUNTIF(AK5:AK27,"<50") -> 0 | AO34: =COUNTIF(AO5:AO27,"<50") -> 2
B35: Pass Rate % | E35: =E33*100/E32 -> 73.913043 | I35: =I33*100/I32 -> 65.217391 | M35: =M33*100/M32 -> 73.913043 | Q35: =Q33*100/Q32 -> 86.956522 | U35: =U33*100/U32 -> 91.304348 | Y35: =Y33*100/Y32 -> 86.956522 | AC35: =AC33*100/AC32 -> 82.608696 | AG35: =AG33*100/AG32 -> 100 | AK35: =AK33*100/AK32 -> 100 | AO35: =AO33*100/AO32 -> 91.304348
A39: 00-19 | B39: 0 | C39: U
A40: 20-29 | B40: 20 | C40: G
A41: 30-39 | B41: 30 | C41: F
A42: 40-49 | B42: 40 | C42: E
A43: 50-59 | B43: 50 | C43: D
A44: 60-69 | B44: 60 | C44: C
A45: 70-79 | B45: 70 | C45: B
A46: 80-89 | B46: 80 | C46: A
A47: 90-100 | B47: 90 | C47: A*

Sheet LS3B
A1: HOME
A3: Roll N0. | B3: Name | C3: English | G3: Mathematics | K3: Science | O3: Global Pesperctive | S3: New Computing | W3: Business Studies | AA3: French | AE3: Art | AI3: MDD | AM3: PE | AR3: AVERAGE | AS3: POSITION | AT3: CREATIVITY | AU3: RESPECT | AV3: EXCELLENCE | AW3: EMPATHY | AX3: DISCIPLINE | AY3: CLASS TEACHER'S COMMENT
C4: Formative | D4: Summative | E4: Final Mark | F4: Grade | G4: Formative | H4: Summative | I4: Final Mark | J4: Grade | K4: Formative | L4: Summative | M4: Final Mark | N4: Grade | O4: Formative | P4: Summative | Q4: Final Mark | R4: Grade | S4: Formative | T4: Summative | U4: Final Mark | V4: Grade | W4: Formative | X4: Summative | Y4: Final Mark | Z4: Grade | AA4: Formative | AB4: Summative | AC4: Final Mark | AD4: Grade | AE4: Formative | AF4: Summative | AG4: Final Mark | AH4: Grade | AI4: Formative | AJ4: Summative | AK4: Final Mark | AL4: Grade | AM4: Formative | AN4: Summative | AO4: Final Mark | AP4: Grade
A6: 1 | B6: SIAME SALIFYANJI | C6: 26 | D6: 38 | E6: =C6+D6 -> 64 | F6: =VLOOKUP(E6,$B$44:$C$52,2) -> C | G6: 28 | H6: 34 | I6: =G6+H6 -> 62 | J6: =VLOOKUP(I6,$B$44:$C$52,2) -> C | K6: 35 | L6: 45 | M6: =K6+L6 -> 80 | N6: =VLOOKUP(M6,$B$44:$C$52,2) -> A | O6: 33 | P6: 50 | Q6: =O6+P6 -> 83 | R6: =VLOOKUP(Q6,$B$44:$C$52,2) -> A | S6: 28 | T6: 42 | U6: =S6+T6 -> 70 | V6: =VLOOKUP(U6,$B$44:$C$52,2) -> B | W6: 35 | X6: 50 | Y6: =W6+X6 -> 85 | Z6: =VLOOKUP(Y6,$B$44:$C$52,2) -> A | AA6: 39 | AB6: 44 | AC6: =AA6+AB6 -> 83 | AD6: =VLOOKUP(AC6,$B$44:$C$52,2) -> A | AE6: 34 | AF6: 48 | AG6: =AE6+AF6 -> 82 | AH6: =VLOOKUP(AG6,$B$44:$C$52,2) -> A | AI6: 24 | AJ6: 43 | AK6: =AI6+AJ6 -> 67 | AL6: =VLOOKUP(AK6,$B$44:$C$52,2) -> C | AM6: 26 | AN6: 51 | AO6: =AM6+AN6 -> 77 | AP6: =VLOOKUP(AO6,$B$44:$C$52,2) -> B | AR6: =AVERAGE(E6,I6,M6,Q6,U6,Y6,AC6,AG6,AK6,AO6) -> 75.3 | AS6: =RANK(AR6,$AR$6:$AR$27) -> 3 | AT6: A | AU6: A | AV6: A | AW6: A | AX6: A | AY6: Salifyanji is a gentle, respectful, and well-organized student who takes pride in her appearance and her work. She performs well academically, especially in areas like Science, but sometimes settles for less than she is capable of in subjects such as Mathematics. With a little more confidence, higher personal goals, and steady practice, she can achieve even more. I encourage her to ask questions freely whenever she needs support.
A7: 2 | B7: Chokr Aya | C7: 16 | D7: 26 | E7: =C7+D7 -> 42 | F7: =VLOOKUP(E7,$B$44:$C$52,2) -> E | G7: 7 | H7: 15 | I7: =G7+H7 -> 22 | J7: =VLOOKUP(I7,$B$44:$C$52,2) -> G | K7: 25.5 | L7: 16 | M7: =K7+L7 -> 41.5 | N7: =VLOOKUP(M7,$B$44:$C$52,2) -> E | O7: 20 | P7: 31 | Q7: =O7+P7 -> 51 | R7: =VLOOKUP(Q7,$B$44:$C$52,2) -> D | S7: 17 | T7: 28 | U7: =S7+T7 -> 45 | V7: =VLOOKUP(U7,$B$44:$C$52,2) -> E | W7: 10 | X7: 15 | Y7: =W7+X7 -> 25 | Z7: =VLOOKUP(Y7,$B$44:$C$52,2) -> G | AA7: 21 | AB7: 27 | AC7: 48 | AD7: =VLOOKUP(AC7,$B$44:$C$52,2) -> E | AE7: 27 | AF7: 35 | AG7: =AE7+AF7 -> 62 | AH7: =VLOOKUP(AG7,$B$44:$C$52,2) -> C | AI7: 26 | AJ7: 38 | AK7: =AI7+AJ7 -> 64 | AL7: =VLOOKUP(AK7,$B$44:$C$52,2) -> C | AM7: 16 | AN7: 39 | AO7: =AM7+AN7 -> 55 | AP7: =VLOOKUP(AO7,$B$44:$C$52,2) -> D | AR7: =AVERAGE(E7,I7,M7,Q7,U7,Y7,AC7,AG7,AK7,AO7) -> 45.55 | AS7: =RANK(AR7,$AR$6:$AR$27) -> 20 | AT7: B | AU7: A | AV7: B | AW7: B | AX7: B | AY7: Aya is respectful, punctual, and responsible in her class behaviour. She is a quiet learner who can be hesitant to ask for help, which affects her progress in some subjects like Mathematics and Science. With improved study habits, better use of her free time, and regular attendance in support sessions, she will grow stronger and more confident in her learning.
A8: 3 | B8: Saad Karim | C8: 20 | D8: 37 | E8: =C8+D8 -> 57 | F8: =VLOOKUP(E8,$B$44:$C$52,2) -> D | G8: 27 | H8: 29 | I8: =G8+H8 -> 56 | J8: =VLOOKUP(I8,$B$44:$C$52,2) -> D | K8: 28 | L8: 30 | M8: =K8+L8 -> 58 | N8: =VLOOKUP(M8,$B$44:$C$52,2) -> D | O8: 28 | P8: 33 | Q8: =O8+P8 -> 61 | R8: =VLOOKUP(Q8,$B$44:$C$52,2) -> C | S8: 20 | T8: 22 | U8: =S8+T8 -> 42 | V8: =VLOOKUP(U8,$B$44:$C$52,2) -> E | W8: 25 | X8: 44 | Y8: =W8+X8 -> 69 | Z8: =VLOOKUP(Y8,$B$44:$C$52,2) -> C | AA8: 27 | AB8: 24 | AC8: =AA8+AB8 -> 51 | AD8: =VLOOKUP(AC8,$B$44:$C$52,2) -> D | AE8: 29 | AF8: 39 | AG8: =AE8+AF8 -> 68 | AH8: =VLOOKUP(AG8,$B$44:$C$52,2) -> C | AI8: 16 | AJ8: 39 | AK8: =AI8+AJ8 -> 55 | AL8: =VLOOKUP(AK8,$B$44:$C$52,2) -> D | AM8: 20 | AN8: 52 | AO8: =AM8+AN8 -> 72 | AP8: =VLOOKUP(AO8,$B$44:$C$52,2) -> B | AR8: =AVERAGE(E8,I8,M8,Q8,U8,Y8,AC8,AG8,AK8,AO8) -> 58.9 | AS8: =RANK(AR8,$AR$6:$AR$27) -> 12 | AT8: B | AU8: A | AV8: B | AW8: B | AX8: B | AY8: Karim is energetic, honest, and expresses himself well when he needs clarification. His enthusiasm is a strength, but sometimes struggles with settling down and following school expectations, which interrupts his learning. With improved discipline, consistency, and focus, Saad can channel his energy positively and see great improvement across all his subjects.
